Workbook
Name Slicer_Date: #N/A
Name Slicer_Date1: #N/A
Name Slicer_Party: #N/A
Name Slicer_Party_Name: #N/A
Name Slicer_Party_Name1: #N/A
Name Slicer_Party_Name2: #N/A
Name Slicer_Person: #N/A
Name Slicer_Shipment_Number: #N/A

Sheet Billing
B1: Party Name | C1: Tiyaar | D1: Rate | E1: Total | G1: Billing
B2: =B49 -> BSC | C2: =SUMIFS(ledger!G:G, ledger!B:B, B2, ledger!E:E, "<>*RD*") / 1.0936 -> 830695.87 | D2: 10 | E2: =(SUMIFS(ledger!G:G, ledger!B:B, B2, ledger!E:E, "<>*RD*",ledger!D:D, "Silky") / 1.0936)*12 + (SUMIFS(ledger!G:G, ledger!B:B, B2, ledger!E:E, "<>*RD*",ledger!D:D, "Chamki") / 1.0936)*10 -> 5987757.9 | I2: BSC | R2: Billing Total
B3: =B50 -> Ejaz Sahab | C3: =SUMIFS(ledger!G:G, ledger!B:B, B3, ledger!E:E, "<>*RD*") / 1.0936 -> 83720.739 | D3: 10 | E3: =(SUMIFS(ledger!G:G, ledger!B:B, B3, ledger!E:E, "<>*RD*",ledger!D:D, "Silky") / 1.0936)*12 + (SUMIFS(ledger!G:G, ledger!B:B, B3, ledger!E:E, "<>*RD*",ledger!D:D, "Chamki") / 1.0936)*10 -> 1004648.9 | I3: Ejaz Sahab
B4: =B51 -> Arshad | C4: =SUMIFS(ledger!G:G, ledger!B:B, B4, ledger!E:E, "<>*RD*") / 1.0936 -> 115056.69 | D4: 10 | E4: =(SUMIFS(ledger!G:G, ledger!B:B, B4, ledger!E:E, "<>*RD*",ledger!D:D, "Silky") / 1.0936)*12 + (SUMIFS(ledger!G:G, ledger!B:B, B4, ledger!E:E, "<>*RD*",ledger!D:D, "Chamki") / 1.0936)*10 -> 1189264.8 | I4: Arshad | S4: Gaz | T4: Total Metres | U4: Total Chamki | V4: Total Super Silky | W4: Billing (Chamki/Crinkle) | X4: Billing (Super Chamki) | Y4: Billing (Slub) | Z4: Billing (Satin) | AA4: Billing (Black-chamki) | AB4: Billing (Kataan) | AC4: Billing (Munaar) | AD4: Billing (Custom) | AE4: Adjusted Bill | AF4: Amount Paid | AG4: Balance | AH4: Rate (Chamki) | AI4: Rate (Super Silky)
B5: =B52 -> Shehzad Kamoki | C5: =SUMIFS(ledger!G:G, ledger!B:B, B5, ledger!E:E, "<>*RD*") / 1.0936 -> 0 | D5: 10.5 | E5: =(SUMIFS(ledger!G:G, ledger!B:B, B5, ledger!E:E, "<>*RD*",ledger!D:D, "Silky") / 1.0936)*12 + (SUMIFS(ledger!G:G, ledger!B:B, B5, ledger!E:E, "<>*RD*",ledger!D:D, "Chamki") / 1.0936)*10.5 -> 0 | I5: Shehzad Kamoki | R5: {=_xlfn.UNIQUE(Table1[Party Name])} -> BSC | S5: {=_xlfn.BYROW(B49,_xlfn.LAMBDA(_xlpm.party,SUMIFS(ledger!G:G,ledger!B:B,_xlpm.party,ledger!E:E,"<>*RD*")))+_xlfn.IFNA(C98,0)} -> 4561215.9 | T5: {=_xlfn.BYROW(B49, _xlfn.LAMBDA(_xlpm.party, SUMIFS(ledger!G:G, ledger!B:B, _xlpm.party, ledger!E:E, "<>*RD*") / 1.0936 ))+_xlfn.IFNA(D98,0)} -> 4170826.5 | U5: {=(_xlfn.BYROW(B49,_xlfn.LAMBDA(_xlpm.party,SUMIFS(ledger!G:G,ledger!B:B,_xlpm.party,ledger!E:E,"<>*RD*",ledger!D:D,"Chamki")+SUMIFS(ledger!G:G, ledger!B:B, _xlpm.party, ledger!E:E, "<>*RD*", ledger!D:D, "Crinkle")))/1.0936)+_xlfn.IFNA(E98,0)} -> 3220573.2 | V5: {=(_xlfn.BYROW(B49,_xlfn.LAMBDA(_xlpm.party,SUMIFS(ledger!G:G,ledger!B:B,_xlpm.party,ledger!E:E,"<>*RD*",ledger!D:D,"Silky")))/1.0936)+_xlfn.IFNA(F98,0)} -> 756880.94 | W5: {=(_xlfn.BYROW(B49,_xlfn.LAMBDA(_xlpm.party, (SUMIFS(ledger!J:J,ledger!B:B,_xlpm.party,ledger!E:E,"<>*RD*",ledger!D:D,"Chamki",ledger!C:C,"<>January Closing CF")+ SUMIFS(ledger!J:J,ledger!B:B,_xlpm.party,ledger!E:E,"<>*RD*",ledger!D:D,"Crinkle",ledger!C:C,"<>January Closing CF") )+_xlfn.IFNA(G98,0))))} -> 32205732 | X5: {=_xlfn.BYROW(B49, _xlfn.LAMBDA(_xlpm.party, SUMIFS(ledger!J:J, ledger!B:B, _xlpm.party, ledger!E:E, "<>*RD*", ledger!D:D, "Silky", ledger!C:C, "<>January Closing CF") )) + _xlfn.IFNA(H98, 0)} -> 9751096.4 | Y5: {=_xlfn.BYROW(B49, _xlfn.LAMBDA(_xlpm.party, SUMIFS(ledger!J:J, ledger!B:B, _xlpm.party, ledger!E:E, "<>*RD*", ledger!D:D, "Slub", ledger!C:C, "<>January Closing CF") ))+ _xlfn.IFNA(I98, 0)} -> 0 | Z5: {=_xlfn.BYROW(B49, _xlfn.LAMBDA(_xlpm.party, SUMIFS(ledger!J:J, ledger!B:B, _xlpm.party, ledger!E:E, "<>*RD*", ledger!D:D, "Satin", ledger!C:C, "<>January Closing CF") ))+ _xlfn.IFNA(J98, 0)} -> 0 | AA5: {=_xlfn.BYROW(B49, _xlfn.LAMBDA(_xlpm.party, SUMIFS(ledger!J:J, ledger!B:B, _xlpm.party, ledger!E:E, "<>*RD*", ledger!D:D, "Black-Chamki", ledger!C:C, "<>January Closing CF") ))+ _xlfn.IFNA(K98, 0)} -> 0 | AB5: {=_xlfn.BYROW(B49, _xlfn.LAMBDA(_xlpm.party, SUMIFS(ledger!J:J, ledger!B:B, _xlpm.party, ledger!E:E, "<>*RD*", ledger!D:D, "Kataan", ledger!C:C, "<>January Closing CF") ))+ _xlfn.IFNA(L98, 0)} -> 2127095.8 | AC5: {=_xlfn.BYROW(B49, _xlfn.LAMBDA(_xlpm.party, SUMIFS(ledger!J:J, ledger!B:B, _xlpm.party, ledger!E:E, "<>*RD*", ledger!D:D, "Munaar", ledger!C:C, "<>January Closing CF") ))+ _xlfn.IFNA(M98, 0)} -> 0 | AD5: {=_xlfn.BYROW(B49, _xlfn.LAMBDA(_xlpm.party, SUMIFS(ledger!J:J, ledger!B:B, _xlpm.party, ledger!E:E, "<>*RD*", ledger!D:D, "Custom", ledger!C:C, "<>January Closing CF") ))+ _xlfn.IFNA(N98, 0)} -> 0 | AE5: =W5+X5+Y5+Z5+AA5+AB5+AC5+AD5 -> 44083924 | AF5: =(SUMIF(Table14[Party],#REF!,Table14[Credit]))+_xlfn.IFNA(P98,0) -> 19750734 | AG5: =AE5-AF5 -> 24333190 | AH5: 10 | AI5: 13
B6: =B53 -> Sufi Nawaz Sahab | C6: =SUMIFS(ledger!G:G, ledger!B:B, B6, ledger!E:E, "<>*RD*") / 1.0936 -> 0 | D6: 10 | E6: =((SUMIFS(ledger!G:G, ledger!B:B, B6, ledger!E:E, "<>*RD*",ledger!D:D, "Silky") / 1.0936) *12) + ((SUMIFS(ledger!G:G, ledger!B:B, B6, ledger!E:E, "<>*RD*",ledger!D:D, "Chamki") / 1.0936)* 9) -> 0 | I6: Sufi Nawaz Sahab | R6: Ejaz Sahab | S6: {=_xlfn.BYROW(B50,_xlfn.LAMBDA(_xlpm.party,SUMIFS(ledger!G:G,ledger!B:B,_xlpm.party,ledger!E:E,"<>*RD*")))+_xlfn.IFNA(C99,0)} -> 672036 | T6: {=_xlfn.BYROW(B50, _xlfn.LAMBDA(_xlpm.party, SUMIFS(ledger!G:G, ledger!B:B, _xlpm.party, ledger!E:E, "<>*RD*") / 1.0936 ))+_xlfn.IFNA(D99,0)} -> 614517.19 | U6: {=(_xlfn.BYROW(B50,_xlfn.LAMBDA(_xlpm.party,SUMIFS(ledger!G:G,ledger!B:B,_xlpm.party,ledger!E:E,"<>*RD*",ledger!D:D,"Chamki")+SUMIFS(ledger!G:G, ledger!B:B, _xlpm.party, ledger!E:E, "<>*RD*", ledger!D:D, "Crinkle")))/1.0936)+_xlfn.IFNA(E99,0)} -> 148145.57 | V6: {=(_xlfn.BYROW(B50,_xlfn.LAMBDA(_xlpm.party,SUMIFS(ledger!G:G,ledger!B:B,_xlpm.party,ledger!E:E,"<>*RD*",ledger!D:D,"Silky")))/1.0936)+_xlfn.IFNA(F99,0)} -> 466371.62 | W6: {=(_xlfn.BYROW(B50,_xlfn.LAMBDA(_xlpm.party, (SUMIFS(ledger!J:J,ledger!B:B,_xlpm.party,ledger!E:E,"<>*RD*",ledger!D:D,"Chamki",ledger!C:C,"<>January Closing CF")+ SUMIFS(ledger!J:J,ledger!B:B,_xlpm.party,ledger!E:E,"<>*RD*",ledger!D:D,"Crinkle",ledger!C:C,"<>January Closing CF") )+_xlfn.IFNA(G99,0))))} -> 1481455.7 | X6: {=_xlfn.BYROW(B50, _xlfn.LAMBDA(_xlpm.party, SUMIFS(ledger!J:J, ledger!B:B, _xlpm.party, ledger!E:E, "<>*RD*", ledger!D:D, "Silky", ledger!C:C, "<>January Closing CF") )) + _xlfn.IFNA(H99, 0)} -> 6003686.9 | Y6: {=_xlfn.BYROW(B50, _xlfn.LAMBDA(_xlpm.party, SUMIFS(ledger!J:J, ledger!B:B, _xlpm.party, ledger!E:E, "<>*RD*", ledger!D:D, "Slub", ledger!C:C, "<>January Closing CF") ))+ _xlfn.IFNA(I99, 0)} -> 0 | Z6: {=_xlfn.BYROW(B50, _xlfn.LAMBDA(_xlpm.party, SUMIFS(ledger!J:J, ledger!B:B, _xlpm.party, ledger!E:E, "<>*RD*", ledger!D:D, "Satin", ledger!C:C, "<>January Closing CF") ))+ _xlfn.IFNA(J99, 0)} -> 0 | AA6: {=_xlfn.BYROW(B50, _xlfn.LAMBDA(_xlpm.party, SUMIFS(ledger!J:J, ledger!B:B, _xlpm.party, ledger!E:E, "<>*RD*", ledger!D:D, "Black-Chamki", ledger!C:C, "<>January Closing CF") ))+ _xlfn.IFNA(K99, 0)} -> 0 | AB6: {=_xlfn.BYROW(B50, _xlfn.LAMBDA(_xlpm.party, SUMIFS(ledger!J:J, ledger!B:B, _xlpm.party, ledger!E:E, "<>*RD*", ledger!D:D, "Kataan", ledger!C:C, "<>January Closing CF") ))+ _xlfn.IFNA(L99, 0)} -> 0 | AC6: {=_xlfn.BYROW(B50, _xlfn.LAMBDA(_xlpm.party, SUMIFS(ledger!J:J, ledger!B:B, _xlpm.party, ledger!E:E, "<>*RD*", ledger!D:D, "Munaar", ledger!C:C, "<>January Closing CF") ))+ _xlfn.IFNA(M99, 0)} -> 0 | AD6: {=_xlfn.BYROW(B50, _xlfn.LAMBDA(_xlpm.party, SUMIFS(ledger!J:J, ledger!B:B, _xlpm.party, ledger!E:E, "<>*RD*", ledger!D:D, "Custom", ledger!C:C, "<>January Closing CF") ))+ _xlfn.IFNA(N99, 0)} -> 0 | AE6: =W6+X6+Y6+Z6+AA6+AB6+AC6+AD6 -> 7485142.6 | AF6: =(SUMIF(Table14[Party],R6,Table14[Credit]))+_xlfn.IFNA(P99,0) -> 7214622 | AG6: =AE6-AF6 -> 270520.65 | AH6: 10 | AI6: 13
B7: =B54 -> Sajad Khan | C7: =SUMIFS(ledger!G:G, ledger!B:B, B7, ledger!E:E, "<>*RD*") / 1.0936 -> 63240.673 | D7: 10 | E7: {=(SUMIFS(ledger!G:G, ledger!B:B, B7, ledger!E:E, "<>*RD*",ledger!D:D, "Silky") / 1.0936)*12 + (SUMIFS(ledger!G:G, ledger!B:B, B7, ledger!E:E, "<>*RD*",ledger!D:D, "Chamki") / 1.0936)*10 +(SUMIFS(ledger!G:G, ledger!B:B, party, ledger!E:E, "<>*RD*", ledger!D:D, "Crinkle")/ 1.0936)*10} -> 632406.73 | I7: Sajad Khan | R7: Arshad | S7: {=_xlfn.BYROW(B51,_xlfn.LAMBDA(_xlpm.party,SUMIFS(ledger!G:G,ledger!B:B,_xlpm.party,ledger!E:E,"<>*RD*")))+_xlfn.IFNA(C100,0)} -> 1020419 | T7: {=_xlfn.BYROW(B51, _xlfn.LAMBDA(_xlpm.party, SUMIFS(ledger!G:G, ledger!B:B, _xlpm.party, ledger!E:E, "<>*RD*") / 1.0936 ))+_xlfn.IFNA(D100,0)} -> 933082.48 | U7: {=(_xlfn.BYROW(B51,_xlfn.LAMBDA(_xlpm.party,SUMIFS(ledger!G:G,ledger!B:B,_xlpm.party,ledger!E:E,"<>*RD*",ledger!D:D,"Chamki")+SUMIFS(ledger!G:G, ledger!B:B, _xlpm.party, ledger!E:E, "<>*RD*", ledger!D:D, "Crinkle")))/1.0936)+_xlfn.IFNA(E100,0)} -> 767556.69 | V7: {=(_xlfn.BYROW(B51,_xlfn.LAMBDA(_xlpm.party,SUMIFS(ledger!G:G,ledger!B:B,_xlpm.party,ledger!E:E,"<>*RD*",ledger!D:D,"Silky")))/1.0936)+_xlfn.IFNA(F100,0)} -> 165525.79 | W7: {=(_xlfn.BYROW(B51,_xlfn.LAMBDA(_xlpm.party, (SUMIFS(ledger!J:J,ledger!B:B,_xlpm.party,ledger!E:E,"<>*RD*",ledger!D:D,"Chamki",ledger!C:C,"<>January Closing CF")+ SUMIFS(ledger!J:J,ledger!B:B,_xlpm.party,ledger!E:E,"<>*RD*",ledger!D:D,"Crinkle",ledger!C:C,"<>January Closing CF") )+_xlfn.IFNA(G100,0))))} -> 7675566.9 | X7: {=_xlfn.BYROW(B51, _xlfn.LAMBDA(_xlpm.party, SUMIFS(ledger!J:J, ledger!B:B, _xlpm.party, ledger!E:E, "<>*RD*", ledger!D:D, "Silky", ledger!C:C, "<>January Closing CF") )) + _xlfn.IFNA(H100, 0)} -> 2137041 | Y7: {=_xlfn.BYROW(B51, _xlfn.LAMBDA(_xlpm.party, SUMIFS(ledger!J:J, ledger!B:B, _xlpm.party, ledger!E:E, "<>*RD*", ledger!D:D, "Slub", ledger!C:C, "<>January Closing CF") ))+ _xlfn.IFNA(I100, 0)} -> 0 | Z7: {=_xlfn.BYROW(B51, _xlfn.LAMBDA(_xlpm.party, SUMIFS(ledger!J:J, ledger!B:B, _xlpm.party, ledger!E:E, "<>*RD*", ledger!D:D, "Satin", ledger!C:C, "<>January Closing CF") ))+ _xlfn.IFNA(J100, 0)} -> 0 | AA7: {=_xlfn.BYROW(B51, _xlfn.LAMBDA(_xlpm.party, SUMIFS(ledger!J:J, ledger!B:B, _xlpm.party, ledger!E:E, "<>*RD*", ledger!D:D, "Black-Chamki", ledger!C:C, "<>January Closing CF") ))+ _xlfn.IFNA(K100, 0)} -> 0 | AB7: {=_xlfn.BYROW(B51, _xlfn.LAMBDA(_xlpm.party, SUMIFS(ledger!J:J, ledger!B:B, _xlpm.party, ledger!E:E, "<>*RD*", ledger!D:D, "Kataan", ledger!C:C, "<>January Closing CF") ))+ _xlfn.IFNA(L100, 0)} -> 0 | AC7: {=_xlfn.BYROW(B51, _xlfn.LAMBDA(_xlpm.party, SUMIFS(ledger!J:J, ledger!B:B, _xlpm.party, ledger!E:E, "<>*RD*", ledger!D:D, "Munaar", ledger!C:C, "<>January Closing CF") ))+ _xlfn.IFNA(M100, 0)} -> 0 | AD7: {=_xlfn.BYROW(B51, _xlfn.LAMBDA(_xlpm.party, SUMIFS(ledger!J:J, ledger!B:B, _xlpm.party, ledger!E:E, "<>*RD*", ledger!D:D, "Custom", ledger!C:C, "<>January Closing CF") ))+ _xlfn.IFNA(N100, 0)} -> 0 | AE7: =W7+X7+Y7+Z7+AA7+AB7+AC7+AD7 -> 9812607.9 | AF7: =(SUMIF(Table14[Party],R7,Table14[Credit]))+_xlfn.IFNA(P100,0) -> 9775501 | AG7: =AE7-AF7 -> 37106.901 | AH7: 10 | AI7: 13
B8: =B55 -> Raaz Fabrics | C8: =SUMIFS(ledger!G:G, ledger!B:B, B8, ledger!E:E, "<>*RD*") / 1.0936 -> 23264.448 | D8: 10 | E8: =(SUMIFS(ledger!G:G, ledger!B:B, B8, ledger!E:E, "<>*RD*",ledger!D:D, "Silky") / 1.0936)*12 + (SUMIFS(ledger!G:G, ledger!B:B, B8, ledger!E:E, "<>*RD*",ledger!D:D, "chamki") / 1.0936)*10 +(SUMIFS(ledger!G:G, ledger!B:B, B8, ledger!E:E, "<>*RD*",ledger!D:D, "Crinkle") / 1.0936)*10 -> 232644.48 | I8: Raaz Fabrics | R8: Shehzad Kamoki | S8: {=_xlfn.BYROW(B52,_xlfn.LAMBDA(_xlpm.party,SUMIFS(ledger!G:G,ledger!B:B,_xlpm.party,ledger!E:E,"<>*RD*")))+_xlfn.IFNA(C101,0)} -> 143457 | T8: {=_xlfn.BYROW(B52, _xlfn.LAMBDA(_xlpm.party, SUMIFS(ledger!G:G, ledger!B:B, _xlpm.party, ledger!E:E, "<>*RD*") / 1.0936 ))+_xlfn.IFNA(D101,0)} -> 131178.68 | U8: {=(_xlfn.BYROW(B52,_xlfn.LAMBDA(_xlpm.party,SUMIFS(ledger!G:G,ledger!B:B,_xlpm.party,ledger!E:E,"<>*RD*",ledger!D:D,"Chamki")+SUMIFS(ledger!G:G, ledger!B:B, _xlpm.party, ledger!E:E, "<>*RD*", ledger!D:D, "Crinkle")))/1.0936)+_xlfn.IFNA(E101,0)} -> 131178.68 | V8: {=(_xlfn.BYROW(B52,_xlfn.LAMBDA(_xlpm.party,SUMIFS(ledger!G:G,ledger!B:B,_xlpm.party,ledger!E:E,"<>*RD*",ledger!D:D,"Silky")))/1.0936)+_xlfn.IFNA(F101,0)} -> 0 | W8: {=(_xlfn.BYROW(B52,_xlfn.LAMBDA(_xlpm.party, (SUMIFS(ledger!J:J,ledger!B:B,_xlpm.party,ledger!E:E,"<>*RD*",ledger!D:D,"Chamki",ledger!C:C,"<>January Closing CF")+ SUMIFS(ledger!J:J,ledger!B:B,_xlpm.party,ledger!E:E,"<>*RD*",ledger!D:D,"Crinkle",ledger!C:C,"<>January Closing CF") )+_xlfn.IFNA(G101,0))))} -> 1354242 | X8: {=_xlfn.BYROW(B52, _xlfn.LAMBDA(_xlpm.party, SUMIFS(ledger!J:J, ledger!B:B, _xlpm.party, ledger!E:E, "<>*RD*", ledger!D:D, "Silky", ledger!C:C, "<>January Closing CF") )) + _xlfn.IFNA(H101, 0)} -> 0 | Y8: {=_xlfn.BYROW(B52, _xlfn.LAMBDA(_xlpm.party, SUMIFS(ledger!J:J, ledger!B:B, _xlpm.party, ledger!E:E, "<>*RD*", ledger!D:D, "Slub", ledger!C:C, "<>January Closing CF") ))+ _xlfn.IFNA(I101, 0)} -> 0 | Z8: {=_xlfn.BYROW(B52, _xlfn.LAMBDA(_xlpm.party, SUMIFS(ledger!J:J, ledger!B:B, _xlpm.party, ledger!E:E, "<>*RD*", ledger!D:D, "Satin", ledger!C:C, "<>January Closing CF") ))+ _xlfn.IFNA(J101, 0)} -> 0 | AA8: {=_xlfn.BYROW(B52, _xlfn.LAMBDA(_xlpm.party, SUMIFS(ledger!J:J, ledger!B:B, _xlpm.party, ledger!E:E, "<>*RD*", ledger!D:D, "Black-Chamki", ledger!C:C, "<>January Closing CF") ))+ _xlfn.IFNA(K101, 0)} -> 0 | AB8: {=_xlfn.BYROW(B52, _xlfn.LAMBDA(_xlpm.party, SUMIFS(ledger!J:J, ledger!B:B, _xlpm.party, ledger!E:E, "<>*RD*", ledger!D:D, "Kataan", ledger!C:C, "<>January Closing CF") ))+ _xlfn.IFNA(L101, 0)} -> 0 | AC8: {=_xlfn.BYROW(B52, _xlfn.LAMBDA(_xlpm.party, SUMIFS(ledger!J:J, ledger!B:B, _xlpm.party, ledger!E:E, "<>*RD*", ledger!D:D, "Munaar", ledger!C:C, "<>January Closing CF") ))+ _xlfn.IFNA(M101, 0)} -> 0 | AD8: {=_xlfn.BYROW(B52, _xlfn.LAMBDA(_xlpm.party, SUMIFS(ledger!J:J, ledger!B:B, _xlpm.party, ledger!E:E, "<>*RD*", ledger!D:D, "Custom", ledger!C:C, "<>January Closing CF") ))+ _xlfn.IFNA(N101, 0)} -> 0 | AE8: =W8+X8+Y8+Z8+AA8+AB8+AC8+AD8 -> 1354242 | AF8: =(SUMIF(Table14[Party],R8,Table14[Credit]))+_xlfn.IFNA(P101,0) -> 1353710 | AG8: =AE8-AF8 -> 531.99729 | AH8: 10.5 | AI8: 13
B9: =B56 -> Azam | C9: =SUMIFS(ledger!G:G, ledger!B:B, B9, ledger!E:E, "<>*RD*") / 1.0936 -> 0 | D9: 10 | E9: =(SUMIFS(ledger!G:G, ledger!B:B, B9, ledger!E:E, "<>*RD*",ledger!D:D, "Silky") / 1.0936)*12 + (SUMIFS(ledger!G:G, ledger!B:B, B9, ledger!E:E, "<>*RD*",ledger!D:D, "Chamki") / 1.0936)*10 -> 0 | I9: Azam | R9: Sufi Nawaz Sahab | S9: {=_xlfn.BYROW(B53,_xlfn.LAMBDA(_xlpm.party,SUMIFS(ledger!G:G,ledger!B:B,_xlpm.party,ledger!E:E,"<>*RD*")))+_xlfn.IFNA(C102,0)} -> 1212967 | T9: {=_xlfn.BYROW(B53, _xlfn.LAMBDA(_xlpm.party, SUMIFS(ledger!G:G, ledger!B:B, _xlpm.party, ledger!E:E, "<>*RD*") / 1.0936 ))+_xlfn.IFNA(D102,0)} -> 1109150.5 | U9: {=(_xlfn.BYROW(B53,_xlfn.LAMBDA(_xlpm.party,SUMIFS(ledger!G:G,ledger!B:B,_xlpm.party,ledger!E:E,"<>*RD*",ledger!D:D,"Chamki")+SUMIFS(ledger!G:G, ledger!B:B, _xlpm.party, ledger!E:E, "<>*RD*", ledger!D:D, "Crinkle")))/1.0936)+_xlfn.IFNA(E102,0)} -> 599330.65 | V9: {=(_xlfn.BYROW(B53,_xlfn.LAMBDA(_xlpm.party,SUMIFS(ledger!G:G,ledger!B:B,_xlpm.party,ledger!E:E,"<>*RD*",ledger!D:D,"Silky")))/1.0936)+_xlfn.IFNA(F102,0)} -> 485823.88 | W9: {=(_xlfn.BYROW(B53,_xlfn.LAMBDA(_xlpm.party, (SUMIFS(ledger!J:J,ledger!B:B,_xlpm.party,ledger!E:E,"<>*RD*",ledger!D:D,"Chamki",ledger!C:C,"<>January Closing CF")+ SUMIFS(ledger!J:J,ledger!B:B,_xlpm.party,ledger!E:E,"<>*RD*",ledger!D:D,"Crinkle",ledger!C:C,"<>January Closing CF") )+_xlfn.IFNA(G102,0))))} -> 5408917.9 | X9: {=_xlfn.BYROW(B53, _xlfn.LAMBDA(_xlpm.party, SUMIFS(ledger!J:J, ledger!B:B, _xlpm.party, ledger!E:E, "<>*RD*", ledger!D:D, "Silky", ledger!C:C, "<>January Closing CF") )) + _xlfn.IFNA(H102, 0)} -> 5829886.6 | Y9: {=_xlfn.BYROW(B53, _xlfn.LAMBDA(_xlpm.party, SUMIFS(ledger!J:J, ledger!B:B, _xlpm.party, ledger!E:E, "<>*RD*", ledger!D:D, "Slub", ledger!C:C, "<>January Closing CF") ))+ _xlfn.IFNA(I102, 0)} -> 0 | Z9: {=_xlfn.BYROW(B53, _xlfn.LAMBDA(_xlpm.party, SUMIFS(ledger!J:J, ledger!B:B, _xlpm.party, ledger!E:E, "<>*RD*", ledger!D:D, "Satin", ledger!C:C, "<>January Closing CF") ))+ _xlfn.IFNA(J102, 0)} -> 239959.77 | AA9: {=_xlfn.BYROW(B53, _xlfn.LAMBDA(_xlpm.party, SUMIFS(ledger!J:J, ledger!B:B, _xlpm.party, ledger!E:E, "<>*RD*", ledger!D:D, "Black-Chamki", ledger!C:C, "<>January Closing CF") ))+ _xlfn.IFNA(K102, 0)} -> 0 | AB9: {=_xlfn.BYROW(B53, _xlfn.LAMBDA(_xlpm.party, SUMIFS(ledger!J:J, ledger!B:B, _xlpm.party, ledger!E:E, "<>*RD*", ledger!D:D, "Kataan", ledger!C:C, "<>January Closing CF") ))+ _xlfn.IFNA(L102, 0)} -> 0 | AC9: {=_xlfn.BYROW(B53, _xlfn.LAMBDA(_xlpm.party, SUMIFS(ledger!J:J, ledger!B:B, _xlpm.party, ledger!E:E, "<>*RD*", ledger!D:D, "Munaar", ledger!C:C, "<>January Closing CF") ))+ _xlfn.IFNA(M102, 0)} -> 0 | AD9: {=_xlfn.BYROW(B53, _xlfn.LAMBDA(_xlpm.party, SUMIFS(ledger!J:J, ledger!B:B, _xlpm.party, ledger!E:E, "<>*RD*", ledger!D:D, "Custom", ledger!C:C, "<>January Closing CF") ))+ _xlfn.IFNA(N102, 0)} -> 0 | AE9: =W9+X9+Y9+Z9+AA9+AB9+AC9+AD9 -> 11478764 | AF9: =(SUMIF(Table14[Party],R9,Table14[Credit]))+_xlfn.IFNA(P102,0) -> 11478764 | AG9: =AE9-AF9 -> 0.23847842 | AH9: 10 | AI9: 13
B10: =B57 -> Ubaidullah | C10: =SUMIFS(ledger!G:G, ledger!B:B, B10, ledger!E:E, "<>*RD*") / 1.0936 -> 100178.31 | D10: 10 | E10: =(SUMIFS(ledger!G:G, ledger!B:B, B10, ledger!E:E, "<>*RD*",ledger!D:D, "Silky") / 1.0936)*12 + (SUMIFS(ledger!G:G, ledger!B:B, B10, ledger!E:E, "<>*RD*",ledger!D:D, "Chamki") / 1.0936)*10 -> 1202139.7 | I10: Ubaidullah | R10: Sajad Khan | S10: {=_xlfn.BYROW(B54,_xlfn.LAMBDA(_xlpm.party,SUMIFS(ledger!G:G,ledger!B:B,_xlpm.party,ledger!E:E,"<>*RD*")))+_xlfn.IFNA(C103,0)} -> 1135029 | T10: {=_xlfn.BYROW(B54, _xlfn.LAMBDA(_xlpm.party, SUMIFS(ledger!G:G, ledger!B:B, _xlpm.party, ledger!E:E, "<>*RD*") / 1.0936 ))+_xlfn.IFNA(D103,0)} -> 1037883.1 | U10: {=(_xlfn.BYROW(B54,_xlfn.LAMBDA(_xlpm.party,SUMIFS(ledger!G:G,ledger!B:B,_xlpm.party,ledger!E:E,"<>*RD*",ledger!D:D,"Chamki")+SUMIFS(ledger!G:G, ledger!B:B, _xlpm.party, ledger!E:E, "<>*RD*", ledger!D:D, "Crinkle")))/1.0936)+_xlfn.IFNA(E103,0)} -> 1005535.8 | V10: {=(_xlfn.BYROW(B54,_xlfn.LAMBDA(_xlpm.party,SUMIFS(ledger!G:G,ledger!B:B,_xlpm.party,ledger!E:E,"<>*RD*",ledger!D:D,"Silky")))/1.0936)+_xlfn.IFNA(F103,0)} -> 0 | W10: {=(_xlfn.BYROW(B54,_xlfn.LAMBDA(_xlpm.party, (SUMIFS(ledger!J:J,ledger!B:B,_xlpm.party,ledger!E:E,"<>*RD*",ledger!D:D,"Chamki",ledger!C:C,"<>January Closing CF")+ SUMIFS(ledger!J:J,ledger!B:B,_xlpm.party,ledger!E:E,"<>*RD*",ledger!D:D,"Crinkle",ledger!C:C,"<>January Closing CF") )+_xlfn.IFNA(G103,0))))} -> 10055358 | X10: {=_xlfn.BYROW(B54, _xlfn.LAMBDA(_xlpm.party, SUMIFS(ledger!J:J, ledger!B:B, _xlpm.party, ledger!E:E, "<>*RD*", ledger!D:D, "Silky", ledger!C:C, "<>January Closing CF") )) + _xlfn.IFNA(H103, 0)} -> 0 | Y10: {=_xlfn.BYROW(B54, _xlfn.LAMBDA(_xlpm.party, SUMIFS(ledger!J:J, ledger!B:B, _xlpm.party, ledger!E:E, "<>*RD*", ledger!D:D, "Slub", ledger!C:C, "<>January Closing CF") ))+ _xlfn.IFNA(I103, 0)} -> 71359.729 | Z10: {=_xlfn.BYROW(B54, _xlfn.LAMBDA(_xlpm.party, SUMIFS(ledger!J:J, ledger!B:B, _xlpm.party, ledger!E:E, "<>*RD*", ledger!D:D, "Satin", ledger!C:C, "<>January Closing CF") ))+ _xlfn.IFNA(J103, 0)} -> 0 | AA10: {=_xlfn.BYROW(B54, _xlfn.LAMBDA(_xlpm.party, SUMIFS(ledger!J:J, ledger!B:B, _xlpm.party, ledger!E:E, "<>*RD*", ledger!D:D, "Black-Chamki", ledger!C:C, "<>January Closing CF") ))+ _xlfn.IFNA(K103, 0)} -> 322297 | AB10: {=_xlfn.BYROW(B54, _xlfn.LAMBDA(_xlpm.party, SUMIFS(ledger!J:J, ledger!B:B, _xlpm.party, ledger!E:E, "<>*RD*", ledger!D:D, "Kataan", ledger!C:C, "<>January Closing CF") ))+ _xlfn.IFNA(L103, 0)} -> 0 | AC10: {=_xlfn.BYROW(B54, _xlfn.LAMBDA(_xlpm.party, SUMIFS(ledger!J:J, ledger!B:B, _xlpm.party, ledger!E:E, "<>*RD*", ledger!D:D, "Munaar", ledger!C:C, "<>January Closing CF") ))+ _xlfn.IFNA(M103, 0)} -> 0 | AD10: {=_xlfn.BYROW(B54, _xlfn.LAMBDA(_xlpm.party, SUMIFS(ledger!J:J, ledger!B:B, _xlpm.party, ledger!E:E, "<>*RD*", ledger!D:D, "Custom", ledger!C:C, "<>January Closing CF") ))+ _xlfn.IFNA(N103, 0)} -> 0 | AE10: =W10+X10+Y10+Z10+AA10+AB10+AC10+AD10 -> 10449015 | AF10: =(SUMIF(Table14[Party],R10,Table14[Credit]))+_xlfn.IFNA(P103,0) -> 10448871 | AG10: =AE10-AF10 -> 144.17922 | AH10: 10 | AI10: 13
B11: =B58 -> Ashraf Zia | C11: =SUMIFS(ledger!G:G, ledger!B:B, B11, ledger!E:E, "<>*RD*") / 1.0936 -> 0 | D11: 12 | E11: =(SUMIFS(ledger!G:G, ledger!B:B, B11, ledger!E:E, "<>*RD*",ledger!D:D, "Silky") / 1.0936)*12 + (SUMIFS(ledger!G:G, ledger!B:B, B11, ledger!E:E, "<>*RD*",ledger!D:D, "Chamki") / 1.0936)*10 -> 0 | I11: Ashraf Zia | R11: Raaz Fabrics | S11: {=_xlfn.BYROW(B55,_xlfn.LAMBDA(_xlpm.party,SUMIFS(ledger!G:G,ledger!B:B,_xlpm.party,ledger!E:E,"<>*RD*")))+_xlfn.IFNA(C104,0)} -> 203303 | T11: {=_xlfn.BYROW(B55, _xlfn.LAMBDA(_xlpm.party, SUMIFS(ledger!G:G, ledger!B:B, _xlpm.party, ledger!E:E, "<>*RD*") / 1.0936 ))+_xlfn.IFNA(D104,0)} -> 185902.52 | U11: {=(_xlfn.BYROW(B55,_xlfn.LAMBDA(_xlpm.party,SUMIFS(ledger!G:G,ledger!B:B,_xlpm.party,ledger!E:E,"<>*RD*",ledger!D:D,"Chamki")+SUMIFS(ledger!G:G, ledger!B:B, _xlpm.party, ledger!E:E, "<>*RD*", ledger!D:D, "Crinkle")))/1.0936)+_xlfn.IFNA(E104,0)} -> 185902.52 | V11: {=(_xlfn.BYROW(B55,_xlfn.LAMBDA(_xlpm.party,SUMIFS(ledger!G:G,ledger!B:B,_xlpm.party,ledger!E:E,"<>*RD*",ledger!D:D,"Silky")))/1.0936)+_xlfn.IFNA(F104,0)} -> 0 | W11: {=(_xlfn.BYROW(B55,_xlfn.LAMBDA(_xlpm.party, (SUMIFS(ledger!J:J,ledger!B:B,_xlpm.party,ledger!E:E,"<>*RD*",ledger!D:D,"Chamki",ledger!C:C,"<>January Closing CF")+ SUMIFS(ledger!J:J,ledger!B:B,_xlpm.party,ledger!E:E,"<>*RD*",ledger!D:D,"Crinkle",ledger!C:C,"<>January Closing CF") )+_xlfn.IFNA(G104,0))))} -> 1859025.2 | X11: {=_xlfn.BYROW(B55, _xlfn.LAMBDA(_xlpm.party, SUMIFS(ledger!J:J, ledger!B:B, _xlpm.party, ledger!E:E, "<>*RD*", ledger!D:D, "Silky", ledger!C:C, "<>January Closing CF") )) + _xlfn.IFNA(H104, 0)} -> 0 | Y11: {=_xlfn.BYROW(B55, _xlfn.LAMBDA(_xlpm.party, SUMIFS(ledger!J:J, ledger!B:B, _xlpm.party, ledger!E:E, "<>*RD*", ledger!D:D, "Slub", ledger!C:C, "<>January Closing CF") ))+ _xlfn.IFNA(I104, 0)} -> 0 | Z11: {=_xlfn.BYROW(B55, _xlfn.LAMBDA(_xlpm.party, SUMIFS(ledger!J:J, ledger!B:B, _xlpm.party, ledger!E:E, "<>*RD*", ledger!D:D, "Satin", ledger!C:C, "<>January Closing CF") ))+ _xlfn.IFNA(J104, 0)} -> 0 | AA11: {=_xlfn.BYROW(B55, _xlfn.LAMBDA(_xlpm.party, SUMIFS(ledger!J:J, ledger!B:B, _xlpm.party, ledger!E:E, "<>*RD*", ledger!D:D, "Black-Chamki", ledger!C:C, "<>January Closing CF") ))+ _xlfn.IFNA(K104, 0)} -> 0 | AB11: {=_xlfn.BYROW(B55, _xlfn.LAMBDA(_xlpm.party, SUMIFS(ledger!J:J, ledger!B:B, _xlpm.party, ledger!E:E, "<>*RD*", ledger!D:D, "Kataan", ledger!C:C, "<>January Closing CF") ))+ _xlfn.IFNA(L104, 0)} -> 0 | AC11: {=_xlfn.BYROW(B55, _xlfn.LAMBDA(_xlpm.party, SUMIFS(ledger!J:J, ledger!B:B, _xlpm.party, ledger!E:E, "<>*RD*", ledger!D:D, "Munaar", ledger!C:C, "<>January Closing CF") ))+ _xlfn.IFNA(M104, 0)} -> 0 | AD11: {=_xlfn.BYROW(B55, _xlfn.LAMBDA(_xlpm.party, SUMIFS(ledger!J:J, ledger!B:B, _xlpm.party, ledger!E:E, "<>*RD*", ledger!D:D, "Custom", ledger!C:C, "<>January Closing CF") ))+ _xlfn.IFNA(N104, 0)} -> 0 | AE11: =W11+X11+Y11+Z11+AA11+AB11+AC11+AD11 -> 1859025.2 | AF11: =(SUMIF(Table14[Party],R11,Table14[Credit]))+_xlfn.IFNA(P104,0) -> 1726321 | AG11: =AE11-AF11 -> 132704.24 | AH11: 10 | AI11: 13
B12: =B59 -> Hafiz Qureshi | C12: =SUMIFS(ledger!G:G, ledger!B:B, B12, ledger!E:E, "<>*RD*") / 1.0936 -> 215558.71 | E12: =(SUMIFS(ledger!G:G, ledger!B:B, B12, ledger!E:E, "<>*RD*",ledger!D:D, "Silky") / 1.0936)*12 + (SUMIFS(ledger!G:G, ledger!B:B, B12, ledger!E:E, "<>*RD*",ledger!D:D, "Chamki") / 1.0936)*10 -> 1682095.8 | I12: Hafiz Qureshi | R12: Azam | S12: {=_xlfn.BYROW(B56,_xlfn.LAMBDA(_xlpm.party,SUMIFS(ledger!G:G,ledger!B:B,_xlpm.party,ledger!E:E,"<>*RD*")))+_xlfn.IFNA(C105,0)} -> 749236 | T12: {=_xlfn.BYROW(B56, _xlfn.LAMBDA(_xlpm.party, SUMIFS(ledger!G:G, ledger!B:B, _xlpm.party, ledger!E:E, "<>*RD*") / 1.0936 ))+_xlfn.IFNA(D105,0)} -> 685109.73 | U12: {=(_xlfn.BYROW(B56,_xlfn.LAMBDA(_xlpm.party,SUMIFS(ledger!G:G,ledger!B:B,_xlpm.party,ledger!E:E,"<>*RD*",ledger!D:D,"Chamki")+SUMIFS(ledger!G:G, ledger!B:B, _xlpm.party, ledger!E:E, "<>*RD*", ledger!D:D, "Crinkle")))/1.0936)+_xlfn.IFNA(E105,0)} -> 501118.32 | V12: {=(_xlfn.BYROW(B56,_xlfn.LAMBDA(_xlpm.party,SUMIFS(ledger!G:G,ledger!B:B,_xlpm.party,ledger!E:E,"<>*RD*",ledger!D:D,"Silky")))/1.0936)+_xlfn.IFNA(F105,0)} -> 183991.4 | W12: {=(_xlfn.BYROW(B56,_xlfn.LAMBDA(_xlpm.party, (SUMIFS(ledger!J:J,ledger!B:B,_xlpm.party,ledger!E:E,"<>*RD*",ledger!D:D,"Chamki",ledger!C:C,"<>January Closing CF")+ SUMIFS(ledger!J:J,ledger!B:B,_xlpm.party,ledger!E:E,"<>*RD*",ledger!D:D,"Crinkle",ledger!C:C,"<>January Closing CF") )+_xlfn.IFNA(G105,0))))} -> 5011183.2 | X12: {=_xlfn.BYROW(B56, _xlfn.LAMBDA(_xlpm.party, SUMIFS(ledger!J:J, ledger!B:B, _xlpm.party, ledger!E:E, "<>*RD*", ledger!D:D, "Silky", ledger!C:C, "<>January Closing CF") )) + _xlfn.IFNA(H105, 0)} -> 2391888.3 | Y12: {=_xlfn.BYROW(B56, _xlfn.LAMBDA(_xlpm.party, SUMIFS(ledger!J:J, ledger!B:B, _xlpm.party, ledger!E:E, "<>*RD*", ledger!D:D, "Slub", ledger!C:C, "<>January Closing CF") ))+ _xlfn.IFNA(I105, 0)} -> 0 | Z12: {=_xlfn.BYROW(B56, _xlfn.LAMBDA(_xlpm.party, SUMIFS(ledger!J:J, ledger!B:B, _xlpm.party, ledger!E:E, "<>*RD*", ledger!D:D, "Satin", ledger!C:C, "<>January Closing CF") ))+ _xlfn.IFNA(J105, 0)} -> 0 | AA12: {=_xlfn.BYROW(B56, _xlfn.LAMBDA(_xlpm.party, SUMIFS(ledger!J:J, ledger!B:B, _xlpm.party, ledger!E:E, "<>*RD*", ledger!D:D, "Black-Chamki", ledger!C:C, "<>January Closing CF") ))+ _xlfn.IFNA(K105, 0)} -> 0 | AB12: {=_xlfn.BYROW(B56, _xlfn.LAMBDA(_xlpm.party, SUMIFS(ledger!J:J, ledger!B:B, _xlpm.party, ledger!E:E, "<>*RD*", ledger!D:D, "Kataan", ledger!C:C, "<>January Closing CF") ))+ _xlfn.IFNA(L105, 0)} -> 0 | AC12: {=_xlfn.BYROW(B56, _xlfn.LAMBDA(_xlpm.party, SUMIFS(ledger!J:J, ledger!B:B, _xlpm.party, ledger!E:E, "<>*RD*", ledger!D:D, "Munaar", ledger!C:C, "<>January Closing CF") ))+ _xlfn.IFNA(M105, 0)} -> 0 | AD12: {=_xlfn.BYROW(B56, _xlfn.LAMBDA(_xlpm.party, SUMIFS(ledger!J:J, ledger!B:B, _xlpm.party, ledger!E:E, "<>*RD*", ledger!D:D, "Custom", ledger!C:C, "<>January Closing CF") ))+ _xlfn.IFNA(N105, 0)} -> 0 | AE12: =W12+X12+Y12+Z12+AA12+AB12+AC12+AD12 -> 7403071.5 | AF12: =(SUMIF(Table14[Party],R12,Table14[Credit]))+_xlfn.IFNA(P105,0) -> 7402540 | AG12: =AE12-AF12 -> 531.50695 | AH12: 10 | AI12: 13
B13: =B60 -> Badshah Fabrics | C13: =SUMIFS(ledger!G:G, ledger!B:B, B13, ledger!E:E, "<>*RD*") / 1.0936 -> 0 | E13: =(SUMIFS(ledger!G:G, ledger!B:B, B13, ledger!E:E, "<>*RD*",ledger!D:D, "Silky") / 1.0936)*12 + (SUMIFS(ledger!G:G, ledger!B:B, B13, ledger!E:E, "<>*RD*",ledger!D:D, "Chamki") / 1.0936)*10 -> 0 | I13: Badshah Fabrics | R13: Ubaidullah | S13: {=_xlfn.BYROW(B57,_xlfn.LAMBDA(_xlpm.party,SUMIFS(ledger!G:G,ledger!B:B,_xlpm.party,ledger!E:E,"<>*RD*")))+_xlfn.IFNA(C106,0)} -> 283089 | T13: {=_xlfn.BYROW(B57, _xlfn.LAMBDA(_xlpm.party, SUMIFS(ledger!G:G, ledger!B:B, _xlpm.party, ledger!E:E, "<>*RD*") / 1.0936 ))+_xlfn.IFNA(D106,0)} -> 258859.73 | U13: {=(_xlfn.BYROW(B57,_xlfn.LAMBDA(_xlpm.party,SUMIFS(ledger!G:G,ledger!B:B,_xlpm.party,ledger!E:E,"<>*RD*",ledger!D:D,"Chamki")+SUMIFS(ledger!G:G, ledger!B:B, _xlpm.party, ledger!E:E, "<>*RD*", ledger!D:D, "Crinkle")))/1.0936)+_xlfn.IFNA(E106,0)} -> 46132.955 | V13: {=(_xlfn.BYROW(B57,_xlfn.LAMBDA(_xlpm.party,SUMIFS(ledger!G:G,ledger!B:B,_xlpm.party,ledger!E:E,"<>*RD*",ledger!D:D,"Silky")))/1.0936)+_xlfn.IFNA(F106,0)} -> 212726.77 | W13: {=(_xlfn.BYROW(B57,_xlfn.LAMBDA(_xlpm.party, (SUMIFS(ledger!J:J,ledger!B:B,_xlpm.party,ledger!E:E,"<>*RD*",ledger!D:D,"Chamki",ledger!C:C,"<>January Closing CF")+ SUMIFS(ledger!J:J,ledger!B:B,_xlpm.party,ledger!E:E,"<>*RD*",ledger!D:D,"Crinkle",ledger!C:C,"<>January Closing CF") )+_xlfn.IFNA(G106,0))))} -> 461329.55 | X13: {=_xlfn.BYROW(B57, _xlfn.LAMBDA(_xlpm.party, SUMIFS(ledger!J:J, ledger!B:B, _xlpm.party, ledger!E:E, "<>*RD*", ledger!D:D, "Silky", ledger!C:C, "<>January Closing CF") )) + _xlfn.IFNA(H106, 0)} -> 2650274.3 | Y13: {=_xlfn.BYROW(B57, _xlfn.LAMBDA(_xlpm.party, SUMIFS(ledger!J:J, ledger!B:B, _xlpm.party, ledger!E:E, "<>*RD*", ledger!D:D, "Slub", ledger!C:C, "<>January Closing CF") ))+ _xlfn.IFNA(I106, 0)} -> 0 | Z13: {=_xlfn.BYROW(B57, _xlfn.LAMBDA(_xlpm.party, SUMIFS(ledger!J:J, ledger!B:B, _xlpm.party, ledger!E:E, "<>*RD*", ledger!D:D, "Satin", ledger!C:C, "<>January Closing CF") ))+ _xlfn.IFNA(J106, 0)} -> 0 | AA13: {=_xlfn.BYROW(B57, _xlfn.LAMBDA(_xlpm.party, SUMIFS(ledger!J:J, ledger!B:B, _xlpm.party, ledger!E:E, "<>*RD*", ledger!D:D, "Black-Chamki", ledger!C:C, "<>January Closing CF") ))+ _xlfn.IFNA(K106, 0)} -> 0 | AB13: {=_xlfn.BYROW(B57, _xlfn.LAMBDA(_xlpm.party, SUMIFS(ledger!J:J, ledger!B:B, _xlpm.party, ledger!E:E, "<>*RD*", ledger!D:D, "Kataan", ledger!C:C, "<>January Closing CF") ))+ _xlfn.IFNA(L106, 0)} -> 0 | AC13: {=_xlfn.BYROW(B57, _xlfn.LAMBDA(_xlpm.party, SUMIFS(ledger!J:J, ledger!B:B, _xlpm.party, ledger!E:E, "<>*RD*", ledger!D:D, "Munaar", ledger!C:C, "<>January Closing CF") ))+ _xlfn.IFNA(M106, 0)} -> 0 | AD13: {=_xlfn.BYROW(B57, _xlfn.LAMBDA(_xlpm.party, SUMIFS(ledger!J:J, ledger!B:B, _xlpm.party, ledger!E:E, "<>*RD*", ledger!D:D, "Custom", ledger!C:C, "<>January Closing CF") ))+ _xlfn.IFNA(N106, 0)} -> 0 | AE13: =W13+X13+Y13+Z13+AA13+AB13+AC13+AD13 -> 3111603.9 | AF13: =(SUMIF(Table14[Party],R13,Table14[Credit]))+_xlfn.IFNA(P106,0) -> 3009990 | AG13: =AE13-AF13 -> 101613.88 | AH13: 10 | AI13: 13
B14: =B61 -> Gauhar Kashif | C14: =SUMIFS(ledger!G:G, ledger!B:B, B14, ledger!E:E, "<>*RD*") / 1.0936 -> 0 | E14: =(SUMIFS(ledger!G:G, ledger!B:B, B14, ledger!E:E, "<>*RD*",ledger!D:D, "Silky") / 1.0936)*12 + (SUMIFS(ledger!G:G, ledger!B:B, B14, ledger!E:E, "<>*RD*",ledger!D:D, "Chamki") / 1.0936)*10 -> 0 | I14: Reject | R14: Ashraf Zia | S14: {=_xlfn.BYROW(B58,_xlfn.LAMBDA(_xlpm.party,SUMIFS(ledger!G:G,ledger!B:B,_xlpm.party,ledger!E:E,"<>*RD*")))+_xlfn.IFNA(C107,0)} -> 23305 | T14: {=_xlfn.BYROW(B58, _xlfn.LAMBDA(_xlpm.party, SUMIFS(ledger!G:G, ledger!B:B, _xlpm.party, ledger!E:E, "<>*RD*") / 1.0936 ))+_xlfn.IFNA(D107,0)} -> 21310.351 | U14: {=(_xlfn.BYROW(B58,_xlfn.LAMBDA(_xlpm.party,SUMIFS(ledger!G:G,ledger!B:B,_xlpm.party,ledger!E:E,"<>*RD*",ledger!D:D,"Chamki")+SUMIFS(ledger!G:G, ledger!B:B, _xlpm.party, ledger!E:E, "<>*RD*", ledger!D:D, "Crinkle")))/1.0936)+_xlfn.IFNA(E107,0)} -> 21310.351 | V14: {=(_xlfn.BYROW(B58,_xlfn.LAMBDA(_xlpm.party,SUMIFS(ledger!G:G,ledger!B:B,_xlpm.party,ledger!E:E,"<>*RD*",ledger!D:D,"Silky")))/1.0936)+_xlfn.IFNA(F107,0)} -> 0 | W14: {=(_xlfn.BYROW(B58,_xlfn.LAMBDA(_xlpm.party, (SUMIFS(ledger!J:J,ledger!B:B,_xlpm.party,ledger!E:E,"<>*RD*",ledger!D:D,"Chamki",ledger!C:C,"<>January Closing CF")+ SUMIFS(ledger!J:J,ledger!B:B,_xlpm.party,ledger!E:E,"<>*RD*",ledger!D:D,"Crinkle",ledger!C:C,"<>January Closing CF") )+_xlfn.IFNA(G107,0))))} -> 255724.21 | X14: {=_xlfn.BYROW(B58, _xlfn.LAMBDA(_xlpm.party, SUMIFS(ledger!J:J, ledger!B:B, _xlpm.party, ledger!E:E, "<>*RD*", ledger!D:D, "Silky", ledger!C:C, "<>January Closing CF") )) + _xlfn.IFNA(H107, 0)} -> 0 | Y14: {=_xlfn.BYROW(B58, _xlfn.LAMBDA(_xlpm.party, SUMIFS(ledger!J:J, ledger!B:B, _xlpm.party, ledger!E:E, "<>*RD*", ledger!D:D, "Slub", ledger!C:C, "<>January Closing CF") ))+ _xlfn.IFNA(I107, 0)} -> 0 | Z14: {=_xlfn.BYROW(B58, _xlfn.LAMBDA(_xlpm.party, SUMIFS(ledger!J:J, ledger!B:B, _xlpm.party, ledger!E:E, "<>*RD*", ledger!D:D, "Satin", ledger!C:C, "<>January Closing CF") ))+ _xlfn.IFNA(J107, 0)} -> 0 | AA14: {=_xlfn.BYROW(B58, _xlfn.LAMBDA(_xlpm.party, SUMIFS(ledger!J:J, ledger!B:B, _xlpm.party, ledger!E:E, "<>*RD*", ledger!D:D, "Black-Chamki", ledger!C:C, "<>January Closing CF") ))+ _xlfn.IFNA(K107, 0)} -> 0 | AB14: {=_xlfn.BYROW(B58, _xlfn.LAMBDA(_xlpm.party, SUMIFS(ledger!J:J, ledger!B:B, _xlpm.party, ledger!E:E, "<>*RD*", ledger!D:D, "Kataan", ledger!C:C, "<>January Closing CF") ))+ _xlfn.IFNA(L107, 0)} -> 0 | AC14: {=_xlfn.BYROW(B58, _xlfn.LAMBDA(_xlpm.party, SUMIFS(ledger!J:J, ledger!B:B, _xlpm.party, ledger!E:E, "<>*RD*", ledger!D:D, "Munaar", ledger!C:C, "<>January Closing CF") ))+ _xlfn.IFNA(M107, 0)} -> 0 | AD14: {=_xlfn.BYROW(B58, _xlfn.LAMBDA(_xlpm.party, SUMIFS(ledger!J:J, ledger!B:B, _xlpm.party, ledger!E:E, "<>*RD*", ledger!D:D, "Custom", ledger!C:C, "<>January Closing CF") ))+ _xlfn.IFNA(N107, 0)} -> 0 | AE14: =W14+X14+Y14+Z14+AA14+AB14+AC14+AD14 -> 255724.21 | AF14: =(SUMIF(Table14[Party],R14,Table14[Credit]))+_xlfn.IFNA(P107,0) -> 130000 | AG14: =AE14-AF14 -> 125724.21 | AH14: 12 | AI14: 13
B15: =B62 -> Amjad 7up | C15: =SUMIFS(ledger!G:G, ledger!B:B, B15, ledger!E:E, "<>*RD*") / 1.0936 -> 0 | E15: =(SUMIFS(ledger!G:G, ledger!B:B, B15, ledger!E:E, "<>*RD*",ledger!D:D, "Silky") / 1.0936)*12 + (SUMIFS(ledger!G:G, ledger!B:B, B15, ledger!E:E, "<>*RD*",ledger!D:D, "Chamki") / 1.0936)*10 -> 0 | I15: Amjad 7up | R15: Hafiz Qureshi | S15: {=_xlfn.BYROW(B59,_xlfn.LAMBDA(_xlpm.party,SUMIFS(ledger!G:G,ledger!B:B,_xlpm.party,ledger!E:E,"<>*RD*")))+_xlfn.IFNA(C108,0)} -> 690362 | T15: {=_xlfn.BYROW(B59, _xlfn.LAMBDA(_xlpm.party, SUMIFS(ledger!G:G, ledger!B:B, _xlpm.party, ledger!E:E, "<>*RD*") / 1.0936 ))+_xlfn.IFNA(D108,0)} -> 631274.69 | U15: {=(_xlfn.BYROW(B59,_xlfn.LAMBDA(_xlpm.party,SUMIFS(ledger!G:G,ledger!B:B,_xlpm.party,ledger!E:E,"<>*RD*",ledger!D:D,"Chamki")+SUMIFS(ledger!G:G, ledger!B:B, _xlpm.party, ledger!E:E, "<>*RD*", ledger!D:D, "Crinkle")))/1.0936)+_xlfn.IFNA(E108,0)} -> 583925.57 | V15: {=(_xlfn.BYROW(B59,_xlfn.LAMBDA(_xlpm.party,SUMIFS(ledger!G:G,ledger!B:B,_xlpm.party,ledger!E:E,"<>*RD*",ledger!D:D,"Silky")))/1.0936)+_xlfn.IFNA(F108,0)} -> 0 | W15: {=(_xlfn.BYROW(B59,_xlfn.LAMBDA(_xlpm.party, (SUMIFS(ledger!J:J,ledger!B:B,_xlpm.party,ledger!E:E,"<>*RD*",ledger!D:D,"Chamki",ledger!C:C,"<>January Closing CF")+ SUMIFS(ledger!J:J,ledger!B:B,_xlpm.party,ledger!E:E,"<>*RD*",ledger!D:D,"Crinkle",ledger!C:C,"<>January Closing CF") )+_xlfn.IFNA(G108,0))))} -> 5839255.7 | X15: {=_xlfn.BYROW(B59, _xlfn.LAMBDA(_xlpm.party, SUMIFS(ledger!J:J, ledger!B:B, _xlpm.party, ledger!E:E, "<>*RD*", ledger!D:D, "Silky", ledger!C:C, "<>January Closing CF") )) + _xlfn.IFNA(H108, 0)} -> 0 | Y15: {=_xlfn.BYROW(B59, _xlfn.LAMBDA(_xlpm.party, SUMIFS(ledger!J:J, ledger!B:B, _xlpm.party, ledger!E:E, "<>*RD*", ledger!D:D, "Slub", ledger!C:C, "<>January Closing CF") ))+ _xlfn.IFNA(I108, 0)} -> 0 | Z15: {=_xlfn.BYROW(B59, _xlfn.LAMBDA(_xlpm.party, SUMIFS(ledger!J:J, ledger!B:B, _xlpm.party, ledger!E:E, "<>*RD*", ledger!D:D, "Satin", ledger!C:C, "<>January Closing CF") ))+ _xlfn.IFNA(J108, 0)} -> 0 | AA15: {=_xlfn.BYROW(B59, _xlfn.LAMBDA(_xlpm.party, SUMIFS(ledger!J:J, ledger!B:B, _xlpm.party, ledger!E:E, "<>*RD*", ledger!D:D, "Black-Chamki", ledger!C:C, "<>January Closing CF") ))+ _xlfn.IFNA(K108, 0)} -> 0 | AB15: {=_xlfn.BYROW(B59, _xlfn.LAMBDA(_xlpm.party, SUMIFS(ledger!J:J, ledger!B:B, _xlpm.party, ledger!E:E, "<>*RD*", ledger!D:D, "Kataan", ledger!C:C, "<>January Closing CF") ))+ _xlfn.IFNA(L108, 0)} -> 520840.34 | AC15: {=_xlfn.BYROW(B59, _xlfn.LAMBDA(_xlpm.party, SUMIFS(ledger!J:J, ledger!B:B, _xlpm.party, ledger!E:E, "<>*RD*", ledger!D:D, "Munaar", ledger!C:C, "<>January Closing CF") ))+ _xlfn.IFNA(M108, 0)} -> 0 | AD15: {=_xlfn.BYROW(B59, _xlfn.LAMBDA(_xlpm.party, SUMIFS(ledger!J:J, ledger!B:B, _xlpm.party, ledger!E:E, "<>*RD*", ledger!D:D, "Custom", ledger!C:C, "<>January Closing CF") ))+ _xlfn.IFNA(N108, 0)} -> 0 | AE15: =W15+X15+Y15+Z15+AA15+AB15+AC15+AD15 -> 6360096 | AF15: =(SUMIF(Table14[Party],R15,Table14[Credit]))+_xlfn.IFNA(P108,0) -> 5825853 | AG15: =AE15-AF15 -> 534243.01 | AH15: 10 | AI15: 13
B16: =B63 -> Hazrat Khan | C16: =SUMIFS(ledger!G:G, ledger!B:B, B16, ledger!E:E, "<>*RD*") / 1.0936 -> 0 | E16: =(SUMIFS(ledger!G:G, ledger!B:B, B16, ledger!E:E, "<>*RD*",ledger!D:D, "Silky") / 1.0936)*12 + (SUMIFS(ledger!G:G, ledger!B:B, B16, ledger!E:E, "<>*RD*",ledger!D:D, "Chamki") / 1.0936)*10 -> 0 | I16: Hazrat Khan | R16: Badshah Fabrics | S16: {=_xlfn.BYROW(B60,_xlfn.LAMBDA(_xlpm.party,SUMIFS(ledger!G:G,ledger!B:B,_xlpm.party,ledger!E:E,"<>*RD*")))+_xlfn.IFNA(C109,0)} -> 681314 | T16: {=_xlfn.BYROW(B60, _xlfn.LAMBDA(_xlpm.party, SUMIFS(ledger!G:G, ledger!B:B, _xlpm.party, ledger!E:E, "<>*RD*") / 1.0936 ))+_xlfn.IFNA(D109,0)} -> 623001.1 | U16: {=(_xlfn.BYROW(B60,_xlfn.LAMBDA(_xlpm.party,SUMIFS(ledger!G:G,ledger!B:B,_xlpm.party,ledger!E:E,"<>*RD*",ledger!D:D,"Chamki")+SUMIFS(ledger!G:G, ledger!B:B, _xlpm.party, ledger!E:E, "<>*RD*", ledger!D:D, "Crinkle")))/1.0936)+_xlfn.IFNA(E109,0)} -> 481526.15 | V16: {=(_xlfn.BYROW(B60,_xlfn.LAMBDA(_xlpm.party,SUMIFS(ledger!G:G,ledger!B:B,_xlpm.party,ledger!E:E,"<>*RD*",ledger!D:D,"Silky")))/1.0936)+_xlfn.IFNA(F109,0)} -> 141474.95 | W16: {=(_xlfn.BYROW(B60,_xlfn.LAMBDA(_xlpm.party, (SUMIFS(ledger!J:J,ledger!B:B,_xlpm.party,ledger!E:E,"<>*RD*",ledger!D:D,"Chamki",ledger!C:C,"<>January Closing CF")+ SUMIFS(ledger!J:J,ledger!B:B,_xlpm.party,ledger!E:E,"<>*RD*",ledger!D:D,"Crinkle",ledger!C:C,"<>January Closing CF") )+_xlfn.IFNA(G109,0))))} -> 4861679.8 | X16: {=_xlfn.BYROW(B60, _xlfn.LAMBDA(_xlpm.party, SUMIFS(ledger!J:J, ledger!B:B, _xlpm.party, ledger!E:E, "<>*RD*", ledger!D:D, "Silky", ledger!C:C, "<>January Closing CF") )) + _xlfn.IFNA(H109, 0)} -> 1776019.6 | Y16: {=_xlfn.BYROW(B60, _xlfn.LAMBDA(_xlpm.party, SUMIFS(ledger!J:J, ledger!B:B, _xlpm.party, ledger!E:E, "<>*RD*", ledger!D:D, "Slub", ledger!C:C, "<>January Closing CF") ))+ _xlfn.IFNA(I109, 0)} -> 0 | Z16: {=_xlfn.BYROW(B60, _xlfn.LAMBDA(_xlpm.party, SUMIFS(ledger!J:J, ledger!B:B, _xlpm.party, ledger!E:E, "<>*RD*", ledger!D:D, "Satin", ledger!C:C, "<>January Closing CF") ))+ _xlfn.IFNA(J109, 0)} -> 0 | AA16: {=_xlfn.BYROW(B60, _xlfn.LAMBDA(_xlpm.party, SUMIFS(ledger!J:J, ledger!B:B, _xlpm.party, ledger!E:E, "<>*RD*", ledger!D:D, "Black-Chamki", ledger!C:C, "<>January Closing CF") ))+ _xlfn.IFNA(K109, 0)} -> 0 | AB16: {=_xlfn.BYROW(B60, _xlfn.LAMBDA(_xlpm.party, SUMIFS(ledger!J:J, ledger!B:B, _xlpm.party, ledger!E:E, "<>*RD*", ledger!D:D, "Kataan", ledger!C:C, "<>January Closing CF") ))+ _xlfn.IFNA(L109, 0)} -> 0 | AC16: {=_xlfn.BYROW(B60, _xlfn.LAMBDA(_xlpm.party, SUMIFS(ledger!J:J, ledger!B:B, _xlpm.party, ledger!E:E, "<>*RD*", ledger!D:D, "Munaar", ledger!C:C, "<>January Closing CF") ))+ _xlfn.IFNA(M109, 0)} -> 0 | AD16: {=_xlfn.BYROW(B60, _xlfn.LAMBDA(_xlpm.party, SUMIFS(ledger!J:J, ledger!B:B, _xlpm.party, ledger!E:E, "<>*RD*", ledger!D:D, "Custom", ledger!C:C, "<>January Closing CF") ))+ _xlfn.IFNA(N109, 0)} -> 0 | AE16: =W16+X16+Y16+Z16+AA16+AB16+AC16+AD16 -> 6637699.3 | AF16: =(SUMIF(Table14[Party],R16,Table14[Credit]))+_xlfn.IFNA(P109,0) -> 6545761 | AG16: =AE16-AF16 -> 91938.342 | AH16: 10 | AI16: 13
B17: =B64 -> Haseeb Shamsi | C17: =SUMIFS(ledger!G:G, ledger!B:B, B17, ledger!E:E, "<>*RD*") / 1.0936 -> 0 | E17: =(SUMIFS(ledger!G:G, ledger!B:B, B17, ledger!E:E, "<>*RD*",ledger!D:D, "Silky") / 1.0936)*12 + (SUMIFS(ledger!G:G, ledger!B:B, B17, ledger!E:E, "<>*RD*",ledger!D:D, "Chamki") / 1.0936)*10 -> 0 | I17: Haseeb Shamsi | R17: Gauhar Kashif | S17: {=_xlfn.BYROW(B61,_xlfn.LAMBDA(_xlpm.party,SUMIFS(ledger!G:G,ledger!B:B,_xlpm.party,ledger!E:E,"<>*RD*")))+_xlfn.IFNA(C110,0)} -> 132768 | T17: {=_xlfn.BYROW(B61, _xlfn.LAMBDA(_xlpm.party, SUMIFS(ledger!G:G, ledger!B:B, _xlpm.party, ledger!E:E, "<>*RD*") / 1.0936 ))+_xlfn.IFNA(D110,0)} -> 121404.54 | U17: {=(_xlfn.BYROW(B61,_xlfn.LAMBDA(_xlpm.party,SUMIFS(ledger!G:G,ledger!B:B,_xlpm.party,ledger!E:E,"<>*RD*",ledger!D:D,"Chamki")+SUMIFS(ledger!G:G, ledger!B:B, _xlpm.party, ledger!E:E, "<>*RD*", ledger!D:D, "Crinkle")))/1.0936)+_xlfn.IFNA(E110,0)} -> 121404.54 | V17: {=(_xlfn.BYROW(B61,_xlfn.LAMBDA(_xlpm.party,SUMIFS(ledger!G:G,ledger!B:B,_xlpm.party,ledger!E:E,"<>*RD*",ledger!D:D,"Silky")))/1.0936)+_xlfn.IFNA(F110,0)} -> 0 | W17: {=(_xlfn.BYROW(B61,_xlfn.LAMBDA(_xlpm.party, (SUMIFS(ledger!J:J,ledger!B:B,_xlpm.party,ledger!E:E,"<>*RD*",ledger!D:D,"Chamki",ledger!C:C,"<>January Closing CF")+ SUMIFS(ledger!J:J,ledger!B:B,_xlpm.party,ledger!E:E,"<>*RD*",ledger!D:D,"Crinkle",ledger!C:C,"<>January Closing CF") )+_xlfn.IFNA(G110,0))))} -> 1214045.4 | X17: {=_xlfn.BYROW(B61, _xlfn.LAMBDA(_xlpm.party, SUMIFS(ledger!J:J, ledger!B:B, _xlpm.party, ledger!E:E, "<>*RD*", ledger!D:D, "Silky", ledger!C:C, "<>January Closing CF") )) + _xlfn.IFNA(H110, 0)} -> 0 | Y17: {=_xlfn.BYROW(B61, _xlfn.LAMBDA(_xlpm.party, SUMIFS(ledger!J:J, ledger!B:B, _xlpm.party, ledger!E:E, "<>*RD*", ledger!D:D, "Slub", ledger!C:C, "<>January Closing CF") ))+ _xlfn.IFNA(I110, 0)} -> 0 | Z17: {=_xlfn.BYROW(B61, _xlfn.LAMBDA(_xlpm.party, SUMIFS(ledger!J:J, ledger!B:B, _xlpm.party, ledger!E:E, "<>*RD*", ledger!D:D, "Satin", ledger!C:C, "<>January Closing CF") ))+ _xlfn.IFNA(J110, 0)} -> 0 | AA17: {=_xlfn.BYROW(B61, _xlfn.LAMBDA(_xlpm.party, SUMIFS(ledger!J:J, ledger!B:B, _xlpm.party, ledger!E:E, "<>*RD*", ledger!D:D, "Black-Chamki", ledger!C:C, "<>January Closing CF") ))+ _xlfn.IFNA(K110, 0)} -> 0 | AB17: {=_xlfn.BYROW(B61, _xlfn.LAMBDA(_xlpm.party, SUMIFS(ledger!J:J, ledger!B:B, _xlpm.party, ledger!E:E, "<>*RD*", ledger!D:D, "Kataan", ledger!C:C, "<>January Closing CF") ))+ _xlfn.IFNA(L110, 0)} -> 0 | AC17: {=_xlfn.BYROW(B61, _xlfn.LAMBDA(_xlpm.party, SUMIFS(ledger!J:J, ledger!B:B, _xlpm.party, ledger!E:E, "<>*RD*", ledger!D:D, "Munaar", ledger!C:C, "<>January Closing CF") ))+ _xlfn.IFNA(M110, 0)} -> 0 | AD17: {=_xlfn.BYROW(B61, _xlfn.LAMBDA(_xlpm.party, SUMIFS(ledger!J:J, ledger!B:B, _xlpm.party, ledger!E:E, "<>*RD*", ledger!D:D, "Custom", ledger!C:C, "<>January Closing CF") ))+ _xlfn.IFNA(N110, 0)} -> 0 | AE17: =W17+X17+Y17+Z17+AA17+AB17+AC17+AD17 -> 1214045.4 | AF17: =(SUMIF(Table14[Party],R17,Table14[Credit]))+_xlfn.IFNA(P110,0) -> 1214045 | AG17: =AE17-AF17 -> 0.35479151 | AH17: 10 | AI17: 13
B18: =B65 -> Faizan | C18: =SUMIFS(ledger!G:G, ledger!B:B, B18, ledger!E:E, "<>*RD*") / 1.0936 -> 50968.361 | E18: =(SUMIFS(ledger!G:G, ledger!B:B, B18, ledger!E:E, "<>*RD*",ledger!D:D, "Silky") / 1.0936)*12 + (SUMIFS(ledger!G:G, ledger!B:B, B18, ledger!E:E, "<>*RD*",ledger!D:D, "Chamki") / 1.0936)*10 -> 611620.34 | I18: Faizan | R18: Amjad 7up | S18: {=_xlfn.BYROW(B62,_xlfn.LAMBDA(_xlpm.party,SUMIFS(ledger!G:G,ledger!B:B,_xlpm.party,ledger!E:E,"<>*RD*")))+_xlfn.IFNA(C111,0)} -> 52914 | T18: {=_xlfn.BYROW(B62, _xlfn.LAMBDA(_xlpm.party, SUMIFS(ledger!G:G, ledger!B:B, _xlpm.party, ledger!E:E, "<>*RD*") / 1.0936 ))+_xlfn.IFNA(D111,0)} -> 48385.15 | U18: {=(_xlfn.BYROW(B62,_xlfn.LAMBDA(_xlpm.party,SUMIFS(ledger!G:G,ledger!B:B,_xlpm.party,ledger!E:E,"<>*RD*",ledger!D:D,"Chamki")+SUMIFS(ledger!G:G, ledger!B:B, _xlpm.party, ledger!E:E, "<>*RD*", ledger!D:D, "Crinkle")))/1.0936)+_xlfn.IFNA(E111,0)} -> 48385.15 | V18: {=(_xlfn.BYROW(B62,_xlfn.LAMBDA(_xlpm.party,SUMIFS(ledger!G:G,ledger!B:B,_xlpm.party,ledger!E:E,"<>*RD*",ledger!D:D,"Silky")))/1.0936)+_xlfn.IFNA(F111,0)} -> 0 | W18: {=(_xlfn.BYROW(B62,_xlfn.LAMBDA(_xlpm.party, (SUMIFS(ledger!J:J,ledger!B:B,_xlpm.party,ledger!E:E,"<>*RD*",ledger!D:D,"Chamki",ledger!C:C,"<>January Closing CF")+ SUMIFS(ledger!J:J,ledger!B:B,_xlpm.party,ledger!E:E,"<>*RD*",ledger!D:D,"Crinkle",ledger!C:C,"<>January Closing CF") )+_xlfn.IFNA(G111,0))))} -> 483851.5 | X18: {=_xlfn.BYROW(B62, _xlfn.LAMBDA(_xlpm.party, SUMIFS(ledger!J:J, ledger!B:B, _xlpm.party, ledger!E:E, "<>*RD*", ledger!D:D, "Silky", ledger!C:C, "<>January Closing CF") )) + _xlfn.IFNA(H111, 0)} -> 0 | Y18: {=_xlfn.BYROW(B62, _xlfn.LAMBDA(_xlpm.party, SUMIFS(ledger!J:J, ledger!B:B, _xlpm.party, ledger!E:E, "<>*RD*", ledger!D:D, "Slub", ledger!C:C, "<>January Closing CF") ))+ _xlfn.IFNA(I111, 0)} -> 0 | Z18: {=_xlfn.BYROW(B62, _xlfn.LAMBDA(_xlpm.party, SUMIFS(ledger!J:J, ledger!B:B, _xlpm.party, ledger!E:E, "<>*RD*", ledger!D:D, "Satin", ledger!C:C, "<>January Closing CF") ))+ _xlfn.IFNA(J111, 0)} -> 0 | AA18: {=_xlfn.BYROW(B62, _xlfn.LAMBDA(_xlpm.party, SUMIFS(ledger!J:J, ledger!B:B, _xlpm.party, ledger!E:E, "<>*RD*", ledger!D:D, "Black-Chamki", ledger!C:C, "<>January Closing CF") ))+ _xlfn.IFNA(K111, 0)} -> 0 | AB18: {=_xlfn.BYROW(B62, _xlfn.LAMBDA(_xlpm.party, SUMIFS(ledger!J:J, ledger!B:B, _xlpm.party, ledger!E:E, "<>*RD*", ledger!D:D, "Kataan", ledger!C:C, "<>January Closing CF") ))+ _xlfn.IFNA(L111, 0)} -> 0 | AC18: {=_xlfn.BYROW(B62, _xlfn.LAMBDA(_xlpm.party, SUMIFS(ledger!J:J, ledger!B:B, _xlpm.party, ledger!E:E, "<>*RD*", ledger!D:D, "Munaar", ledger!C:C, "<>January Closing CF") ))+ _xlfn.IFNA(M111, 0)} -> 0 | AD18: {=_xlfn.BYROW(B62, _xlfn.LAMBDA(_xlpm.party, SUMIFS(ledger!J:J, ledger!B:B, _xlpm.party, ledger!E:E, "<>*RD*", ledger!D:D, "Custom", ledger!C:C, "<>January Closing CF") ))+ _xlfn.IFNA(N111, 0)} -> 0 | AE18: =W18+X18+Y18+Z18+AA18+AB18+AC18+AD18 -> 483851.5 | AF18: =(SUMIF(Table14[Party],R18,Table14[Credit]))+_xlfn.IFNA(P111,0) -> 480000 | AG18: =AE18-AF18 -> 3851.4996 | AH18: 10 | AI18: 13
I19: Shafique Ansari | R19: Hazrat Khan | S19: {=_xlfn.BYROW(B63,_xlfn.LAMBDA(_xlpm.party,SUMIFS(ledger!G:G,ledger!B:B,_xlpm.party,ledger!E:E,"<>*RD*")))+_xlfn.IFNA(C112,0)} -> 9750 | T19: {=_xlfn.BYROW(B63, _xlfn.LAMBDA(_xlpm.party, SUMIFS(ledger!G:G, ledger!B:B, _xlpm.party, ledger!E:E, "<>*RD*") / 1.0936 ))+_xlfn.IFNA(D112,0)} -> 8915.5084 | U19: {=(_xlfn.BYROW(B63,_xlfn.LAMBDA(_xlpm.party,SUMIFS(ledger!G:G,ledger!B:B,_xlpm.party,ledger!E:E,"<>*RD*",ledger!D:D,"Chamki")+SUMIFS(ledger!G:G, ledger!B:B, _xlpm.party, ledger!E:E, "<>*RD*", ledger!D:D, "Crinkle")))/1.0936)+_xlfn.IFNA(E112,0)} -> 8915.5084 | V19: {=(_xlfn.BYROW(B63,_xlfn.LAMBDA(_xlpm.party,SUMIFS(ledger!G:G,ledger!B:B,_xlpm.party,ledger!E:E,"<>*RD*",ledger!D:D,"Silky")))/1.0936)+_xlfn.IFNA(F112,0)} -> 0 | W19: {=(_xlfn.BYROW(B63,_xlfn.LAMBDA(_xlpm.party, (SUMIFS(ledger!J:J,ledger!B:B,_xlpm.party,ledger!E:E,"<>*RD*",ledger!D:D,"Chamki",ledger!C:C,"<>January Closing CF")+ SUMIFS(ledger!J:J,ledger!B:B,_xlpm.party,ledger!E:E,"<>*RD*",ledger!D:D,"Crinkle",ledger!C:C,"<>January Closing CF") )+_xlfn.IFNA(G112,0))))} -> 89155.084 | X19: {=_xlfn.BYROW(B63, _xlfn.LAMBDA(_xlpm.party, SUMIFS(ledger!J:J, ledger!B:B, _xlpm.party, ledger!E:E, "<>*RD*", ledger!D:D, "Silky", ledger!C:C, "<>January Closing CF") )) + _xlfn.IFNA(H112, 0)} -> 0 | Y19: {=_xlfn.BYROW(B63, _xlfn.LAMBDA(_xlpm.party, SUMIFS(ledger!J:J, ledger!B:B, _xlpm.party, ledger!E:E, "<>*RD*", ledger!D:D, "Slub", ledger!C:C, "<>January Closing CF") ))+ _xlfn.IFNA(I112, 0)} -> 0 | Z19: {=_xlfn.BYROW(B63, _xlfn.LAMBDA(_xlpm.party, SUMIFS(ledger!J:J, ledger!B:B, _xlpm.party, ledger!E:E, "<>*RD*", ledger!D:D, "Satin", ledger!C:C, "<>January Closing CF") ))+ _xlfn.IFNA(J112, 0)} -> 0 | AA19: {=_xlfn.BYROW(B63, _xlfn.LAMBDA(_xlpm.party, SUMIFS(ledger!J:J, ledger!B:B, _xlpm.party, ledger!E:E, "<>*RD*", ledger!D:D, "Black-Chamki", ledger!C:C, "<>January Closing CF") ))+ _xlfn.IFNA(K112, 0)} -> 0 | AB19: {=_xlfn.BYROW(B63, _xlfn.LAMBDA(_xlpm.party, SUMIFS(ledger!J:J, ledger!B:B, _xlpm.party, ledger!E:E, "<>*RD*", ledger!D:D, "Kataan", ledger!C:C, "<>January Closing CF") ))+ _xlfn.IFNA(L112, 0)} -> 0 | AC19: {=_xlfn.BYROW(B63, _xlfn.LAMBDA(_xlpm.party, SUMIFS(ledger!J:J, ledger!B:B, _xlpm.party, ledger!E:E, "<>*RD*", ledger!D:D, "Munaar", ledger!C:C, "<>January Closing CF") ))+ _xlfn.IFNA(M112, 0)} -> 0 | AD19: {=_xlfn.BYROW(B63, _xlfn.LAMBDA(_xlpm.party, SUMIFS(ledger!J:J, ledger!B:B, _xlpm.party, ledger!E:E, "<>*RD*", ledger!D:D, "Custom", ledger!C:C, "<>January Closing CF") ))+ _xlfn.IFNA(N112, 0)} -> 0 | AE19: =W19+X19+Y19+Z19+AA19+AB19+AC19+AD19 -> 89155.084 | AF19: =(SUMIF(Table14[Party],R19,Table14[Credit]))+_xlfn.IFNA(P112,0) -> 95000 | AG19: =AE19-AF19 -> -5844.9159 | AH19: 10 | AI19: 13
I20: Amjad sohail | R20: Haseeb Shamsi | S20: {=_xlfn.BYROW(B64,_xlfn.LAMBDA(_xlpm.party,SUMIFS(ledger!G:G,ledger!B:B,_xlpm.party,ledger!E:E,"<>*RD*")))+_xlfn.IFNA(C113,0)} -> 61975 | T20: {=_xlfn.BYROW(B64, _xlfn.LAMBDA(_xlpm.party, SUMIFS(ledger!G:G, ledger!B:B, _xlpm.party, ledger!E:E, "<>*RD*") / 1.0936 ))+_xlfn.IFNA(D113,0)} -> 56670.629 | U20: {=(_xlfn.BYROW(B64,_xlfn.LAMBDA(_xlpm.party,SUMIFS(ledger!G:G,ledger!B:B,_xlpm.party,ledger!E:E,"<>*RD*",ledger!D:D,"Chamki")+SUMIFS(ledger!G:G, ledger!B:B, _xlpm.party, ledger!E:E, "<>*RD*", ledger!D:D, "Crinkle")))/1.0936)+_xlfn.IFNA(E113,0)} -> 47437.82 | V20: {=(_xlfn.BYROW(B64,_xlfn.LAMBDA(_xlpm.party,SUMIFS(ledger!G:G,ledger!B:B,_xlpm.party,ledger!E:E,"<>*RD*",ledger!D:D,"Silky")))/1.0936)+_xlfn.IFNA(F113,0)} -> 9232.8091 | W20: {=(_xlfn.BYROW(B64,_xlfn.LAMBDA(_xlpm.party, (SUMIFS(ledger!J:J,ledger!B:B,_xlpm.party,ledger!E:E,"<>*RD*",ledger!D:D,"Chamki",ledger!C:C,"<>January Closing CF")+ SUMIFS(ledger!J:J,ledger!B:B,_xlpm.party,ledger!E:E,"<>*RD*",ledger!D:D,"Crinkle",ledger!C:C,"<>January Closing CF") )+_xlfn.IFNA(G113,0))))} -> 474378.2 | X20: {=_xlfn.BYROW(B64, _xlfn.LAMBDA(_xlpm.party, SUMIFS(ledger!J:J, ledger!B:B, _xlpm.party, ledger!E:E, "<>*RD*", ledger!D:D, "Silky", ledger!C:C, "<>January Closing CF") )) + _xlfn.IFNA(H113, 0)} -> 120026.52 | Y20: {=_xlfn.BYROW(B64, _xlfn.LAMBDA(_xlpm.party, SUMIFS(ledger!J:J, ledger!B:B, _xlpm.party, ledger!E:E, "<>*RD*", ledger!D:D, "Slub", ledger!C:C, "<>January Closing CF") ))+ _xlfn.IFNA(I113, 0)} -> 0 | Z20: {=_xlfn.BYROW(B64, _xlfn.LAMBDA(_xlpm.party, SUMIFS(ledger!J:J, ledger!B:B, _xlpm.party, ledger!E:E, "<>*RD*", ledger!D:D, "Satin", ledger!C:C, "<>January Closing CF") ))+ _xlfn.IFNA(J113, 0)} -> 0 | AA20: {=_xlfn.BYROW(B64, _xlfn.LAMBDA(_xlpm.party, SUMIFS(ledger!J:J, ledger!B:B, _xlpm.party, ledger!E:E, "<>*RD*", ledger!D:D, "Black-Chamki", ledger!C:C, "<>January Closing CF") ))+ _xlfn.IFNA(K113, 0)} -> 0 | AB20: {=_xlfn.BYROW(B64, _xlfn.LAMBDA(_xlpm.party, SUMIFS(ledger!J:J, ledger!B:B, _xlpm.party, ledger!E:E, "<>*RD*", ledger!D:D, "Kataan", ledger!C:C, "<>January Closing CF") ))+ _xlfn.IFNA(L113, 0)} -> 0 | AC20: {=_xlfn.BYROW(B64, _xlfn.LAMBDA(_xlpm.party, SUMIFS(ledger!J:J, ledger!B:B, _xlpm.party, ledger!E:E, "<>*RD*", ledger!D:D, "Munaar", ledger!C:C, "<>January Closing CF") ))+ _xlfn.IFNA(M113, 0)} -> 0 | AD20: {=_xlfn.BYROW(B64, _xlfn.LAMBDA(_xlpm.party, SUMIFS(ledger!J:J, ledger!B:B, _xlpm.party, ledger!E:E, "<>*RD*", ledger!D:D, "Custom", ledger!C:C, "<>January Closing CF") ))+ _xlfn.IFNA(N113, 0)} -> 0 | AE20: =W20+X20+Y20+Z20+AA20+AB20+AC20+AD20 -> 594404.72 | AF20: =(SUMIF(Table14[Party],R20,Table14[Credit]))+_xlfn.IFNA(P113,0) -> 594405 | AG20: =AE20-AF20 -> -0.28163862 | AH20: 10 | AI20: 13
B21: Total: | C21: =SUM(O49:O85) -> 29036182 | D21: (Real Figure) | I21: Salman Zaffar | R21: Faizan | S21: {=_xlfn.BYROW(B65,_xlfn.LAMBDA(_xlpm.party,SUMIFS(ledger!G:G,ledger!B:B,_xlpm.party,ledger!E:E,"<>*RD*")))+_xlfn.IFNA(C114,0)} -> 565150 | T21: {=_xlfn.BYROW(B65, _xlfn.LAMBDA(_xlpm.party, SUMIFS(ledger!G:G, ledger!B:B, _xlpm.party, ledger!E:E, "<>*RD*") / 1.0936 ))+_xlfn.IFNA(D114,0)} -> 516779.44 | U21: {=(_xlfn.BYROW(B65,_xlfn.LAMBDA(_xlpm.party,SUMIFS(ledger!G:G,ledger!B:B,_xlpm.party,ledger!E:E,"<>*RD*",ledger!D:D,"Chamki")+SUMIFS(ledger!G:G, ledger!B:B, _xlpm.party, ledger!E:E, "<>*RD*", ledger!D:D, "Crinkle")))/1.0936)+_xlfn.IFNA(E114,0)} -> 0 | V21: {=(_xlfn.BYROW(B65,_xlfn.LAMBDA(_xlpm.party,SUMIFS(ledger!G:G,ledger!B:B,_xlpm.party,ledger!E:E,"<>*RD*",ledger!D:D,"Silky")))/1.0936)+_xlfn.IFNA(F114,0)} -> 513809.44 | W21: {=(_xlfn.BYROW(B65,_xlfn.LAMBDA(_xlpm.party, (SUMIFS(ledger!J:J,ledger!B:B,_xlpm.party,ledger!E:E,"<>*RD*",ledger!D:D,"Chamki",ledger!C:C,"<>January Closing CF")+ SUMIFS(ledger!J:J,ledger!B:B,_xlpm.party,ledger!E:E,"<>*RD*",ledger!D:D,"Crinkle",ledger!C:C,"<>January Closing CF") )+_xlfn.IFNA(G114,0))))} -> 30000 | X21: {=_xlfn.BYROW(B65, _xlfn.LAMBDA(_xlpm.party, SUMIFS(ledger!J:J, ledger!B:B, _xlpm.party, ledger!E:E, "<>*RD*", ledger!D:D, "Silky", ledger!C:C, "<>January Closing CF") )) + _xlfn.IFNA(H114, 0)} -> 6679522.7 | Y21: {=_xlfn.BYROW(B65, _xlfn.LAMBDA(_xlpm.party, SUMIFS(ledger!J:J, ledger!B:B, _xlpm.party, ledger!E:E, "<>*RD*", ledger!D:D, "Slub", ledger!C:C, "<>January Closing CF") ))+ _xlfn.IFNA(I114, 0)} -> 44550.11 | Z21: {=_xlfn.BYROW(B65, _xlfn.LAMBDA(_xlpm.party, SUMIFS(ledger!J:J, ledger!B:B, _xlpm.party, ledger!E:E, "<>*RD*", ledger!D:D, "Satin", ledger!C:C, "<>January Closing CF") ))+ _xlfn.IFNA(J114, 0)} -> 0 | AA21: {=_xlfn.BYROW(B65, _xlfn.LAMBDA(_xlpm.party, SUMIFS(ledger!J:J, ledger!B:B, _xlpm.party, ledger!E:E, "<>*RD*", ledger!D:D, "Black-Chamki", ledger!C:C, "<>January Closing CF") ))+ _xlfn.IFNA(K114, 0)} -> 0 | AB21: {=_xlfn.BYROW(B65, _xlfn.LAMBDA(_xlpm.party, SUMIFS(ledger!J:J, ledger!B:B, _xlpm.party, ledger!E:E, "<>*RD*", ledger!D:D, "Kataan", ledger!C:C, "<>January Closing CF") ))+ _xlfn.IFNA(L114, 0)} -> 0 | AC21: {=_xlfn.BYROW(B65, _xlfn.LAMBDA(_xlpm.party, SUMIFS(ledger!J:J, ledger!B:B, _xlpm.party, ledger!E:E, "<>*RD*", ledger!D:D, "Munaar", ledger!C:C, "<>January Closing CF") ))+ _xlfn.IFNA(M114, 0)} -> 0 | AD21: {=_xlfn.BYROW(B65, _xlfn.LAMBDA(_xlpm.party, SUMIFS(ledger!J:J, ledger!B:B, _xlpm.party, ledger!E:E, "<>*RD*", ledger!D:D, "Custom", ledger!C:C, "<>January Closing CF") ))+ _xlfn.IFNA(N114, 0)} -> 0 | AE21: =W21+X21+Y21+Z21+AA21+AB21+AC21+AD21 -> 6754072.8 | AF21: =(SUMIF(Table14[Party],R21,Table14[Credit]))+_xlfn.IFNA(P114,0) -> 6728187 | AG21: =AE21-AF21 -> 25885.787 | AH21: 10 | AI21: 13
I22: Shahid Qasayi | R22: Shafique Ansari | S22: {=_xlfn.BYROW(B66,_xlfn.LAMBDA(_xlpm.party,SUMIFS(ledger!G:G,ledger!B:B,_xlpm.party,ledger!E:E,"<>*RD*")))+_xlfn.IFNA(C115,0)} -> 82290 | T22: {=_xlfn.BYROW(B66, _xlfn.LAMBDA(_xlpm.party, SUMIFS(ledger!G:G, ledger!B:B, _xlpm.party, ledger!E:E, "<>*RD*") / 1.0936 ))+_xlfn.IFNA(D115,0)} -> 75246.891 | U22: {=(_xlfn.BYROW(B66,_xlfn.LAMBDA(_xlpm.party,SUMIFS(ledger!G:G,ledger!B:B,_xlpm.party,ledger!E:E,"<>*RD*",ledger!D:D,"Chamki")+SUMIFS(ledger!G:G, ledger!B:B, _xlpm.party, ledger!E:E, "<>*RD*", ledger!D:D, "Crinkle")))/1.0936)+_xlfn.IFNA(E115,0)} -> 64300.475 | V22: {=(_xlfn.BYROW(B66,_xlfn.LAMBDA(_xlpm.party,SUMIFS(ledger!G:G,ledger!B:B,_xlpm.party,ledger!E:E,"<>*RD*",ledger!D:D,"Silky")))/1.0936)+_xlfn.IFNA(F115,0)} -> 7565.8376 | W22: {=(_xlfn.BYROW(B66,_xlfn.LAMBDA(_xlpm.party, (SUMIFS(ledger!J:J,ledger!B:B,_xlpm.party,ledger!E:E,"<>*RD*",ledger!D:D,"Chamki",ledger!C:C,"<>January Closing CF")+ SUMIFS(ledger!J:J,ledger!B:B,_xlpm.party,ledger!E:E,"<>*RD*",ledger!D:D,"Crinkle",ledger!C:C,"<>January Closing CF") )+_xlfn.IFNA(G115,0))))} -> 643004.75 | X22: {=_xlfn.BYROW(B66, _xlfn.LAMBDA(_xlpm.party, SUMIFS(ledger!J:J, ledger!B:B, _xlpm.party, ledger!E:E, "<>*RD*", ledger!D:D, "Silky", ledger!C:C, "<>January Closing CF") )) + _xlfn.IFNA(H115, 0)} -> 98355.889 | Y22: {=_xlfn.BYROW(B66, _xlfn.LAMBDA(_xlpm.party, SUMIFS(ledger!J:J, ledger!B:B, _xlpm.party, ledger!E:E, "<>*RD*", ledger!D:D, "Slub", ledger!C:C, "<>January Closing CF") ))+ _xlfn.IFNA(I115, 0)} -> 0 | Z22: {=_xlfn.BYROW(B66, _xlfn.LAMBDA(_xlpm.party, SUMIFS(ledger!J:J, ledger!B:B, _xlpm.party, ledger!E:E, "<>*RD*", ledger!D:D, "Satin", ledger!C:C, "<>January Closing CF") ))+ _xlfn.IFNA(J115, 0)} -> 94656.181 | AA22: {=_xlfn.BYROW(B66, _xlfn.LAMBDA(_xlpm.party, SUMIFS(ledger!J:J, ledger!B:B, _xlpm.party, ledger!E:E, "<>*RD*", ledger!D:D, "Black-Chamki", ledger!C:C, "<>January Closing CF") ))+ _xlfn.IFNA(K115, 0)} -> 0 | AB22: {=_xlfn.BYROW(B66, _xlfn.LAMBDA(_xlpm.party, SUMIFS(ledger!J:J, ledger!B:B, _xlpm.party, ledger!E:E, "<>*RD*", ledger!D:D, "Kataan", ledger!C:C, "<>January Closing CF") ))+ _xlfn.IFNA(L115, 0)} -> 0 | AC22: {=_xlfn.BYROW(B66, _xlfn.LAMBDA(_xlpm.party, SUMIFS(ledger!J:J, ledger!B:B, _xlpm.party, ledger!E:E, "<>*RD*", ledger!D:D, "Munaar", ledger!C:C, "<>January Closing CF") ))+ _xlfn.IFNA(M115, 0)} -> 0 | AD22: {=_xlfn.BYROW(B66, _xlfn.LAMBDA(_xlpm.party, SUMIFS(ledger!J:J, ledger!B:B, _xlpm.party, ledger!E:E, "<>*RD*", ledger!D:D, "Custom", ledger!C:C, "<>January Closing CF") ))+ _xlfn.IFNA(N115, 0)} -> 0 | AE22: =W22+X22+Y22+Z22+AA22+AB22+AC22+AD22 -> 836016.83 | AF22: =(SUMIF(Table14[Party],R22,Table14[Credit]))+_xlfn.IFNA(P115,0) -> 835660 | AG22: =AE22-AF22 -> 356.82516 | AH22: 10 | AI22: 13
B23: Total influx | C23: =SUM(O49:O85) -> 29036182 | D23: (considering 10.5) | I23: Hameed corporation | R23: Amjad sohail | S23: {=_xlfn.BYROW(B67,_xlfn.LAMBDA(_xlpm.party,SUMIFS(ledger!G:G,ledger!B:B,_xlpm.party,ledger!E:E,"<>*RD*")))+_xlfn.IFNA(C116,0)} -> 501155 | T23: {=_xlfn.BYROW(B67, _xlfn.LAMBDA(_xlpm.party, SUMIFS(ledger!G:G, ledger!B:B, _xlpm.party, ledger!E:E, "<>*RD*") / 1.0936 ))+_xlfn.IFNA(D116,0)} -> 458261.7 | U23: {=(_xlfn.BYROW(B67,_xlfn.LAMBDA(_xlpm.party,SUMIFS(ledger!G:G,ledger!B:B,_xlpm.party,ledger!E:E,"<>*RD*",ledger!D:D,"Chamki")+SUMIFS(ledger!G:G, ledger!B:B, _xlpm.party, ledger!E:E, "<>*RD*", ledger!D:D, "Crinkle")))/1.0936)+_xlfn.IFNA(E116,0)} -> 362820.04 | V23: {=(_xlfn.BYROW(B67,_xlfn.LAMBDA(_xlpm.party,SUMIFS(ledger!G:G,ledger!B:B,_xlpm.party,ledger!E:E,"<>*RD*",ledger!D:D,"Silky")))/1.0936)+_xlfn.IFNA(F116,0)} -> 95441.661 | W23: {=(_xlfn.BYROW(B67,_xlfn.LAMBDA(_xlpm.party, (SUMIFS(ledger!J:J,ledger!B:B,_xlpm.party,ledger!E:E,"<>*RD*",ledger!D:D,"Chamki",ledger!C:C,"<>January Closing CF")+ SUMIFS(ledger!J:J,ledger!B:B,_xlpm.party,ledger!E:E,"<>*RD*",ledger!D:D,"Crinkle",ledger!C:C,"<>January Closing CF") )+_xlfn.IFNA(G116,0))))} -> 3628200.4 | X23: {=_xlfn.BYROW(B67, _xlfn.LAMBDA(_xlpm.party, SUMIFS(ledger!J:J, ledger!B:B, _xlpm.party, ledger!E:E, "<>*RD*", ledger!D:D, "Silky", ledger!C:C, "<>January Closing CF") )) + _xlfn.IFNA(H116, 0)} -> 1240741.6 | Y23: {=_xlfn.BYROW(B67, _xlfn.LAMBDA(_xlpm.party, SUMIFS(ledger!J:J, ledger!B:B, _xlpm.party, ledger!E:E, "<>*RD*", ledger!D:D, "Slub", ledger!C:C, "<>January Closing CF") ))+ _xlfn.IFNA(I116, 0)} -> 0 | Z23: {=_xlfn.BYROW(B67, _xlfn.LAMBDA(_xlpm.party, SUMIFS(ledger!J:J, ledger!B:B, _xlpm.party, ledger!E:E, "<>*RD*", ledger!D:D, "Satin", ledger!C:C, "<>January Closing CF") ))+ _xlfn.IFNA(J116, 0)} -> 0 | AA23: {=_xlfn.BYROW(B67, _xlfn.LAMBDA(_xlpm.party, SUMIFS(ledger!J:J, ledger!B:B, _xlpm.party, ledger!E:E, "<>*RD*", ledger!D:D, "Black-Chamki", ledger!C:C, "<>January Closing CF") ))+ _xlfn.IFNA(K116, 0)} -> 0 | AB23: {=_xlfn.BYROW(B67, _xlfn.LAMBDA(_xlpm.party, SUMIFS(ledger!J:J, ledger!B:B, _xlpm.party, ledger!E:E, "<>*RD*", ledger!D:D, "Kataan", ledger!C:C, "<>January Closing CF") ))+ _xlfn.IFNA(L116, 0)} -> 0 | AC23: {=_xlfn.BYROW(B67, _xlfn.LAMBDA(_xlpm.party, SUMIFS(ledger!J:J, ledger!B:B, _xlpm.party, ledger!E:E, "<>*RD*", ledger!D:D, "Munaar", ledger!C:C, "<>January Closing CF") ))+ _xlfn.IFNA(M116, 0)} -> 0 | AD23: {=_xlfn.BYROW(B67, _xlfn.LAMBDA(_xlpm.party, SUMIFS(ledger!J:J, ledger!B:B, _xlpm.party, ledger!E:E, "<>*RD*", ledger!D:D, "Custom", ledger!C:C, "<>January Closing CF") ))+ _xlfn.IFNA(N116, 0)} -> 0 | AE23: =W23+X23+Y23+Z23+AA23+AB23+AC23+AD23 -> 4868942 | AF23: =(SUMIF(Table14[Party],R23,Table14[Credit]))+_xlfn.IFNA(P116,0) -> 4417830 | AG23: =AE23-AF23 -> 451112.03 | AH23: 10 | AI23: 13
I24: ibraheem behraam | R24: Salman Zaffar | S24: {=_xlfn.BYROW(B68,_xlfn.LAMBDA(_xlpm.party,SUMIFS(ledger!G:G,ledger!B:B,_xlpm.party,ledger!E:E,"<>*RD*")))+_xlfn.IFNA(C117,0)} -> 344332 | T24: {=_xlfn.BYROW(B68, _xlfn.LAMBDA(_xlpm.party, SUMIFS(ledger!G:G, ledger!B:B, _xlpm.party, ledger!E:E, "<>*RD*") / 1.0936 ))+_xlfn.IFNA(D117,0)} -> 314861.01 | U24: {=(_xlfn.BYROW(B68,_xlfn.LAMBDA(_xlpm.party,SUMIFS(ledger!G:G,ledger!B:B,_xlpm.party,ledger!E:E,"<>*RD*",ledger!D:D,"Chamki")+SUMIFS(ledger!G:G, ledger!B:B, _xlpm.party, ledger!E:E, "<>*RD*", ledger!D:D, "Crinkle")))/1.0936)+_xlfn.IFNA(E117,0)} -> 72939.832 | V24: {=(_xlfn.BYROW(B68,_xlfn.LAMBDA(_xlpm.party,SUMIFS(ledger!G:G,ledger!B:B,_xlpm.party,ledger!E:E,"<>*RD*",ledger!D:D,"Silky")))/1.0936)+_xlfn.IFNA(F117,0)} -> 31409.108 | W24: {=(_xlfn.BYROW(B68,_xlfn.LAMBDA(_xlpm.party, (SUMIFS(ledger!J:J,ledger!B:B,_xlpm.party,ledger!E:E,"<>*RD*",ledger!D:D,"Chamki",ledger!C:C,"<>January Closing CF")+ SUMIFS(ledger!J:J,ledger!B:B,_xlpm.party,ledger!E:E,"<>*RD*",ledger!D:D,"Crinkle",ledger!C:C,"<>January Closing CF") )+_xlfn.IFNA(G117,0))))} -> 729398.32 | X24: {=_xlfn.BYROW(B68, _xlfn.LAMBDA(_xlpm.party, SUMIFS(ledger!J:J, ledger!B:B, _xlpm.party, ledger!E:E, "<>*RD*", ledger!D:D, "Silky", ledger!C:C, "<>January Closing CF") )) + _xlfn.IFNA(H117, 0)} -> 408318.4 | Y24: {=_xlfn.BYROW(B68, _xlfn.LAMBDA(_xlpm.party, SUMIFS(ledger!J:J, ledger!B:B, _xlpm.party, ledger!E:E, "<>*RD*", ledger!D:D, "Slub", ledger!C:C, "<>January Closing CF") ))+ _xlfn.IFNA(I117, 0)} -> 0 | Z24: {=_xlfn.BYROW(B68, _xlfn.LAMBDA(_xlpm.party, SUMIFS(ledger!J:J, ledger!B:B, _xlpm.party, ledger!E:E, "<>*RD*", ledger!D:D, "Satin", ledger!C:C, "<>January Closing CF") ))+ _xlfn.IFNA(J117, 0)} -> 0 | AA24: {=_xlfn.BYROW(B68, _xlfn.LAMBDA(_xlpm.party, SUMIFS(ledger!J:J, ledger!B:B, _xlpm.party, ledger!E:E, "<>*RD*", ledger!D:D, "Black-Chamki", ledger!C:C, "<>January Closing CF") ))+ _xlfn.IFNA(K117, 0)} -> 161653.26 | AB24: {=_xlfn.BYROW(B68, _xlfn.LAMBDA(_xlpm.party, SUMIFS(ledger!J:J, ledger!B:B, _xlpm.party, ledger!E:E, "<>*RD*", ledger!D:D, "Kataan", ledger!C:C, "<>January Closing CF") ))+ _xlfn.IFNA(L117, 0)} -> 1970409.7 | AC24: {=_xlfn.BYROW(B68, _xlfn.LAMBDA(_xlpm.party, SUMIFS(ledger!J:J, ledger!B:B, _xlpm.party, ledger!E:E, "<>*RD*", ledger!D:D, "Munaar", ledger!C:C, "<>January Closing CF") ))+ _xlfn.IFNA(M117, 0)} -> 0 | AD24: {=_xlfn.BYROW(B68, _xlfn.LAMBDA(_xlpm.party, SUMIFS(ledger!J:J, ledger!B:B, _xlpm.party, ledger!E:E, "<>*RD*", ledger!D:D, "Custom", ledger!C:C, "<>January Closing CF") ))+ _xlfn.IFNA(N117, 0)} -> 0 | AE24: =W24+X24+Y24+Z24+AA24+AB24+AC24+AD24 -> 3269779.6 | AF24: =(SUMIF(Table14[Party],R24,Table14[Credit]))+_xlfn.IFNA(P117,0) -> 3296025 | AG24: =AE24-AF24 -> -26245.373 | AH24: 10 | AI24: 13
I25: Zia-ullah karachi | R25: Shahid Qasayi | S25: {=_xlfn.BYROW(B69,_xlfn.LAMBDA(_xlpm.party,SUMIFS(ledger!G:G,ledger!B:B,_xlpm.party,ledger!E:E,"<>*RD*")))+_xlfn.IFNA(C118,0)} -> 477959 | T25: {=_xlfn.BYROW(B69, _xlfn.LAMBDA(_xlpm.party, SUMIFS(ledger!G:G, ledger!B:B, _xlpm.party, ledger!E:E, "<>*RD*") / 1.0936 ))+_xlfn.IFNA(D118,0)} -> 437051.02 | U25: {=(_xlfn.BYROW(B69,_xlfn.LAMBDA(_xlpm.party,SUMIFS(ledger!G:G,ledger!B:B,_xlpm.party,ledger!E:E,"<>*RD*",ledger!D:D,"Chamki")+SUMIFS(ledger!G:G, ledger!B:B, _xlpm.party, ledger!E:E, "<>*RD*", ledger!D:D, "Crinkle")))/1.0936)+_xlfn.IFNA(E118,0)} -> 387511.89 | V25: {=(_xlfn.BYROW(B69,_xlfn.LAMBDA(_xlpm.party,SUMIFS(ledger!G:G,ledger!B:B,_xlpm.party,ledger!E:E,"<>*RD*",ledger!D:D,"Silky")))/1.0936)+_xlfn.IFNA(F118,0)} -> 0 | W25: {=(_xlfn.BYROW(B69,_xlfn.LAMBDA(_xlpm.party, (SUMIFS(ledger!J:J,ledger!B:B,_xlpm.party,ledger!E:E,"<>*RD*",ledger!D:D,"Chamki",ledger!C:C,"<>January Closing CF")+ SUMIFS(ledger!J:J,ledger!B:B,_xlpm.party,ledger!E:E,"<>*RD*",ledger!D:D,"Crinkle",ledger!C:C,"<>January Closing CF") )+_xlfn.IFNA(G118,0))))} -> 3875118.9 | X25: {=_xlfn.BYROW(B69, _xlfn.LAMBDA(_xlpm.party, SUMIFS(ledger!J:J, ledger!B:B, _xlpm.party, ledger!E:E, "<>*RD*", ledger!D:D, "Silky", ledger!C:C, "<>January Closing CF") )) + _xlfn.IFNA(H118, 0)} -> 0 | Y25: {=_xlfn.BYROW(B69, _xlfn.LAMBDA(_xlpm.party, SUMIFS(ledger!J:J, ledger!B:B, _xlpm.party, ledger!E:E, "<>*RD*", ledger!D:D, "Slub", ledger!C:C, "<>January Closing CF") ))+ _xlfn.IFNA(I118, 0)} -> 0 | Z25: {=_xlfn.BYROW(B69, _xlfn.LAMBDA(_xlpm.party, SUMIFS(ledger!J:J, ledger!B:B, _xlpm.party, ledger!E:E, "<>*RD*", ledger!D:D, "Satin", ledger!C:C, "<>January Closing CF") ))+ _xlfn.IFNA(J118, 0)} -> 0 | AA25: {=_xlfn.BYROW(B69, _xlfn.LAMBDA(_xlpm.party, SUMIFS(ledger!J:J, ledger!B:B, _xlpm.party, ledger!E:E, "<>*RD*", ledger!D:D, "Black-Chamki", ledger!C:C, "<>January Closing CF") ))+ _xlfn.IFNA(K118, 0)} -> 23767.374 | AB25: {=_xlfn.BYROW(B69, _xlfn.LAMBDA(_xlpm.party, SUMIFS(ledger!J:J, ledger!B:B, _xlpm.party, ledger!E:E, "<>*RD*", ledger!D:D, "Kataan", ledger!C:C, "<>January Closing CF") ))+ _xlfn.IFNA(L118, 0)} -> 523143.75 | AC25: {=_xlfn.BYROW(B69, _xlfn.LAMBDA(_xlpm.party, SUMIFS(ledger!J:J, ledger!B:B, _xlpm.party, ledger!E:E, "<>*RD*", ledger!D:D, "Munaar", ledger!C:C, "<>January Closing CF") ))+ _xlfn.IFNA(M118, 0)} -> 0 | AD25: {=_xlfn.BYROW(B69, _xlfn.LAMBDA(_xlpm.party, SUMIFS(ledger!J:J, ledger!B:B, _xlpm.party, ledger!E:E, "<>*RD*", ledger!D:D, "Custom", ledger!C:C, "<>January Closing CF") ))+ _xlfn.IFNA(N118, 0)} -> 0 | AE25: =W25+X25+Y25+Z25+AA25+AB25+AC25+AD25 -> 4422030 | AF25: =(SUMIF(Table14[Party],R25,Table14[Credit]))+_xlfn.IFNA(P118,0) -> 3845477 | AG25: =AE25-AF25 -> 576552.99 | AH25: 10 | AI25: 13
I26: ZA | R26: Hameed corporation | S26: {=_xlfn.BYROW(B70,_xlfn.LAMBDA(_xlpm.party,SUMIFS(ledger!G:G,ledger!B:B,_xlpm.party,ledger!E:E,"<>*RD*")))+_xlfn.IFNA(C119,0)} -> 46404 | T26: {=_xlfn.BYROW(B70, _xlfn.LAMBDA(_xlpm.party, SUMIFS(ledger!G:G, ledger!B:B, _xlpm.party, ledger!E:E, "<>*RD*") / 1.0936 ))+_xlfn.IFNA(D119,0)} -> 42432.334 | U26: {=(_xlfn.BYROW(B70,_xlfn.LAMBDA(_xlpm.party,SUMIFS(ledger!G:G,ledger!B:B,_xlpm.party,ledger!E:E,"<>*RD*",ledger!D:D,"Chamki")+SUMIFS(ledger!G:G, ledger!B:B, _xlpm.party, ledger!E:E, "<>*RD*", ledger!D:D, "Crinkle")))/1.0936)+_xlfn.IFNA(E119,0)} -> 42432.334 | V26: {=(_xlfn.BYROW(B70,_xlfn.LAMBDA(_xlpm.party,SUMIFS(ledger!G:G,ledger!B:B,_xlpm.party,ledger!E:E,"<>*RD*",ledger!D:D,"Silky")))/1.0936)+_xlfn.IFNA(F119,0)} -> 0 | W26: {=(_xlfn.BYROW(B70,_xlfn.LAMBDA(_xlpm.party, (SUMIFS(ledger!J:J,ledger!B:B,_xlpm.party,ledger!E:E,"<>*RD*",ledger!D:D,"Chamki",ledger!C:C,"<>January Closing CF")+ SUMIFS(ledger!J:J,ledger!B:B,_xlpm.party,ledger!E:E,"<>*RD*",ledger!D:D,"Crinkle",ledger!C:C,"<>January Closing CF") )+_xlfn.IFNA(G119,0))))} -> 424323.34 | X26: {=_xlfn.BYROW(B70, _xlfn.LAMBDA(_xlpm.party, SUMIFS(ledger!J:J, ledger!B:B, _xlpm.party, ledger!E:E, "<>*RD*", ledger!D:D, "Silky", ledger!C:C, "<>January Closing CF") )) + _xlfn.IFNA(H119, 0)} -> 0 | Y26: {=_xlfn.BYROW(B70, _xlfn.LAMBDA(_xlpm.party, SUMIFS(ledger!J:J, ledger!B:B, _xlpm.party, ledger!E:E, "<>*RD*", ledger!D:D, "Slub", ledger!C:C, "<>January Closing CF") ))+ _xlfn.IFNA(I119, 0)} -> 0 | Z26: {=_xlfn.BYROW(B70, _xlfn.LAMBDA(_xlpm.party, SUMIFS(ledger!J:J, ledger!B:B, _xlpm.party, ledger!E:E, "<>*RD*", ledger!D:D, "Satin", ledger!C:C, "<>January Closing CF") ))+ _xlfn.IFNA(J119, 0)} -> 0 | AA26: {=_xlfn.BYROW(B70, _xlfn.LAMBDA(_xlpm.party, SUMIFS(ledger!J:J, ledger!B:B, _xlpm.party, ledger!E:E, "<>*RD*", ledger!D:D, "Black-Chamki", ledger!C:C, "<>January Closing CF") ))+ _xlfn.IFNA(K119, 0)} -> 0 | AB26: {=_xlfn.BYROW(B70, _xlfn.LAMBDA(_xlpm.party, SUMIFS(ledger!J:J, ledger!B:B, _xlpm.party, ledger!E:E, "<>*RD*", ledger!D:D, "Kataan", ledger!C:C, "<>January Closing CF") ))+ _xlfn.IFNA(L119, 0)} -> 0 | AC26: {=_xlfn.BYROW(B70, _xlfn.LAMBDA(_xlpm.party, SUMIFS(ledger!J:J, ledger!B:B, _xlpm.party, ledger!E:E, "<>*RD*", ledger!D:D, "Munaar", ledger!C:C, "<>January Closing CF") ))+ _xlfn.IFNA(M119, 0)} -> 0 | AD26: {=_xlfn.BYROW(B70, _xlfn.LAMBDA(_xlpm.party, SUMIFS(ledger!J:J, ledger!B:B, _xlpm.party, ledger!E:E, "<>*RD*", ledger!D:D, "Custom", ledger!C:C, "<>January Closing CF") ))+ _xlfn.IFNA(N119, 0)} -> 0 | AE26: =W26+X26+Y26+Z26+AA26+AB26+AC26+AD26 -> 424323.34 | AF26: =(SUMIF(Table14[Party],R26,Table14[Credit]))+_xlfn.IFNA(P119,0) -> 424323 | AG26: =AE26-AF26 -> 0.33577176 | AH26: 10 | AI26: 13
I27: Ahmad Javaid | R27: ibraheem behraam | S27: {=_xlfn.BYROW(B71,_xlfn.LAMBDA(_xlpm.party,SUMIFS(ledger!G:G,ledger!B:B,_xlpm.party,ledger!E:E,"<>*RD*")))+_xlfn.IFNA(C120,0)} -> 160320 | T27: {=_xlfn.BYROW(B71, _xlfn.LAMBDA(_xlpm.party, SUMIFS(ledger!G:G, ledger!B:B, _xlpm.party, ledger!E:E, "<>*RD*") / 1.0936 ))+_xlfn.IFNA(D120,0)} -> 146598.39 | U27: {=(_xlfn.BYROW(B71,_xlfn.LAMBDA(_xlpm.party,SUMIFS(ledger!G:G,ledger!B:B,_xlpm.party,ledger!E:E,"<>*RD*",ledger!D:D,"Chamki")+SUMIFS(ledger!G:G, ledger!B:B, _xlpm.party, ledger!E:E, "<>*RD*", ledger!D:D, "Crinkle")))/1.0936)+_xlfn.IFNA(E120,0)} -> 0 | V27: {=(_xlfn.BYROW(B71,_xlfn.LAMBDA(_xlpm.party,SUMIFS(ledger!G:G,ledger!B:B,_xlpm.party,ledger!E:E,"<>*RD*",ledger!D:D,"Silky")))/1.0936)+_xlfn.IFNA(F120,0)} -> 146598.39 | W27: {=(_xlfn.BYROW(B71,_xlfn.LAMBDA(_xlpm.party, (SUMIFS(ledger!J:J,ledger!B:B,_xlpm.party,ledger!E:E,"<>*RD*",ledger!D:D,"Chamki",ledger!C:C,"<>January Closing CF")+ SUMIFS(ledger!J:J,ledger!B:B,_xlpm.party,ledger!E:E,"<>*RD*",ledger!D:D,"Crinkle",ledger!C:C,"<>January Closing CF") )+_xlfn.IFNA(G120,0))))} -> 0 | X27: {=_xlfn.BYROW(B71, _xlfn.LAMBDA(_xlpm.party, SUMIFS(ledger!J:J, ledger!B:B, _xlpm.party, ledger!E:E, "<>*RD*", ledger!D:D, "Silky", ledger!C:C, "<>January Closing CF") )) + _xlfn.IFNA(H120, 0)} -> 1905779.1 | Y27: {=_xlfn.BYROW(B71, _xlfn.LAMBDA(_xlpm.party, SUMIFS(ledger!J:J, ledger!B:B, _xlpm.party, ledger!E:E, "<>*RD*", ledger!D:D, "Slub", ledger!C:C, "<>January Closing CF") ))+ _xlfn.IFNA(I120, 0)} -> 0 | Z27: {=_xlfn.BYROW(B71, _xlfn.LAMBDA(_xlpm.party, SUMIFS(ledger!J:J, ledger!B:B, _xlpm.party, ledger!E:E, "<>*RD*", ledger!D:D, "Satin", ledger!C:C, "<>January Closing CF") ))+ _xlfn.IFNA(J120, 0)} -> 0 | AA27: {=_xlfn.BYROW(B71, _xlfn.LAMBDA(_xlpm.party, SUMIFS(ledger!J:J, ledger!B:B, _xlpm.party, ledger!E:E, "<>*RD*", ledger!D:D, "Black-Chamki", ledger!C:C, "<>January Closing CF") ))+ _xlfn.IFNA(K120, 0)} -> 0 | AB27: {=_xlfn.BYROW(B71, _xlfn.LAMBDA(_xlpm.party, SUMIFS(ledger!J:J, ledger!B:B, _xlpm.party, ledger!E:E, "<>*RD*", ledger!D:D, "Kataan", ledger!C:C, "<>January Closing CF") ))+ _xlfn.IFNA(L120, 0)} -> 0 | AC27: {=_xlfn.BYROW(B71, _xlfn.LAMBDA(_xlpm.party, SUMIFS(ledger!J:J, ledger!B:B, _xlpm.party, ledger!E:E, "<>*RD*", ledger!D:D, "Munaar", ledger!C:C, "<>January Closing CF") ))+ _xlfn.IFNA(M120, 0)} -> 0 | AD27: {=_xlfn.BYROW(B71, _xlfn.LAMBDA(_xlpm.party, SUMIFS(ledger!J:J, ledger!B:B, _xlpm.party, ledger!E:E, "<>*RD*", ledger!D:D, "Custom", ledger!C:C, "<>January Closing CF") ))+ _xlfn.IFNA(N120, 0)} -> 0 | AE27: =W27+X27+Y27+Z27+AA27+AB27+AC27+AD27 -> 1905779.1 | AF27: =(SUMIF(Table14[Party],R27,Table14[Credit]))+_xlfn.IFNA(P120,0) -> 1723500 | AG27: =AE27-AF27 -> 182279.08 | AH27: 10 | AI27: 13
R28: Zia-ullah karachi | S28: {=_xlfn.BYROW(B72,_xlfn.LAMBDA(_xlpm.party,SUMIFS(ledger!G:G,ledger!B:B,_xlpm.party,ledger!E:E,"<>*RD*")))+_xlfn.IFNA(C121,0)} -> 13622 | T28: {=_xlfn.BYROW(B72, _xlfn.LAMBDA(_xlpm.party, SUMIFS(ledger!G:G, ledger!B:B, _xlpm.party, ledger!E:E, "<>*RD*") / 1.0936 ))+_xlfn.IFNA(D121,0)} -> 12456.108 | U28: {=(_xlfn.BYROW(B72,_xlfn.LAMBDA(_xlpm.party,SUMIFS(ledger!G:G,ledger!B:B,_xlpm.party,ledger!E:E,"<>*RD*",ledger!D:D,"Chamki")+SUMIFS(ledger!G:G, ledger!B:B, _xlpm.party, ledger!E:E, "<>*RD*", ledger!D:D, "Crinkle")))/1.0936)+_xlfn.IFNA(E121,0)} -> 12456.108 | V28: {=(_xlfn.BYROW(B72,_xlfn.LAMBDA(_xlpm.party,SUMIFS(ledger!G:G,ledger!B:B,_xlpm.party,ledger!E:E,"<>*RD*",ledger!D:D,"Silky")))/1.0936)+_xlfn.IFNA(F121,0)} -> 0 | W28: {=(_xlfn.BYROW(B72,_xlfn.LAMBDA(_xlpm.party, (SUMIFS(ledger!J:J,ledger!B:B,_xlpm.party,ledger!E:E,"<>*RD*",ledger!D:D,"Chamki",ledger!C:C,"<>January Closing CF")+ SUMIFS(ledger!J:J,ledger!B:B,_xlpm.party,ledger!E:E,"<>*RD*",ledger!D:D,"Crinkle",ledger!C:C,"<>January Closing CF") )+_xlfn.IFNA(G121,0))))} -> 124561.08 | X28: {=_xlfn.BYROW(B72, _xlfn.LAMBDA(_xlpm.party, SUMIFS(ledger!J:J, ledger!B:B, _xlpm.party, ledger!E:E, "<>*RD*", ledger!D:D, "Silky", ledger!C:C, "<>January Closing CF") )) + _xlfn.IFNA(H121, 0)} -> 0 | Y28: {=_xlfn.BYROW(B72, _xlfn.LAMBDA(_xlpm.party, SUMIFS(ledger!J:J, ledger!B:B, _xlpm.party, ledger!E:E, "<>*RD*", ledger!D:D, "Slub", ledger!C:C, "<>January Closing CF") ))+ _xlfn.IFNA(I121, 0)} -> 0 | Z28: {=_xlfn.BYROW(B72, _xlfn.LAMBDA(_xlpm.party, SUMIFS(ledger!J:J, ledger!B:B, _xlpm.party, ledger!E:E, "<>*RD*", ledger!D:D, "Satin", ledger!C:C, "<>January Closing CF") ))+ _xlfn.IFNA(J121, 0)} -> 0 | AA28: {=_xlfn.BYROW(B72, _xlfn.LAMBDA(_xlpm.party, SUMIFS(ledger!J:J, ledger!B:B, _xlpm.party, ledger!E:E, "<>*RD*", ledger!D:D, "Black-Chamki", ledger!C:C, "<>January Closing CF") ))+ _xlfn.IFNA(K121, 0)} -> 0 | AB28: {=_xlfn.BYROW(B72, _xlfn.LAMBDA(_xlpm.party, SUMIFS(ledger!J:J, ledger!B:B, _xlpm.party, ledger!E:E, "<>*RD*", ledger!D:D, "Kataan", ledger!C:C, "<>January Closing CF") ))+ _xlfn.IFNA(L121, 0)} -> 0 | AC28: {=_xlfn.BYROW(B72, _xlfn.LAMBDA(_xlpm.party, SUMIFS(ledger!J:J, ledger!B:B, _xlpm.party, ledger!E:E, "<>*RD*", ledger!D:D, "Munaar", ledger!C:C, "<>January Closing CF") ))+ _xlfn.IFNA(M121, 0)} -> 0 | AD28: {=_xlfn.BYROW(B72, _xlfn.LAMBDA(_xlpm.party, SUMIFS(ledger!J:J, ledger!B:B, _xlpm.party, ledger!E:E, "<>*RD*", ledger!D:D, "Custom", ledger!C:C, "<>January Closing CF") ))+ _xlfn.IFNA(N121, 0)} -> 0 | AE28: =W28+X28+Y28+Z28+AA28+AB28+AC28+AD28 -> 124561.08 | AF28: =(SUMIF(Table14[Party],R28,Table14[Credit]))+_xlfn.IFNA(P121,0) -> 124560 | AG28: =AE28-AF28 -> 1.0826628 | AH28: 10 | AI28: 13
R29: ZA | S29: {=_xlfn.BYROW(B73,_xlfn.LAMBDA(_xlpm.party,SUMIFS(ledger!G:G,ledger!B:B,_xlpm.party,ledger!E:E,"<>*RD*")))+_xlfn.IFNA(C122,0)} -> 32399 | T29: {=_xlfn.BYROW(B73, _xlfn.LAMBDA(_xlpm.party, SUMIFS(ledger!G:G, ledger!B:B, _xlpm.party, ledger!E:E, "<>*RD*") / 1.0936 ))+_xlfn.IFNA(D122,0)} -> 29626.006 | U29: {=(_xlfn.BYROW(B73,_xlfn.LAMBDA(_xlpm.party,SUMIFS(ledger!G:G,ledger!B:B,_xlpm.party,ledger!E:E,"<>*RD*",ledger!D:D,"Chamki")+SUMIFS(ledger!G:G, ledger!B:B, _xlpm.party, ledger!E:E, "<>*RD*", ledger!D:D, "Crinkle")))/1.0936)+_xlfn.IFNA(E122,0)} -> 0 | V29: {=(_xlfn.BYROW(B73,_xlfn.LAMBDA(_xlpm.party,SUMIFS(ledger!G:G,ledger!B:B,_xlpm.party,ledger!E:E,"<>*RD*",ledger!D:D,"Silky")))/1.0936)+_xlfn.IFNA(F122,0)} -> 29626.006 | W29: {=(_xlfn.BYROW(B73,_xlfn.LAMBDA(_xlpm.party, (SUMIFS(ledger!J:J,ledger!B:B,_xlpm.party,ledger!E:E,"<>*RD*",ledger!D:D,"Chamki",ledger!C:C,"<>January Closing CF")+ SUMIFS(ledger!J:J,ledger!B:B,_xlpm.party,ledger!E:E,"<>*RD*",ledger!D:D,"Crinkle",ledger!C:C,"<>January Closing CF") )+_xlfn.IFNA(G122,0))))} -> 0 | X29: {=_xlfn.BYROW(B73, _xlfn.LAMBDA(_xlpm.party, SUMIFS(ledger!J:J, ledger!B:B, _xlpm.party, ledger!E:E, "<>*RD*", ledger!D:D, "Silky", ledger!C:C, "<>January Closing CF") )) + _xlfn.IFNA(H122, 0)} -> 385138.08 | Y29: {=_xlfn.BYROW(B73, _xlfn.LAMBDA(_xlpm.party, SUMIFS(ledger!J:J, ledger!B:B, _xlpm.party, ledger!E:E, "<>*RD*", ledger!D:D, "Slub", ledger!C:C, "<>January Closing CF") ))+ _xlfn.IFNA(I122, 0)} -> 0 | Z29: {=_xlfn.BYROW(B73, _xlfn.LAMBDA(_xlpm.party, SUMIFS(ledger!J:J, ledger!B:B, _xlpm.party, ledger!E:E, "<>*RD*", ledger!D:D, "Satin", ledger!C:C, "<>January Closing CF") ))+ _xlfn.IFNA(J122, 0)} -> 0 | AA29: {=_xlfn.BYROW(B73, _xlfn.LAMBDA(_xlpm.party, SUMIFS(ledger!J:J, ledger!B:B, _xlpm.party, ledger!E:E, "<>*RD*", ledger!D:D, "Black-Chamki", ledger!C:C, "<>January Closing CF") ))+ _xlfn.IFNA(K122, 0)} -> 0 | AB29: {=_xlfn.BYROW(B73, _xlfn.LAMBDA(_xlpm.party, SUMIFS(ledger!J:J, ledger!B:B, _xlpm.party, ledger!E:E, "<>*RD*", ledger!D:D, "Kataan", ledger!C:C, "<>January Closing CF") ))+ _xlfn.IFNA(L122, 0)} -> 0 | AC29: {=_xlfn.BYROW(B73, _xlfn.LAMBDA(_xlpm.party, SUMIFS(ledger!J:J, ledger!B:B, _xlpm.party, ledger!E:E, "<>*RD*", ledger!D:D, "Munaar", ledger!C:C, "<>January Closing CF") ))+ _xlfn.IFNA(M122, 0)} -> 0 | AD29: {=_xlfn.BYROW(B73, _xlfn.LAMBDA(_xlpm.party, SUMIFS(ledger!J:J, ledger!B:B, _xlpm.party, ledger!E:E, "<>*RD*", ledger!D:D, "Custom", ledger!C:C, "<>January Closing CF") ))+ _xlfn.IFNA(N122, 0)} -> 0 | AE29: =W29+X29+Y29+Z29+AA29+AB29+AC29+AD29 -> 385138.08 | AF29: =(SUMIF(Table14[Party],R29,Table14[Credit]))+_xlfn.IFNA(P122,0) -> 385000 | AG29: =AE29-AF29 -> 138.07608 | AH29: 10 | AI29: 13
R30: Ahmad Javaid | S30: {=_xlfn.BYROW(B74,_xlfn.LAMBDA(_xlpm.party,SUMIFS(ledger!G:G,ledger!B:B,_xlpm.party,ledger!E:E,"<>*RD*")))+_xlfn.IFNA(C123,0)} -> 12745 | T30: {=_xlfn.BYROW(B74, _xlfn.LAMBDA(_xlpm.party, SUMIFS(ledger!G:G, ledger!B:B, _xlpm.party, ledger!E:E, "<>*RD*") / 1.0936 ))+_xlfn.IFNA(D123,0)} -> 11654.17 | U30: {=(_xlfn.BYROW(B74,_xlfn.LAMBDA(_xlpm.party,SUMIFS(ledger!G:G,ledger!B:B,_xlpm.party,ledger!E:E,"<>*RD*",ledger!D:D,"Chamki")+SUMIFS(ledger!G:G, ledger!B:B, _xlpm.party, ledger!E:E, "<>*RD*", ledger!D:D, "Crinkle")))/1.0936)+_xlfn.IFNA(E123,0)} -> 0 | V30: {=(_xlfn.BYROW(B74,_xlfn.LAMBDA(_xlpm.party,SUMIFS(ledger!G:G,ledger!B:B,_xlpm.party,ledger!E:E,"<>*RD*",ledger!D:D,"Silky")))/1.0936)+_xlfn.IFNA(F123,0)} -> 0 | W30: {=(_xlfn.BYROW(B74,_xlfn.LAMBDA(_xlpm.party, (SUMIFS(ledger!J:J,ledger!B:B,_xlpm.party,ledger!E:E,"<>*RD*",ledger!D:D,"Chamki",ledger!C:C,"<>January Closing CF")+ SUMIFS(ledger!J:J,ledger!B:B,_xlpm.party,ledger!E:E,"<>*RD*",ledger!D:D,"Crinkle",ledger!C:C,"<>January Closing CF") )+_xlfn.IFNA(G123,0))))} -> 0 | X30: {=_xlfn.BYROW(B74, _xlfn.LAMBDA(_xlpm.party, SUMIFS(ledger!J:J, ledger!B:B, _xlpm.party, ledger!E:E, "<>*RD*", ledger!D:D, "Silky", ledger!C:C, "<>January Closing CF") )) + _xlfn.IFNA(H123, 0)} -> 0 | Y30: {=_xlfn.BYROW(B74, _xlfn.LAMBDA(_xlpm.party, SUMIFS(ledger!J:J, ledger!B:B, _xlpm.party, ledger!E:E, "<>*RD*", ledger!D:D, "Slub", ledger!C:C, "<>January Closing CF") ))+ _xlfn.IFNA(I123, 0)} -> 0 | Z30: {=_xlfn.BYROW(B74, _xlfn.LAMBDA(_xlpm.party, SUMIFS(ledger!J:J, ledger!B:B, _xlpm.party, ledger!E:E, "<>*RD*", ledger!D:D, "Satin", ledger!C:C, "<>January Closing CF") ))+ _xlfn.IFNA(J123, 0)} -> 0 | AA30: {=_xlfn.BYROW(B74, _xlfn.LAMBDA(_xlpm.party, SUMIFS(ledger!J:J, ledger!B:B, _xlpm.party, ledger!E:E, "<>*RD*", ledger!D:D, "Black-Chamki", ledger!C:C, "<>January Closing CF") ))+ _xlfn.IFNA(K123, 0)} -> 0 | AB30: {=_xlfn.BYROW(B74, _xlfn.LAMBDA(_xlpm.party, SUMIFS(ledger!J:J, ledger!B:B, _xlpm.party, ledger!E:E, "<>*RD*", ledger!D:D, "Kataan", ledger!C:C, "<>January Closing CF") ))+ _xlfn.IFNA(L123, 0)} -> 0 | AC30: {=_xlfn.BYROW(B74, _xlfn.LAMBDA(_xlpm.party, SUMIFS(ledger!J:J, ledger!B:B, _xlpm.party, ledger!E:E, "<>*RD*", ledger!D:D, "Munaar", ledger!C:C, "<>January Closing CF") ))+ _xlfn.IFNA(M123, 0)} -> 151504.21 | AD30: {=_xlfn.BYROW(B74, _xlfn.LAMBDA(_xlpm.party, SUMIFS(ledger!J:J, ledger!B:B, _xlpm.party, ledger!E:E, "<>*RD*", ledger!D:D, "Custom", ledger!C:C, "<>January Closing CF") ))+ _xlfn.IFNA(N123, 0)} -> 0 | AE30: =W30+X30+Y30+Z30+AA30+AB30+AC30+AD30 -> 151504.21 | AF30: =(SUMIF(Table14[Party],R30,Table14[Credit]))+_xlfn.IFNA(P123,0) -> 130000 | AG30: =AE30-AF30 -> 21504.206 | AH30: 10 | AI30: 13
R31: Shani Badshah | S31: {=_xlfn.BYROW(B75,_xlfn.LAMBDA(_xlpm.party,SUMIFS(ledger!G:G,ledger!B:B,_xlpm.party,ledger!E:E,"<>*RD*")))+_xlfn.IFNA(C124,0)} -> 312320 | T31: {=_xlfn.BYROW(B75, _xlfn.LAMBDA(_xlpm.party, SUMIFS(ledger!G:G, ledger!B:B, _xlpm.party, ledger!E:E, "<>*RD*") / 1.0936 ))+_xlfn.IFNA(D124,0)} -> 285588.88 | U31: {=(_xlfn.BYROW(B75,_xlfn.LAMBDA(_xlpm.party,SUMIFS(ledger!G:G,ledger!B:B,_xlpm.party,ledger!E:E,"<>*RD*",ledger!D:D,"Chamki")+SUMIFS(ledger!G:G, ledger!B:B, _xlpm.party, ledger!E:E, "<>*RD*", ledger!D:D, "Crinkle")))/1.0936)+_xlfn.IFNA(E124,0)} -> 198861.56 | V31: {=(_xlfn.BYROW(B75,_xlfn.LAMBDA(_xlpm.party,SUMIFS(ledger!G:G,ledger!B:B,_xlpm.party,ledger!E:E,"<>*RD*",ledger!D:D,"Silky")))/1.0936)+_xlfn.IFNA(F124,0)} -> 86727.323 | W31: {=(_xlfn.BYROW(B75,_xlfn.LAMBDA(_xlpm.party, (SUMIFS(ledger!J:J,ledger!B:B,_xlpm.party,ledger!E:E,"<>*RD*",ledger!D:D,"Chamki",ledger!C:C,"<>January Closing CF")+ SUMIFS(ledger!J:J,ledger!B:B,_xlpm.party,ledger!E:E,"<>*RD*",ledger!D:D,"Crinkle",ledger!C:C,"<>January Closing CF") )+_xlfn.IFNA(G124,0))))} -> 1988615.6 | X31: {=_xlfn.BYROW(B75, _xlfn.LAMBDA(_xlpm.party, SUMIFS(ledger!J:J, ledger!B:B, _xlpm.party, ledger!E:E, "<>*RD*", ledger!D:D, "Silky", ledger!C:C, "<>January Closing CF") )) + _xlfn.IFNA(H124, 0)} -> 1127455.2 | Y31: {=_xlfn.BYROW(B75, _xlfn.LAMBDA(_xlpm.party, SUMIFS(ledger!J:J, ledger!B:B, _xlpm.party, ledger!E:E, "<>*RD*", ledger!D:D, "Slub", ledger!C:C, "<>January Closing CF") ))+ _xlfn.IFNA(I124, 0)} -> 0 | Z31: {=_xlfn.BYROW(B75, _xlfn.LAMBDA(_xlpm.party, SUMIFS(ledger!J:J, ledger!B:B, _xlpm.party, ledger!E:E, "<>*RD*", ledger!D:D, "Satin", ledger!C:C, "<>January Closing CF") ))+ _xlfn.IFNA(J124, 0)} -> 0 | AA31: {=_xlfn.BYROW(B75, _xlfn.LAMBDA(_xlpm.party, SUMIFS(ledger!J:J, ledger!B:B, _xlpm.party, ledger!E:E, "<>*RD*", ledger!D:D, "Black-Chamki", ledger!C:C, "<>January Closing CF") ))+ _xlfn.IFNA(K124, 0)} -> 0 | AB31: {=_xlfn.BYROW(B75, _xlfn.LAMBDA(_xlpm.party, SUMIFS(ledger!J:J, ledger!B:B, _xlpm.party, ledger!E:E, "<>*RD*", ledger!D:D, "Kataan", ledger!C:C, "<>January Closing CF") ))+ _xlfn.IFNA(L124, 0)} -> 0 | AC31: {=_xlfn.BYROW(B75, _xlfn.LAMBDA(_xlpm.party, SUMIFS(ledger!J:J, ledger!B:B, _xlpm.party, ledger!E:E, "<>*RD*", ledger!D:D, "Munaar", ledger!C:C, "<>January Closing CF") ))+ _xlfn.IFNA(M124, 0)} -> 0 | AD31: {=_xlfn.BYROW(B75, _xlfn.LAMBDA(_xlpm.party, SUMIFS(ledger!J:J, ledger!B:B, _xlpm.party, ledger!E:E, "<>*RD*", ledger!D:D, "Custom", ledger!C:C, "<>January Closing CF") ))+ _xlfn.IFNA(N124, 0)} -> 0 | AE31: =W31+X31+Y31+Z31+AA31+AB31+AC31+AD31 -> 3116070.8 | AF31: =(SUMIF(Table14[Party],R31,Table14[Credit]))+_xlfn.IFNA(P124,0) -> 3116071 | AG31: =AE31-AF31 -> -0.22457937 | AH31: 10 | AI31: 13
R32: Rehman Ali | S32: {=_xlfn.BYROW(B76,_xlfn.LAMBDA(_xlpm.party,SUMIFS(ledger!G:G,ledger!B:B,_xlpm.party,ledger!E:E,"<>*RD*")))+_xlfn.IFNA(C125,0)} -> 50131 | T32: {=_xlfn.BYROW(B76, _xlfn.LAMBDA(_xlpm.party, SUMIFS(ledger!G:G, ledger!B:B, _xlpm.party, ledger!E:E, "<>*RD*") / 1.0936 ))+_xlfn.IFNA(D125,0)} -> 45840.344 | U32: {=(_xlfn.BYROW(B76,_xlfn.LAMBDA(_xlpm.party,SUMIFS(ledger!G:G,ledger!B:B,_xlpm.party,ledger!E:E,"<>*RD*",ledger!D:D,"Chamki")+SUMIFS(ledger!G:G, ledger!B:B, _xlpm.party, ledger!E:E, "<>*RD*", ledger!D:D, "Crinkle")))/1.0936)+_xlfn.IFNA(E125,0)} -> 0 | V32: {=(_xlfn.BYROW(B76,_xlfn.LAMBDA(_xlpm.party,SUMIFS(ledger!G:G,ledger!B:B,_xlpm.party,ledger!E:E,"<>*RD*",ledger!D:D,"Silky")))/1.0936)+_xlfn.IFNA(F125,0)} -> 45840.344 | W32: {=(_xlfn.BYROW(B76,_xlfn.LAMBDA(_xlpm.party, (SUMIFS(ledger!J:J,ledger!B:B,_xlpm.party,ledger!E:E,"<>*RD*",ledger!D:D,"Chamki",ledger!C:C,"<>January Closing CF")+ SUMIFS(ledger!J:J,ledger!B:B,_xlpm.party,ledger!E:E,"<>*RD*",ledger!D:D,"Crinkle",ledger!C:C,"<>January Closing CF") )+_xlfn.IFNA(G125,0))))} -> 0 | X32: {=_xlfn.BYROW(B76, _xlfn.LAMBDA(_xlpm.party, SUMIFS(ledger!J:J, ledger!B:B, _xlpm.party, ledger!E:E, "<>*RD*", ledger!D:D, "Silky", ledger!C:C, "<>January Closing CF") )) + _xlfn.IFNA(H125, 0)} -> 595924.47 | Y32: {=_xlfn.BYROW(B76, _xlfn.LAMBDA(_xlpm.party, SUMIFS(ledger!J:J, ledger!B:B, _xlpm.party, ledger!E:E, "<>*RD*", ledger!D:D, "Slub", ledger!C:C, "<>January Closing CF") ))+ _xlfn.IFNA(I125, 0)} -> 0 | Z32: {=_xlfn.BYROW(B76, _xlfn.LAMBDA(_xlpm.party, SUMIFS(ledger!J:J, ledger!B:B, _xlpm.party, ledger!E:E, "<>*RD*", ledger!D:D, "Satin", ledger!C:C, "<>January Closing CF") ))+ _xlfn.IFNA(J125, 0)} -> 0 | AA32: {=_xlfn.BYROW(B76, _xlfn.LAMBDA(_xlpm.party, SUMIFS(ledger!J:J, ledger!B:B, _xlpm.party, ledger!E:E, "<>*RD*", ledger!D:D, "Black-Chamki", ledger!C:C, "<>January Closing CF") ))+ _xlfn.IFNA(K125, 0)} -> 0 | AB32: {=_xlfn.BYROW(B76, _xlfn.LAMBDA(_xlpm.party, SUMIFS(ledger!J:J, ledger!B:B, _xlpm.party, ledger!E:E, "<>*RD*", ledger!D:D, "Kataan", ledger!C:C, "<>January Closing CF") ))+ _xlfn.IFNA(L125, 0)} -> 0 | AC32: {=_xlfn.BYROW(B76, _xlfn.LAMBDA(_xlpm.party, SUMIFS(ledger!J:J, ledger!B:B, _xlpm.party, ledger!E:E, "<>*RD*", ledger!D:D, "Munaar", ledger!C:C, "<>January Closing CF") ))+ _xlfn.IFNA(M125, 0)} -> 0 | AD32: {=_xlfn.BYROW(B76, _xlfn.LAMBDA(_xlpm.party, SUMIFS(ledger!J:J, ledger!B:B, _xlpm.party, ledger!E:E, "<>*RD*", ledger!D:D, "Custom", ledger!C:C, "<>January Closing CF") ))+ _xlfn.IFNA(N125, 0)} -> 0 | AE32: =W32+X32+Y32+Z32+AA32+AB32+AC32+AD32 -> 595924.47 | AF32: =(SUMIF(Table14[Party],R32,Table14[Credit]))+_xlfn.IFNA(P125,0) -> 550000 | AG32: =AE32-AF32 -> 45924.47 | AH32: 10 | AI32: 13
R33: Ahmad Shafique | S33: {=_xlfn.BYROW(B77,_xlfn.LAMBDA(_xlpm.party,SUMIFS(ledger!G:G,ledger!B:B,_xlpm.party,ledger!E:E,"<>*RD*")))+_xlfn.IFNA(C126,0)} -> 53541 | T33: {=_xlfn.BYROW(B77, _xlfn.LAMBDA(_xlpm.party, SUMIFS(ledger!G:G, ledger!B:B, _xlpm.party, ledger!E:E, "<>*RD*") / 1.0936 ))+_xlfn.IFNA(D126,0)} -> 48958.486 | U33: {=(_xlfn.BYROW(B77,_xlfn.LAMBDA(_xlpm.party,SUMIFS(ledger!G:G,ledger!B:B,_xlpm.party,ledger!E:E,"<>*RD*",ledger!D:D,"Chamki")+SUMIFS(ledger!G:G, ledger!B:B, _xlpm.party, ledger!E:E, "<>*RD*", ledger!D:D, "Crinkle")))/1.0936)+_xlfn.IFNA(E126,0)} -> 0 | V33: {=(_xlfn.BYROW(B77,_xlfn.LAMBDA(_xlpm.party,SUMIFS(ledger!G:G,ledger!B:B,_xlpm.party,ledger!E:E,"<>*RD*",ledger!D:D,"Silky")))/1.0936)+_xlfn.IFNA(F126,0)} -> 48958.486 | W33: {=(_xlfn.BYROW(B77,_xlfn.LAMBDA(_xlpm.party, (SUMIFS(ledger!J:J,ledger!B:B,_xlpm.party,ledger!E:E,"<>*RD*",ledger!D:D,"Chamki",ledger!C:C,"<>January Closing CF")+ SUMIFS(ledger!J:J,ledger!B:B,_xlpm.party,ledger!E:E,"<>*RD*",ledger!D:D,"Crinkle",ledger!C:C,"<>January Closing CF") )+_xlfn.IFNA(G126,0))))} -> 0 | X33: {=_xlfn.BYROW(B77, _xlfn.LAMBDA(_xlpm.party, SUMIFS(ledger!J:J, ledger!B:B, _xlpm.party, ledger!E:E, "<>*RD*", ledger!D:D, "Silky", ledger!C:C, "<>January Closing CF") )) + _xlfn.IFNA(H126, 0)} -> 636460.31 | Y33: {=_xlfn.BYROW(B77, _xlfn.LAMBDA(_xlpm.party, SUMIFS(ledger!J:J, ledger!B:B, _xlpm.party, ledger!E:E, "<>*RD*", ledger!D:D, "Slub", ledger!C:C, "<>January Closing CF") ))+ _xlfn.IFNA(I126, 0)} -> 0 | Z33: {=_xlfn.BYROW(B77, _xlfn.LAMBDA(_xlpm.party, SUMIFS(ledger!J:J, ledger!B:B, _xlpm.party, ledger!E:E, "<>*RD*", ledger!D:D, "Satin", ledger!C:C, "<>January Closing CF") ))+ _xlfn.IFNA(J126, 0)} -> 0 | AA33: {=_xlfn.BYROW(B77, _xlfn.LAMBDA(_xlpm.party, SUMIFS(ledger!J:J, ledger!B:B, _xlpm.party, ledger!E:E, "<>*RD*", ledger!D:D, "Black-Chamki", ledger!C:C, "<>January Closing CF") ))+ _xlfn.IFNA(K126, 0)} -> 0 | AB33: {=_xlfn.BYROW(B77, _xlfn.LAMBDA(_xlpm.party, SUMIFS(ledger!J:J, ledger!B:B, _xlpm.party, ledger!E:E, "<>*RD*", ledger!D:D, "Kataan", ledger!C:C, "<>January Closing CF") ))+ _xlfn.IFNA(L126, 0)} -> 0 | AC33: {=_xlfn.BYROW(B77, _xlfn.LAMBDA(_xlpm.party, SUMIFS(ledger!J:J, ledger!B:B, _xlpm.party, ledger!E:E, "<>*RD*", ledger!D:D, "Munaar", ledger!C:C, "<>January Closing CF") ))+ _xlfn.IFNA(M126, 0)} -> 0 | AD33: {=_xlfn.BYROW(B77, _xlfn.LAMBDA(_xlpm.party, SUMIFS(ledger!J:J, ledger!B:B, _xlpm.party, ledger!E:E, "<>*RD*", ledger!D:D, "Custom", ledger!C:C, "<>January Closing CF") ))+ _xlfn.IFNA(N126, 0)} -> 0 | AE33: =W33+X33+Y33+Z33+AA33+AB33+AC33+AD33 -> 636460.31 | AF33: =(SUMIF(Table14[Party],R33,Table14[Credit]))+_xlfn.IFNA(P126,0) -> 636000 | AG33: =AE33-AF33 -> 460.31456 | AH33: 10 | AI33: 13
R34: Hafiz Shawl | S34: {=_xlfn.BYROW(B78,_xlfn.LAMBDA(_xlpm.party,SUMIFS(ledger!G:G,ledger!B:B,_xlpm.party,ledger!E:E,"<>*RD*")))+_xlfn.IFNA(C127,0)} -> 33395 | T34: {=_xlfn.BYROW(B78, _xlfn.LAMBDA(_xlpm.party, SUMIFS(ledger!G:G, ledger!B:B, _xlpm.party, ledger!E:E, "<>*RD*") / 1.0936 ))+_xlfn.IFNA(D127,0)} -> 30536.759 | U34: {=(_xlfn.BYROW(B78,_xlfn.LAMBDA(_xlpm.party,SUMIFS(ledger!G:G,ledger!B:B,_xlpm.party,ledger!E:E,"<>*RD*",ledger!D:D,"Chamki")+SUMIFS(ledger!G:G, ledger!B:B, _xlpm.party, ledger!E:E, "<>*RD*", ledger!D:D, "Crinkle")))/1.0936)+_xlfn.IFNA(E127,0)} -> 0 | V34: {=(_xlfn.BYROW(B78,_xlfn.LAMBDA(_xlpm.party,SUMIFS(ledger!G:G,ledger!B:B,_xlpm.party,ledger!E:E,"<>*RD*",ledger!D:D,"Silky")))/1.0936)+_xlfn.IFNA(F127,0)} -> 1321.3241 | W34: {=(_xlfn.BYROW(B78,_xlfn.LAMBDA(_xlpm.party, (SUMIFS(ledger!J:J,ledger!B:B,_xlpm.party,ledger!E:E,"<>*RD*",ledger!D:D,"Chamki",ledger!C:C,"<>January Closing CF")+ SUMIFS(ledger!J:J,ledger!B:B,_xlpm.party,ledger!E:E,"<>*RD*",ledger!D:D,"Crinkle",ledger!C:C,"<>January Closing CF") )+_xlfn.IFNA(G127,0))))} -> 0 | X34: {=_xlfn.BYROW(B78, _xlfn.LAMBDA(_xlpm.party, SUMIFS(ledger!J:J, ledger!B:B, _xlpm.party, ledger!E:E, "<>*RD*", ledger!D:D, "Silky", ledger!C:C, "<>January Closing CF") )) + _xlfn.IFNA(H127, 0)} -> 15855.889 | Y34: {=_xlfn.BYROW(B78, _xlfn.LAMBDA(_xlpm.party, SUMIFS(ledger!J:J, ledger!B:B, _xlpm.party, ledger!E:E, "<>*RD*", ledger!D:D, "Slub", ledger!C:C, "<>January Closing CF") ))+ _xlfn.IFNA(I127, 0)} -> 0 | Z34: {=_xlfn.BYROW(B78, _xlfn.LAMBDA(_xlpm.party, SUMIFS(ledger!J:J, ledger!B:B, _xlpm.party, ledger!E:E, "<>*RD*", ledger!D:D, "Satin", ledger!C:C, "<>January Closing CF") ))+ _xlfn.IFNA(J127, 0)} -> 0 | AA34: {=_xlfn.BYROW(B78, _xlfn.LAMBDA(_xlpm.party, SUMIFS(ledger!J:J, ledger!B:B, _xlpm.party, ledger!E:E, "<>*RD*", ledger!D:D, "Black-Chamki", ledger!C:C, "<>January Closing CF") ))+ _xlfn.IFNA(K127, 0)} -> 0 | AB34: {=_xlfn.BYROW(B78, _xlfn.LAMBDA(_xlpm.party, SUMIFS(ledger!J:J, ledger!B:B, _xlpm.party, ledger!E:E, "<>*RD*", ledger!D:D, "Kataan", ledger!C:C, "<>January Closing CF") ))+ _xlfn.IFNA(L127, 0)} -> 0 | AC34: {=_xlfn.BYROW(B78, _xlfn.LAMBDA(_xlpm.party, SUMIFS(ledger!J:J, ledger!B:B, _xlpm.party, ledger!E:E, "<>*RD*", ledger!D:D, "Munaar", ledger!C:C, "<>January Closing CF") ))+ _xlfn.IFNA(M127, 0)} -> 0 | AD34: {=_xlfn.BYROW(B78, _xlfn.LAMBDA(_xlpm.party, SUMIFS(ledger!J:J, ledger!B:B, _xlpm.party, ledger!E:E, "<>*RD*", ledger!D:D, "Custom", ledger!C:C, "<>January Closing CF") ))+ _xlfn.IFNA(N127, 0)} -> 584043.53 | AE34: =W34+X34+Y34+Z34+AA34+AB34+AC34+AD34 -> 599899.41 | AF34: =(SUMIF(Table14[Party],R34,Table14[Credit]))+_xlfn.IFNA(P127,0) -> 55855 | AG34: =AE34-AF34 -> 544044.41 | AH34: 10 | AI34: 13
R35: Zahid Ejaz | S35: {=_xlfn.BYROW(B79,_xlfn.LAMBDA(_xlpm.party,SUMIFS(ledger!G:G,ledger!B:B,_xlpm.party,ledger!E:E,"<>*RD*")))+_xlfn.IFNA(C128,0)} -> 16060 | T35: {=_xlfn.BYROW(B79, _xlfn.LAMBDA(_xlpm.party, SUMIFS(ledger!G:G, ledger!B:B, _xlpm.party, ledger!E:E, "<>*RD*") / 1.0936 ))+_xlfn.IFNA(D128,0)} -> 14685.443 | U35: {=(_xlfn.BYROW(B79,_xlfn.LAMBDA(_xlpm.party,SUMIFS(ledger!G:G,ledger!B:B,_xlpm.party,ledger!E:E,"<>*RD*",ledger!D:D,"Chamki")+SUMIFS(ledger!G:G, ledger!B:B, _xlpm.party, ledger!E:E, "<>*RD*", ledger!D:D, "Crinkle")))/1.0936)+_xlfn.IFNA(E128,0)} -> 14685.443 | V35: {=(_xlfn.BYROW(B79,_xlfn.LAMBDA(_xlpm.party,SUMIFS(ledger!G:G,ledger!B:B,_xlpm.party,ledger!E:E,"<>*RD*",ledger!D:D,"Silky")))/1.0936)+_xlfn.IFNA(F128,0)} -> 0 | W35: {=(_xlfn.BYROW(B79,_xlfn.LAMBDA(_xlpm.party, (SUMIFS(ledger!J:J,ledger!B:B,_xlpm.party,ledger!E:E,"<>*RD*",ledger!D:D,"Chamki",ledger!C:C,"<>January Closing CF")+ SUMIFS(ledger!J:J,ledger!B:B,_xlpm.party,ledger!E:E,"<>*RD*",ledger!D:D,"Crinkle",ledger!C:C,"<>January Closing CF") )+_xlfn.IFNA(G128,0))))} -> 161539.87 | X35: {=_xlfn.BYROW(B79, _xlfn.LAMBDA(_xlpm.party, SUMIFS(ledger!J:J, ledger!B:B, _xlpm.party, ledger!E:E, "<>*RD*", ledger!D:D, "Silky", ledger!C:C, "<>January Closing CF") )) + _xlfn.IFNA(H128, 0)} -> 0 | Y35: {=_xlfn.BYROW(B79, _xlfn.LAMBDA(_xlpm.party, SUMIFS(ledger!J:J, ledger!B:B, _xlpm.party, ledger!E:E, "<>*RD*", ledger!D:D, "Slub", ledger!C:C, "<>January Closing CF") ))+ _xlfn.IFNA(I128, 0)} -> 0 | Z35: {=_xlfn.BYROW(B79, _xlfn.LAMBDA(_xlpm.party, SUMIFS(ledger!J:J, ledger!B:B, _xlpm.party, ledger!E:E, "<>*RD*", ledger!D:D, "Satin", ledger!C:C, "<>January Closing CF") ))+ _xlfn.IFNA(J128, 0)} -> 0 | AA35: {=_xlfn.BYROW(B79, _xlfn.LAMBDA(_xlpm.party, SUMIFS(ledger!J:J, ledger!B:B, _xlpm.party, ledger!E:E, "<>*RD*", ledger!D:D, "Black-Chamki", ledger!C:C, "<>January Closing CF") ))+ _xlfn.IFNA(K128, 0)} -> 0 | AB35: {=_xlfn.BYROW(B79, _xlfn.LAMBDA(_xlpm.party, SUMIFS(ledger!J:J, ledger!B:B, _xlpm.party, ledger!E:E, "<>*RD*", ledger!D:D, "Kataan", ledger!C:C, "<>January Closing CF") ))+ _xlfn.IFNA(L128, 0)} -> 0 | AC35: {=_xlfn.BYROW(B79, _xlfn.LAMBDA(_xlpm.party, SUMIFS(ledger!J:J, ledger!B:B, _xlpm.party, ledger!E:E, "<>*RD*", ledger!D:D, "Munaar", ledger!C:C, "<>January Closing CF") ))+ _xlfn.IFNA(M128, 0)} -> 0 | AD35: {=_xlfn.BYROW(B79, _xlfn.LAMBDA(_xlpm.party, SUMIFS(ledger!J:J, ledger!B:B, _xlpm.party, ledger!E:E, "<>*RD*", ledger!D:D, "Custom", ledger!C:C, "<>January Closing CF") ))+ _xlfn.IFNA(N128, 0)} -> 0 | AE35: =W35+X35+Y35+Z35+AA35+AB35+AC35+AD35 -> 161539.87 | AF35: =(SUMIF(Table14[Party],R35,Table14[Credit]))+_xlfn.IFNA(P128,0) -> 169278 | AG35: =AE35-AF35 -> -7738.1317 | AH35: 10 | AI35: 13
R36: Faizan Kamoki | S36: {=_xlfn.BYROW(B80,_xlfn.LAMBDA(_xlpm.party,SUMIFS(ledger!G:G,ledger!B:B,_xlpm.party,ledger!E:E,"<>*RD*")))+_xlfn.IFNA(C129,0)} -> 490216 | T36: {=_xlfn.BYROW(B80, _xlfn.LAMBDA(_xlpm.party, SUMIFS(ledger!G:G, ledger!B:B, _xlpm.party, ledger!E:E, "<>*RD*") / 1.0936 ))+_xlfn.IFNA(D129,0)} -> 448258.96 | U36: {=(_xlfn.BYROW(B80,_xlfn.LAMBDA(_xlpm.party,SUMIFS(ledger!G:G,ledger!B:B,_xlpm.party,ledger!E:E,"<>*RD*",ledger!D:D,"Chamki")+SUMIFS(ledger!G:G, ledger!B:B, _xlpm.party, ledger!E:E, "<>*RD*", ledger!D:D, "Crinkle")))/1.0936)+_xlfn.IFNA(E129,0)} -> 0 | V36: {=(_xlfn.BYROW(B80,_xlfn.LAMBDA(_xlpm.party,SUMIFS(ledger!G:G,ledger!B:B,_xlpm.party,ledger!E:E,"<>*RD*",ledger!D:D,"Silky")))/1.0936)+_xlfn.IFNA(F129,0)} -> 306760.24 | W36: {=(_xlfn.BYROW(B80,_xlfn.LAMBDA(_xlpm.party, (SUMIFS(ledger!J:J,ledger!B:B,_xlpm.party,ledger!E:E,"<>*RD*",ledger!D:D,"Chamki",ledger!C:C,"<>January Closing CF")+ SUMIFS(ledger!J:J,ledger!B:B,_xlpm.party,ledger!E:E,"<>*RD*",ledger!D:D,"Crinkle",ledger!C:C,"<>January Closing CF") )+_xlfn.IFNA(G129,0))))} -> 0 | X36: {=_xlfn.BYROW(B80, _xlfn.LAMBDA(_xlpm.party, SUMIFS(ledger!J:J, ledger!B:B, _xlpm.party, ledger!E:E, "<>*RD*", ledger!D:D, "Silky", ledger!C:C, "<>January Closing CF") )) + _xlfn.IFNA(H129, 0)} -> 3987883.1 | Y36: {=_xlfn.BYROW(B80, _xlfn.LAMBDA(_xlpm.party, SUMIFS(ledger!J:J, ledger!B:B, _xlpm.party, ledger!E:E, "<>*RD*", ledger!D:D, "Slub", ledger!C:C, "<>January Closing CF") ))+ _xlfn.IFNA(I129, 0)} -> 0 | Z36: {=_xlfn.BYROW(B80, _xlfn.LAMBDA(_xlpm.party, SUMIFS(ledger!J:J, ledger!B:B, _xlpm.party, ledger!E:E, "<>*RD*", ledger!D:D, "Satin", ledger!C:C, "<>January Closing CF") ))+ _xlfn.IFNA(J129, 0)} -> 0 | AA36: {=_xlfn.BYROW(B80, _xlfn.LAMBDA(_xlpm.party, SUMIFS(ledger!J:J, ledger!B:B, _xlpm.party, ledger!E:E, "<>*RD*", ledger!D:D, "Black-Chamki", ledger!C:C, "<>January Closing CF") ))+ _xlfn.IFNA(K129, 0)} -> 0 | AB36: {=_xlfn.BYROW(B80, _xlfn.LAMBDA(_xlpm.party, SUMIFS(ledger!J:J, ledger!B:B, _xlpm.party, ledger!E:E, "<>*RD*", ledger!D:D, "Kataan", ledger!C:C, "<>January Closing CF") ))+ _xlfn.IFNA(L129, 0)} -> 1638023 | AC36: {=_xlfn.BYROW(B80, _xlfn.LAMBDA(_xlpm.party, SUMIFS(ledger!J:J, ledger!B:B, _xlpm.party, ledger!E:E, "<>*RD*", ledger!D:D, "Munaar", ledger!C:C, "<>January Closing CF") ))+ _xlfn.IFNA(M129, 0)} -> 0 | AD36: {=_xlfn.BYROW(B80, _xlfn.LAMBDA(_xlpm.party, SUMIFS(ledger!J:J, ledger!B:B, _xlpm.party, ledger!E:E, "<>*RD*", ledger!D:D, "Custom", ledger!C:C, "<>January Closing CF") ))+ _xlfn.IFNA(N129, 0)} -> 0 | AE36: =W36+X36+Y36+Z36+AA36+AB36+AC36+AD36 -> 5625906.2 | AF36: =(SUMIF(Table14[Party],R36,Table14[Credit]))+_xlfn.IFNA(P129,0) -> 5245323.5 | AG36: =AE36-AF36 -> 380582.69
R37: KK fabrics | S37: {=_xlfn.BYROW(B81,_xlfn.LAMBDA(_xlpm.party,SUMIFS(ledger!G:G,ledger!B:B,_xlpm.party,ledger!E:E,"<>*RD*")))+_xlfn.IFNA(C130,0)} -> 59639 | T37: {=_xlfn.BYROW(B81, _xlfn.LAMBDA(_xlpm.party, SUMIFS(ledger!G:G, ledger!B:B, _xlpm.party, ledger!E:E, "<>*RD*") / 1.0936 ))+_xlfn.IFNA(D130,0)} -> 54534.565 | U37: {=(_xlfn.BYROW(B81,_xlfn.LAMBDA(_xlpm.party,SUMIFS(ledger!G:G,ledger!B:B,_xlpm.party,ledger!E:E,"<>*RD*",ledger!D:D,"Chamki")+SUMIFS(ledger!G:G, ledger!B:B, _xlpm.party, ledger!E:E, "<>*RD*", ledger!D:D, "Crinkle")))/1.0936)+_xlfn.IFNA(E130,0)} -> 54534.565 | V37: {=(_xlfn.BYROW(B81,_xlfn.LAMBDA(_xlpm.party,SUMIFS(ledger!G:G,ledger!B:B,_xlpm.party,ledger!E:E,"<>*RD*",ledger!D:D,"Silky")))/1.0936)+_xlfn.IFNA(F130,0)} -> 0 | W37: {=(_xlfn.BYROW(B81,_xlfn.LAMBDA(_xlpm.party, (SUMIFS(ledger!J:J,ledger!B:B,_xlpm.party,ledger!E:E,"<>*RD*",ledger!D:D,"Chamki",ledger!C:C,"<>January Closing CF")+ SUMIFS(ledger!J:J,ledger!B:B,_xlpm.party,ledger!E:E,"<>*RD*",ledger!D:D,"Crinkle",ledger!C:C,"<>January Closing CF") )+_xlfn.IFNA(G130,0))))} -> 545345.65 | X37: {=_xlfn.BYROW(B81, _xlfn.LAMBDA(_xlpm.party, SUMIFS(ledger!J:J, ledger!B:B, _xlpm.party, ledger!E:E, "<>*RD*", ledger!D:D, "Silky", ledger!C:C, "<>January Closing CF") )) + _xlfn.IFNA(H130, 0)} -> 0 | Y37: {=_xlfn.BYROW(B81, _xlfn.LAMBDA(_xlpm.party, SUMIFS(ledger!J:J, ledger!B:B, _xlpm.party, ledger!E:E, "<>*RD*", ledger!D:D, "Slub", ledger!C:C, "<>January Closing CF") ))+ _xlfn.IFNA(I130, 0)} -> 0 | Z37: {=_xlfn.BYROW(B81, _xlfn.LAMBDA(_xlpm.party, SUMIFS(ledger!J:J, ledger!B:B, _xlpm.party, ledger!E:E, "<>*RD*", ledger!D:D, "Satin", ledger!C:C, "<>January Closing CF") ))+ _xlfn.IFNA(J130, 0)} -> 0 | AA37: {=_xlfn.BYROW(B81, _xlfn.LAMBDA(_xlpm.party, SUMIFS(ledger!J:J, ledger!B:B, _xlpm.party, ledger!E:E, "<>*RD*", ledger!D:D, "Black-Chamki", ledger!C:C, "<>January Closing CF") ))+ _xlfn.IFNA(K130, 0)} -> 0 | AB37: {=_xlfn.BYROW(B81, _xlfn.LAMBDA(_xlpm.party, SUMIFS(ledger!J:J, ledger!B:B, _xlpm.party, ledger!E:E, "<>*RD*", ledger!D:D, "Kataan", ledger!C:C, "<>January Closing CF") ))+ _xlfn.IFNA(L130, 0)} -> 0 | AC37: {=_xlfn.BYROW(B81, _xlfn.LAMBDA(_xlpm.party, SUMIFS(ledger!J:J, ledger!B:B, _xlpm.party, ledger!E:E, "<>*RD*", ledger!D:D, "Munaar", ledger!C:C, "<>January Closing CF") ))+ _xlfn.IFNA(M130, 0)} -> 0 | AD37: {=_xlfn.BYROW(B81, _xlfn.LAMBDA(_xlpm.party, SUMIFS(ledger!J:J, ledger!B:B, _xlpm.party, ledger!E:E, "<>*RD*", ledger!D:D, "Custom", ledger!C:C, "<>January Closing CF") ))+ _xlfn.IFNA(N130, 0)} -> 0 | AE37: =W37+X37+Y37+Z37+AA37+AB37+AC37+AD37 -> 545345.65 | AF37: =(SUMIF(Table14[Party],R37,Table14[Credit]))+_xlfn.IFNA(P130,0) -> 544000 | AG37: =AE37-AF37 -> 1345.6474
R38: Rauf Khan | S38: {=_xlfn.BYROW(B82,_xlfn.LAMBDA(_xlpm.party,SUMIFS(ledger!G:G,ledger!B:B,_xlpm.party,ledger!E:E,"<>*RD*")))+_xlfn.IFNA(C131,0)} -> 110981 | T38: {=_xlfn.BYROW(B82, _xlfn.LAMBDA(_xlpm.party, SUMIFS(ledger!G:G, ledger!B:B, _xlpm.party, ledger!E:E, "<>*RD*") / 1.0936 ))+_xlfn.IFNA(D131,0)} -> 101482.26 | U38: {=(_xlfn.BYROW(B82,_xlfn.LAMBDA(_xlpm.party,SUMIFS(ledger!G:G,ledger!B:B,_xlpm.party,ledger!E:E,"<>*RD*",ledger!D:D,"Chamki")+SUMIFS(ledger!G:G, ledger!B:B, _xlpm.party, ledger!E:E, "<>*RD*", ledger!D:D, "Crinkle")))/1.0936)+_xlfn.IFNA(E131,0)} -> 81045.172 | V38: {=(_xlfn.BYROW(B82,_xlfn.LAMBDA(_xlpm.party,SUMIFS(ledger!G:G,ledger!B:B,_xlpm.party,ledger!E:E,"<>*RD*",ledger!D:D,"Silky")))/1.0936)+_xlfn.IFNA(F131,0)} -> 0 | W38: {=(_xlfn.BYROW(B82,_xlfn.LAMBDA(_xlpm.party, (SUMIFS(ledger!J:J,ledger!B:B,_xlpm.party,ledger!E:E,"<>*RD*",ledger!D:D,"Chamki",ledger!C:C,"<>January Closing CF")+ SUMIFS(ledger!J:J,ledger!B:B,_xlpm.party,ledger!E:E,"<>*RD*",ledger!D:D,"Crinkle",ledger!C:C,"<>January Closing CF") )+_xlfn.IFNA(G131,0))))} -> 810451.72 | X38: {=_xlfn.BYROW(B82, _xlfn.LAMBDA(_xlpm.party, SUMIFS(ledger!J:J, ledger!B:B, _xlpm.party, ledger!E:E, "<>*RD*", ledger!D:D, "Silky", ledger!C:C, "<>January Closing CF") )) + _xlfn.IFNA(H131, 0)} -> 0 | Y38: {=_xlfn.BYROW(B82, _xlfn.LAMBDA(_xlpm.party, SUMIFS(ledger!J:J, ledger!B:B, _xlpm.party, ledger!E:E, "<>*RD*", ledger!D:D, "Slub", ledger!C:C, "<>January Closing CF") ))+ _xlfn.IFNA(I131, 0)} -> 0 | Z38: {=_xlfn.BYROW(B82, _xlfn.LAMBDA(_xlpm.party, SUMIFS(ledger!J:J, ledger!B:B, _xlpm.party, ledger!E:E, "<>*RD*", ledger!D:D, "Satin", ledger!C:C, "<>January Closing CF") ))+ _xlfn.IFNA(J131, 0)} -> 306556.33 | AA38: {=_xlfn.BYROW(B82, _xlfn.LAMBDA(_xlpm.party, SUMIFS(ledger!J:J, ledger!B:B, _xlpm.party, ledger!E:E, "<>*RD*", ledger!D:D, "Black-Chamki", ledger!C:C, "<>January Closing CF") ))+ _xlfn.IFNA(K131, 0)} -> 0 | AB38: {=_xlfn.BYROW(B82, _xlfn.LAMBDA(_xlpm.party, SUMIFS(ledger!J:J, ledger!B:B, _xlpm.party, ledger!E:E, "<>*RD*", ledger!D:D, "Kataan", ledger!C:C, "<>January Closing CF") ))+ _xlfn.IFNA(L131, 0)} -> 0 | AC38: {=_xlfn.BYROW(B82, _xlfn.LAMBDA(_xlpm.party, SUMIFS(ledger!J:J, ledger!B:B, _xlpm.party, ledger!E:E, "<>*RD*", ledger!D:D, "Munaar", ledger!C:C, "<>January Closing CF") ))+ _xlfn.IFNA(M131, 0)} -> 0 | AD38: {=_xlfn.BYROW(B82, _xlfn.LAMBDA(_xlpm.party, SUMIFS(ledger!J:J, ledger!B:B, _xlpm.party, ledger!E:E, "<>*RD*", ledger!D:D, "Custom", ledger!C:C, "<>January Closing CF") ))+ _xlfn.IFNA(N131, 0)} -> 0 | AE38: =W38+X38+Y38+Z38+AA38+AB38+AC38+AD38 -> 1117008 | AF38: =(SUMIF(Table14[Party],R38,Table14[Credit]))+_xlfn.IFNA(P131,0) -> 0 | AG38: =AE38-AF38 -> 1117008
R39: Farhaan ali | S39: {=_xlfn.BYROW(B83,_xlfn.LAMBDA(_xlpm.party,SUMIFS(ledger!G:G,ledger!B:B,_xlpm.party,ledger!E:E,"<>*RD*")))+_xlfn.IFNA(C132,0)} -> 163883 | T39: {=_xlfn.BYROW(B83, _xlfn.LAMBDA(_xlpm.party, SUMIFS(ledger!G:G, ledger!B:B, _xlpm.party, ledger!E:E, "<>*RD*") / 1.0936 ))+_xlfn.IFNA(D132,0)} -> 149856.44 | U39: {=(_xlfn.BYROW(B83,_xlfn.LAMBDA(_xlpm.party,SUMIFS(ledger!G:G,ledger!B:B,_xlpm.party,ledger!E:E,"<>*RD*",ledger!D:D,"Chamki")+SUMIFS(ledger!G:G, ledger!B:B, _xlpm.party, ledger!E:E, "<>*RD*", ledger!D:D, "Crinkle")))/1.0936)+_xlfn.IFNA(E132,0)} -> 0 | V39: {=(_xlfn.BYROW(B83,_xlfn.LAMBDA(_xlpm.party,SUMIFS(ledger!G:G,ledger!B:B,_xlpm.party,ledger!E:E,"<>*RD*",ledger!D:D,"Silky")))/1.0936)+_xlfn.IFNA(F132,0)} -> 149856.44 | W39: {=(_xlfn.BYROW(B83,_xlfn.LAMBDA(_xlpm.party, (SUMIFS(ledger!J:J,ledger!B:B,_xlpm.party,ledger!E:E,"<>*RD*",ledger!D:D,"Chamki",ledger!C:C,"<>January Closing CF")+ SUMIFS(ledger!J:J,ledger!B:B,_xlpm.party,ledger!E:E,"<>*RD*",ledger!D:D,"Crinkle",ledger!C:C,"<>January Closing CF") )+_xlfn.IFNA(G132,0))))} -> 0 | X39: {=_xlfn.BYROW(B83, _xlfn.LAMBDA(_xlpm.party, SUMIFS(ledger!J:J, ledger!B:B, _xlpm.party, ledger!E:E, "<>*RD*", ledger!D:D, "Silky", ledger!C:C, "<>January Closing CF") )) + _xlfn.IFNA(H132, 0)} -> 1798277.2 | Y39: {=_xlfn.BYROW(B83, _xlfn.LAMBDA(_xlpm.party, SUMIFS(ledger!J:J, ledger!B:B, _xlpm.party, ledger!E:E, "<>*RD*", ledger!D:D, "Slub", ledger!C:C, "<>January Closing CF") ))+ _xlfn.IFNA(I132, 0)} -> 0 | Z39: {=_xlfn.BYROW(B83, _xlfn.LAMBDA(_xlpm.party, SUMIFS(ledger!J:J, ledger!B:B, _xlpm.party, ledger!E:E, "<>*RD*", ledger!D:D, "Satin", ledger!C:C, "<>January Closing CF") ))+ _xlfn.IFNA(J132, 0)} -> 0 | AA39: {=_xlfn.BYROW(B83, _xlfn.LAMBDA(_xlpm.party, SUMIFS(ledger!J:J, ledger!B:B, _xlpm.party, ledger!E:E, "<>*RD*", ledger!D:D, "Black-Chamki", ledger!C:C, "<>January Closing CF") ))+ _xlfn.IFNA(K132, 0)} -> 0 | AB39: {=_xlfn.BYROW(B83, _xlfn.LAMBDA(_xlpm.party, SUMIFS(ledger!J:J, ledger!B:B, _xlpm.party, ledger!E:E, "<>*RD*", ledger!D:D, "Kataan", ledger!C:C, "<>January Closing CF") ))+ _xlfn.IFNA(L132, 0)} -> 0 | AC39: {=_xlfn.BYROW(B83, _xlfn.LAMBDA(_xlpm.party, SUMIFS(ledger!J:J, ledger!B:B, _xlpm.party, ledger!E:E, "<>*RD*", ledger!D:D, "Munaar", ledger!C:C, "<>January Closing CF") ))+ _xlfn.IFNA(M132, 0)} -> 0 | AD39: {=_xlfn.BYROW(B83, _xlfn.LAMBDA(_xlpm.party, SUMIFS(ledger!J:J, ledger!B:B, _xlpm.party, ledger!E:E, "<>*RD*", ledger!D:D, "Custom", ledger!C:C, "<>January Closing CF") ))+ _xlfn.IFNA(N132, 0)} -> 0 | AE39: =W39+X39+Y39+Z39+AA39+AB39+AC39+AD39 -> 1798277.2 | AF39: =(SUMIF(Table14[Party],R39,Table14[Credit]))+_xlfn.IFNA(P132,0) -> 0 | AG39: =AE39-AF39 -> 1798277.2
R40: 0 | S40: {=_xlfn.BYROW(B84,_xlfn.LAMBDA(_xlpm.party,SUMIFS(ledger!G:G,ledger!B:B,_xlpm.party,ledger!E:E,"<>*RD*")))+_xlfn.IFNA(C133,0)} -> 0 | T40: {=_xlfn.BYROW(B84, _xlfn.LAMBDA(_xlpm.party, SUMIFS(ledger!G:G, ledger!B:B, _xlpm.party, ledger!E:E, "<>*RD*") / 1.0936 ))+_xlfn.IFNA(D133,0)} -> 0 | U40: {=(_xlfn.BYROW(B84,_xlfn.LAMBDA(_xlpm.party,SUMIFS(ledger!G:G,ledger!B:B,_xlpm.party,ledger!E:E,"<>*RD*",ledger!D:D,"Chamki")+SUMIFS(ledger!G:G, ledger!B:B, _xlpm.party, ledger!E:E, "<>*RD*", ledger!D:D, "Crinkle")))/1.0936)+_xlfn.IFNA(E133,0)} -> 0 | V40: {=(_xlfn.BYROW(B84,_xlfn.LAMBDA(_xlpm.party,SUMIFS(ledger!G:G,ledger!B:B,_xlpm.party,ledger!E:E,"<>*RD*",ledger!D:D,"Silky")))/1.0936)+_xlfn.IFNA(F133,0)} -> 0 | W40: {=(_xlfn.BYROW(B84,_xlfn.LAMBDA(_xlpm.party, (SUMIFS(ledger!J:J,ledger!B:B,_xlpm.party,ledger!E:E,"<>*RD*",ledger!D:D,"Chamki",ledger!C:C,"<>January Closing CF")+ SUMIFS(ledger!J:J,ledger!B:B,_xlpm.party,ledger!E:E,"<>*RD*",ledger!D:D,"Crinkle",ledger!C:C,"<>January Closing CF") )+_xlfn.IFNA(G133,0))))} -> 0 | X40: {=_xlfn.BYROW(B84, _xlfn.LAMBDA(_xlpm.party, SUMIFS(ledger!J:J, ledger!B:B, _xlpm.party, ledger!E:E, "<>*RD*", ledger!D:D, "Silky", ledger!C:C, "<>January Closing CF") )) + _xlfn.IFNA(H133, 0)} -> 0 | Y40: {=_xlfn.BYROW(B84, _xlfn.LAMBDA(_xlpm.party, SUMIFS(ledger!J:J, ledger!B:B, _xlpm.party, ledger!E:E, "<>*RD*", ledger!D:D, "Slub", ledger!C:C, "<>January Closing CF") ))+ _xlfn.IFNA(I133, 0)} -> 0 | Z40: {=_xlfn.BYROW(B84, _xlfn.LAMBDA(_xlpm.party, SUMIFS(ledger!J:J, ledger!B:B, _xlpm.party, ledger!E:E, "<>*RD*", ledger!D:D, "Satin", ledger!C:C, "<>January Closing CF") ))+ _xlfn.IFNA(J133, 0)} -> 0 | AA40: {=_xlfn.BYROW(B84, _xlfn.LAMBDA(_xlpm.party, SUMIFS(ledger!J:J, ledger!B:B, _xlpm.party, ledger!E:E, "<>*RD*", ledger!D:D, "Black-Chamki", ledger!C:C, "<>January Closing CF") ))+ _xlfn.IFNA(K133, 0)} -> 0 | AB40: {=_xlfn.BYROW(B84, _xlfn.LAMBDA(_xlpm.party, SUMIFS(ledger!J:J, ledger!B:B, _xlpm.party, ledger!E:E, "<>*RD*", ledger!D:D, "Kataan", ledger!C:C, "<>January Closing CF") ))+ _xlfn.IFNA(L133, 0)} -> 0 | AC40: {=_xlfn.BYROW(B84, _xlfn.LAMBDA(_xlpm.party, SUMIFS(ledger!J:J, ledger!B:B, _xlpm.party, ledger!E:E, "<>*RD*", ledger!D:D, "Munaar", ledger!C:C, "<>January Closing CF") ))+ _xlfn.IFNA(M133, 0)} -> 0 | AD40: {=_xlfn.BYROW(B84, _xlfn.LAMBDA(_xlpm.party, SUMIFS(ledger!J:J, ledger!B:B, _xlpm.party, ledger!E:E, "<>*RD*", ledger!D:D, "Custom", ledger!C:C, "<>January Closing CF") ))+ _xlfn.IFNA(N133, 0)} -> 0 | AE40: =W40+X40+Y40+Z40+AA40+AB40+AC40+AD40 -> 0 | AF40: =(SUMIF(Table14[Party],R40,Table14[Credit]))+_xlfn.IFNA(P133,0) -> 0 | AG40: =AE40-AF40 -> 0
S41: {=_xlfn.BYROW(B85,_xlfn.LAMBDA(_xlpm.party,SUMIFS(ledger!G:G,ledger!B:B,_xlpm.party,ledger!E:E,"<>*RD*")))+_xlfn.IFNA(C134,0)} -> 0 | T41: {=_xlfn.BYROW(B85, _xlfn.LAMBDA(_xlpm.party, SUMIFS(ledger!G:G, ledger!B:B, _xlpm.party, ledger!E:E, "<>*RD*") / 1.0936 ))+_xlfn.IFNA(D134,0)} -> 0 | U41: {=(_xlfn.BYROW(B85,_xlfn.LAMBDA(_xlpm.party,SUMIFS(ledger!G:G,ledger!B:B,_xlpm.party,ledger!E:E,"<>*RD*",ledger!D:D,"Chamki")+SUMIFS(ledger!G:G, ledger!B:B, _xlpm.party, ledger!E:E, "<>*RD*", ledger!D:D, "Crinkle")))/1.0936)+_xlfn.IFNA(E134,0)} -> 0 | V41: {=(_xlfn.BYROW(B85,_xlfn.LAMBDA(_xlpm.party,SUMIFS(ledger!G:G,ledger!B:B,_xlpm.party,ledger!E:E,"<>*RD*",ledger!D:D,"Silky")))/1.0936)+_xlfn.IFNA(F134,0)} -> 0 | W41: {=(_xlfn.BYROW(B85,_xlfn.LAMBDA(_xlpm.party, (SUMIFS(ledger!J:J,ledger!B:B,_xlpm.party,ledger!E:E,"<>*RD*",ledger!D:D,"Chamki",ledger!C:C,"<>January Closing CF")+ SUMIFS(ledger!J:J,ledger!B:B,_xlpm.party,ledger!E:E,"<>*RD*",ledger!D:D,"Crinkle",ledger!C:C,"<>January Closing CF") )+_xlfn.IFNA(G134,0))))} -> 0 | X41: {=_xlfn.BYROW(B85, _xlfn.LAMBDA(_xlpm.party, SUMIFS(ledger!J:J, ledger!B:B, _xlpm.party, ledger!E:E, "<>*RD*", ledger!D:D, "Silky", ledger!C:C, "<>January Closing CF") )) + _xlfn.IFNA(H134, 0)} -> 0 | Y41: {=_xlfn.BYROW(B85, _xlfn.LAMBDA(_xlpm.party, SUMIFS(ledger!J:J, ledger!B:B, _xlpm.party, ledger!E:E, "<>*RD*", ledger!D:D, "Slub", ledger!C:C, "<>January Closing CF") ))+ _xlfn.IFNA(I134, 0)} -> 0 | Z41: {=_xlfn.BYROW(B85, _xlfn.LAMBDA(_xlpm.party, SUMIFS(ledger!J:J, ledger!B:B, _xlpm.party, ledger!E:E, "<>*RD*", ledger!D:D, "Satin", ledger!C:C, "<>January Closing CF") ))+ _xlfn.IFNA(J134, 0)} -> 0 | AA41: {=_xlfn.BYROW(B85, _xlfn.LAMBDA(_xlpm.party, SUMIFS(ledger!J:J, ledger!B:B, _xlpm.party, ledger!E:E, "<>*RD*", ledger!D:D, "Black-Chamki", ledger!C:C, "<>January Closing CF") ))+ _xlfn.IFNA(K134, 0)} -> 0 | AB41: {=_xlfn.BYROW(B85, _xlfn.LAMBDA(_xlpm.party, SUMIFS(ledger!J:J, ledger!B:B, _xlpm.party, ledger!E:E, "<>*RD*", ledger!D:D, "Kataan", ledger!C:C, "<>January Closing CF") ))+ _xlfn.IFNA(L134, 0)} -> 0 | AC41: {=_xlfn.BYROW(B85, _xlfn.LAMBDA(_xlpm.party, SUMIFS(ledger!J:J, ledger!B:B, _xlpm.party, ledger!E:E, "<>*RD*", ledger!D:D, "Munaar", ledger!C:C, "<>January Closing CF") ))+ _xlfn.IFNA(M134, 0)} -> 0 | AD41: {=_xlfn.BYROW(B85, _xlfn.LAMBDA(_xlpm.party, SUMIFS(ledger!J:J, ledger!B:B, _xlpm.party, ledger!E:E, "<>*RD*", ledger!D:D, "Custom", ledger!C:C, "<>January Closing CF") ))+ _xlfn.IFNA(N134, 0)} -> 0 | AE41: =W41+X41+Y41+Z41+AA41+AB41+AC41+AD41 -> 0 | AF41: =(SUMIF(Table14[Party],R41,Table14[Credit]))+_xlfn.IFNA(P134,0) -> 0 | AG41: =AE41-AF41 -> 0
S42: {=_xlfn.BYROW(B86,_xlfn.LAMBDA(_xlpm.party,SUMIFS(ledger!G:G,ledger!B:B,_xlpm.party,ledger!E:E,"<>*RD*")))+_xlfn.IFNA(C135,0)} -> 0 | T42: {=_xlfn.BYROW(B86, _xlfn.LAMBDA(_xlpm.party, SUMIFS(ledger!G:G, ledger!B:B, _xlpm.party, ledger!E:E, "<>*RD*") / 1.0936 ))+_xlfn.IFNA(D135,0)} -> 0 | U42: {=(_xlfn.BYROW(B86,_xlfn.LAMBDA(_xlpm.party,SUMIFS(ledger!G:G,ledger!B:B,_xlpm.party,ledger!E:E,"<>*RD*",ledger!D:D,"Chamki")+SUMIFS(ledger!G:G, ledger!B:B, _xlpm.party, ledger!E:E, "<>*RD*", ledger!D:D, "Crinkle")))/1.0936)+_xlfn.IFNA(E135,0)} -> 0 | V42: {=(_xlfn.BYROW(B86,_xlfn.LAMBDA(_xlpm.party,SUMIFS(ledger!G:G,ledger!B:B,_xlpm.party,ledger!E:E,"<>*RD*",ledger!D:D,"Silky")))/1.0936)+_xlfn.IFNA(F135,0)} -> 0 | W42: {=(_xlfn.BYROW(B86,_xlfn.LAMBDA(_xlpm.party, (SUMIFS(ledger!J:J,ledger!B:B,_xlpm.party,ledger!E:E,"<>*RD*",ledger!D:D,"Chamki",ledger!C:C,"<>January Closing CF")+ SUMIFS(ledger!J:J,ledger!B:B,_xlpm.party,ledger!E:E,"<>*RD*",ledger!D:D,"Crinkle",ledger!C:C,"<>January Closing CF") )+_xlfn.IFNA(G135,0))))} -> 0 | X42: {=_xlfn.BYROW(B86, _xlfn.LAMBDA(_xlpm.party, SUMIFS(ledger!J:J, ledger!B:B, _xlpm.party, ledger!E:E, "<>*RD*", ledger!D:D, "Silky", ledger!C:C, "<>January Closing CF") )) + _xlfn.IFNA(H135, 0)} -> 0 | Y42: {=_xlfn.BYROW(B86, _xlfn.LAMBDA(_xlpm.party, SUMIFS(ledger!J:J, ledger!B:B, _xlpm.party, ledger!E:E, "<>*RD*", ledger!D:D, "Slub", ledger!C:C, "<>January Closing CF") ))+ _xlfn.IFNA(I135, 0)} -> 0 | Z42: {=_xlfn.BYROW(B86, _xlfn.LAMBDA(_xlpm.party, SUMIFS(ledger!J:J, ledger!B:B, _xlpm.party, ledger!E:E, "<>*RD*", ledger!D:D, "Satin", ledger!C:C, "<>January Closing CF") ))+ _xlfn.IFNA(J135, 0)} -> 0 | AA42: {=_xlfn.BYROW(B86, _xlfn.LAMBDA(_xlpm.party, SUMIFS(ledger!J:J, ledger!B:B, _xlpm.party, ledger!E:E, "<>*RD*", ledger!D:D, "Black-Chamki", ledger!C:C, "<>January Closing CF") ))+ _xlfn.IFNA(K135, 0)} -> 0 | AB42: {=_xlfn.BYROW(B86, _xlfn.LAMBDA(_xlpm.party, SUMIFS(ledger!J:J, ledger!B:B, _xlpm.party, ledger!E:E, "<>*RD*", ledger!D:D, "Kataan", ledger!C:C, "<>January Closing CF") ))+ _xlfn.IFNA(L135, 0)} -> 0 | AC42: {=_xlfn.BYROW(B86, _xlfn.LAMBDA(_xlpm.party, SUMIFS(ledger!J:J, ledger!B:B, _xlpm.party, ledger!E:E, "<>*RD*", ledger!D:D, "Munaar", ledger!C:C, "<>January Closing CF") ))+ _xlfn.IFNA(M135, 0)} -> 0 | AD42: {=_xlfn.BYROW(B86, _xlfn.LAMBDA(_xlpm.party, SUMIFS(ledger!J:J, ledger!B:B, _xlpm.party, ledger!E:E, "<>*RD*", ledger!D:D, "Custom", ledger!C:C, "<>January Closing CF") ))+ _xlfn.IFNA(N135, 0)} -> 0 | AE42: =W42+X42+Y42+Z42+AA42+AB42+AC42+AD42 -> 0 | AF42: =(SUMIF(Table14[Party],R42,Table14[Credit]))+_xlfn.IFNA(P135,0) -> 0 | AG42: =AE42-AF42 -> 0
B47: Billing September
C48: Gaz | D48: Total Metres | E48: Total Chamki | F48: Total Super Silky | G48: Billing (Chamki/Crinkle) | H48: Billing (Super Chamki) | I48: Billing (Slub) | J48: Billing (Satin) | K48: Billing (Black-chamki) | L48: Billing (Kataan) | M48: Billing (Munaar) | N48: Billing Custom | O48: Adjusted Bill | P48: Amount Paid | Q48: Balance | R48: Rate (Chamki) | S48: Rate (Super Silky)
A49: Parties: | B49: {=_xlfn.UNIQUE(Table1[Party Name])} -> BSC | C49: {=_xlfn.BYROW(_xlfn.ANCHORARRAY(B49),_xlfn.LAMBDA(_xlpm.party,SUMIFS(ledger!G:G,ledger!B:B,_xlpm.party,ledger!E:E,"<>*RD*")))} -> 908449 | D49: {=_xlfn.BYROW(_xlfn.ANCHORARRAY(B49), _xlfn.LAMBDA(_xlpm.party, SUMIFS(ledger!G:G, ledger!B:B, _xlpm.party, ledger!E:E, "<>*RD*") / 1.0936 ))} -> 830695.87 | E49: {=(_xlfn.BYROW(_xlfn.ANCHORARRAY(B49),_xlfn.LAMBDA(_xlpm.party,SUMIFS(ledger!G:G,ledger!B:B,_xlpm.party,ledger!E:E,"<>*RD*",ledger!D:D,"Chamki")+SUMIFS(ledger!G:G, ledger!B:B, _xlpm.party, ledger!E:E, "<>*RD*", ledger!D:D, "Crinkle")))/1.0936)} -> 452989.21 | F49: {=(_xlfn.BYROW(_xlfn.ANCHORARRAY(B49),_xlfn.LAMBDA(_xlpm.party,SUMIFS(ledger!G:G,ledger!B:B,_xlpm.party,ledger!E:E,"<>*RD*",ledger!D:D,"Silky")))/1.0936)} -> 195849.49 | G49: {=(_xlfn.BYROW(B49,_xlfn.LAMBDA(_xlpm.party, (SUMIFS(ledger!J:J,ledger!B:B,_xlpm.party,ledger!E:E,"<>*RD*",ledger!D:D,"Chamki",ledger!C:C,"<>January Closing CF")+ SUMIFS(ledger!J:J,ledger!B:B,_xlpm.party,ledger!E:E,"<>*RD*",ledger!D:D,"Crinkle",ledger!C:C,"<>January Closing CF") ))))} -> 4529892.1 | H49: {=_xlfn.BYROW(B49, _xlfn.LAMBDA(_xlpm.party, SUMIFS(ledger!J:J, ledger!B:B, _xlpm.party, ledger!E:E, "<>*RD*", ledger!D:D, "Silky", ledger!C:C, "<>January Closing CF") ))} -> 2546043.3 | I49: {=_xlfn.BYROW(B49, _xlfn.LAMBDA(_xlpm.party, SUMIFS(ledger!J:J, ledger!B:B, _xlpm.party, ledger!E:E, "<>*RD*", ledger!D:D, "Slub", ledger!C:C, "<>January Closing CF") ))} -> 0 | J49: {=_xlfn.BYROW(B49, _xlfn.LAMBDA(_xlpm.party, SUMIFS(ledger!J:J, ledger!B:B, _xlpm.party, ledger!E:E, "<>*RD*", ledger!D:D, "Satin", ledger!C:C, "<>January Closing CF") ))} -> 0 | K49: {=_xlfn.BYROW(B49, _xlfn.LAMBDA(_xlpm.party, SUMIFS(ledger!J:J, ledger!B:B, _xlpm.party, ledger!E:E, "<>*RD*", ledger!D:D, "Black-chamki", ledger!C:C, "<>January Closing CF") ))} -> 0 | L49: {=_xlfn.BYROW(B49, _xlfn.LAMBDA(_xlpm.party, SUMIFS(ledger!J:J, ledger!B:B, _xlpm.party, ledger!E:E, "<>*RD*", ledger!D:D, "Kataan", ledger!C:C, "<>January Closing CF") ))} -> 2000428.9 | M49: {=_xlfn.BYROW(B49, _xlfn.LAMBDA(_xlpm.party, SUMIFS(ledger!J:J, ledger!B:B, _xlpm.party, ledger!E:E, "<>*RD*", ledger!D:D, "Munaar", ledger!C:C, "<>January Closing CF") ))} -> 0 | N49: {=_xlfn.BYROW(B49, _xlfn.LAMBDA(_xlpm.party, SUMIFS(ledger!J:J, ledger!B:B, _xlpm.party, ledger!E:E, "<>*RD*", ledger!D:D, "Custom", ledger!C:C, "<>January Closing CF") ))} -> 0 | O49: =SUM(G49:N49) -> 9076364.3 | P49: =(SUMIF(Table14[Party],B49,Table14[Credit])) -> 0 | Q49: =O49-P49 -> 9076364.3 | R49: 10 | S49: 12
B50: Ejaz Sahab | C50: 91557 | D50: 83720.739 | E50: 0 | F50: 83720.739 | G50: {=(_xlfn.BYROW(B50,_xlfn.LAMBDA(_xlpm.party, (SUMIFS(ledger!J:J,ledger!B:B,_xlpm.party,ledger!E:E,"<>*RD*",ledger!D:D,"Chamki",ledger!C:C,"<>January Closing CF")+ SUMIFS(ledger!J:J,ledger!B:B,_xlpm.party,ledger!E:E,"<>*RD*",ledger!D:D,"Crinkle",ledger!C:C,"<>January Closing CF") ))))} -> 0 | H50: {=_xlfn.BYROW(B50, _xlfn.LAMBDA(_xlpm.party, SUMIFS(ledger!J:J, ledger!B:B, _xlpm.party, ledger!E:E, "<>*RD*", ledger!D:D, "Silky", ledger!C:C, "<>January Closing CF") ))} -> 1088369.6 | I50: {=_xlfn.BYROW(B50, _xlfn.LAMBDA(_xlpm.party, SUMIFS(ledger!J:J, ledger!B:B, _xlpm.party, ledger!E:E, "<>*RD*", ledger!D:D, "Slub", ledger!C:C, "<>January Closing CF") ))} -> 0 | J50: {=_xlfn.BYROW(B50, _xlfn.LAMBDA(_xlpm.party, SUMIFS(ledger!J:J, ledger!B:B, _xlpm.party, ledger!E:E, "<>*RD*", ledger!D:D, "Satin", ledger!C:C, "<>January Closing CF") ))} -> 0 | K50: {=_xlfn.BYROW(B50, _xlfn.LAMBDA(_xlpm.party, SUMIFS(ledger!J:J, ledger!B:B, _xlpm.party, ledger!E:E, "<>*RD*", ledger!D:D, "Black-chamki", ledger!C:C, "<>January Closing CF") ))} -> 0 | L50: {=_xlfn.BYROW(B50, _xlfn.LAMBDA(_xlpm.party, SUMIFS(ledger!J:J, ledger!B:B, _xlpm.party, ledger!E:E, "<>*RD*", ledger!D:D, "Kataan", ledger!C:C, "<>January Closing CF") ))} -> 0 | M50: {=_xlfn.BYROW(B50, _xlfn.LAMBDA(_xlpm.party, SUMIFS(ledger!J:J, ledger!B:B, _xlpm.party, ledger!E:E, "<>*RD*", ledger!D:D, "Munaar", ledger!C:C, "<>January Closing CF") ))} -> 0 | N50: {=_xlfn.BYROW(B50, _xlfn.LAMBDA(_xlpm.party, SUMIFS(ledger!J:J, ledger!B:B, _xlpm.party, ledger!E:E, "<>*RD*", ledger!D:D, "Custom", ledger!C:C, "<>January Closing CF") ))} -> 0 | O50: =SUM(G50:N50) -> 1088369.6 | P50: =(SUMIF(Table14[Party],B50,Table14[Credit])) -> 1147303 | Q50: =O50-P50 -> -58933.395 | R50: 10 | S50: 12
B51: Arshad | C51: 125826 | D51: 115056.69 | E51: 95707.754 | F51: 19348.939 | G51: {=(_xlfn.BYROW(B51,_xlfn.LAMBDA(_xlpm.party, (SUMIFS(ledger!J:J,ledger!B:B,_xlpm.party,ledger!E:E,"<>*RD*",ledger!D:D,"Chamki",ledger!C:C,"<>January Closing CF")+ SUMIFS(ledger!J:J,ledger!B:B,_xlpm.party,ledger!E:E,"<>*RD*",ledger!D:D,"Crinkle",ledger!C:C,"<>January Closing CF") ))))} -> 957077.54 | H51: {=_xlfn.BYROW(B51, _xlfn.LAMBDA(_xlpm.party, SUMIFS(ledger!J:J, ledger!B:B, _xlpm.party, ledger!E:E, "<>*RD*", ledger!D:D, "Silky", ledger!C:C, "<>January Closing CF") ))} -> 251536.21 | I51: {=_xlfn.BYROW(B51, _xlfn.LAMBDA(_xlpm.party, SUMIFS(ledger!J:J, ledger!B:B, _xlpm.party, ledger!E:E, "<>*RD*", ledger!D:D, "Slub", ledger!C:C, "<>January Closing CF") ))} -> 0 | J51: {=_xlfn.BYROW(B51, _xlfn.LAMBDA(_xlpm.party, SUMIFS(ledger!J:J, ledger!B:B, _xlpm.party, ledger!E:E, "<>*RD*", ledger!D:D, "Satin", ledger!C:C, "<>January Closing CF") ))} -> 0 | K51: {=_xlfn.BYROW(B51, _xlfn.LAMBDA(_xlpm.party, SUMIFS(ledger!J:J, ledger!B:B, _xlpm.party, ledger!E:E, "<>*RD*", ledger!D:D, "Black-chamki", ledger!C:C, "<>January Closing CF") ))} -> 0 | L51: {=_xlfn.BYROW(B51, _xlfn.LAMBDA(_xlpm.party, SUMIFS(ledger!J:J, ledger!B:B, _xlpm.party, ledger!E:E, "<>*RD*", ledger!D:D, "Kataan", ledger!C:C, "<>January Closing CF") ))} -> 0 | M51: {=_xlfn.BYROW(B51, _xlfn.LAMBDA(_xlpm.party, SUMIFS(ledger!J:J, ledger!B:B, _xlpm.party, ledger!E:E, "<>*RD*", ledger!D:D, "Munaar", ledger!C:C, "<>January Closing CF") ))} -> 0 | N51: {=_xlfn.BYROW(B51, _xlfn.LAMBDA(_xlpm.party, SUMIFS(ledger!J:J, ledger!B:B, _xlpm.party, ledger!E:E, "<>*RD*", ledger!D:D, "Custom", ledger!C:C, "<>January Closing CF") ))} -> 0 | O51: =SUM(G51:N51) -> 1208613.8 | P51: =(SUMIF(Table14[Party],B51,Table14[Credit])) -> 1283000 | Q51: =O51-P51 -> -74386.247 | R51: 10 | S51: 12
B52: Shehzad Kamoki | C52: 0 | D52: 0 | E52: 0 | F52: 0 | G52: {=(_xlfn.BYROW(B52,_xlfn.LAMBDA(_xlpm.party, (SUMIFS(ledger!J:J,ledger!B:B,_xlpm.party,ledger!E:E,"<>*RD*",ledger!D:D,"Chamki",ledger!C:C,"<>January Closing CF")+ SUMIFS(ledger!J:J,ledger!B:B,_xlpm.party,ledger!E:E,"<>*RD*",ledger!D:D,"Crinkle",ledger!C:C,"<>January Closing CF") ))))} -> 0 | H52: {=_xlfn.BYROW(B52, _xlfn.LAMBDA(_xlpm.party, SUMIFS(ledger!J:J, ledger!B:B, _xlpm.party, ledger!E:E, "<>*RD*", ledger!D:D, "Silky", ledger!C:C, "<>January Closing CF") ))} -> 0 | I52: {=_xlfn.BYROW(B52, _xlfn.LAMBDA(_xlpm.party, SUMIFS(ledger!J:J, ledger!B:B, _xlpm.party, ledger!E:E, "<>*RD*", ledger!D:D, "Slub", ledger!C:C, "<>January Closing CF") ))} -> 0 | J52: {=_xlfn.BYROW(B52, _xlfn.LAMBDA(_xlpm.party, SUMIFS(ledger!J:J, ledger!B:B, _xlpm.party, ledger!E:E, "<>*RD*", ledger!D:D, "Satin", ledger!C:C, "<>January Closing CF") ))} -> 0 | K52: {=_xlfn.BYROW(B52, _xlfn.LAMBDA(_xlpm.party, SUMIFS(ledger!J:J, ledger!B:B, _xlpm.party, ledger!E:E, "<>*RD*", ledger!D:D, "Black-chamki", ledger!C:C, "<>January Closing CF") ))} -> 0 | L52: {=_xlfn.BYROW(B52, _xlfn.LAMBDA(_xlpm.party, SUMIFS(ledger!J:J, ledger!B:B, _xlpm.party, ledger!E:E, "<>*RD*", ledger!D:D, "Kataan", ledger!C:C, "<>January Closing CF") ))} -> 0 | M52: {=_xlfn.BYROW(B52, _xlfn.LAMBDA(_xlpm.party, SUMIFS(ledger!J:J, ledger!B:B, _xlpm.party, ledger!E:E, "<>*RD*", ledger!D:D, "Munaar", ledger!C:C, "<>January Closing CF") ))} -> 0 | N52: {=_xlfn.BYROW(B52, _xlfn.LAMBDA(_xlpm.party, SUMIFS(ledger!J:J, ledger!B:B, _xlpm.party, ledger!E:E, "<>*RD*", ledger!D:D, "Custom", ledger!C:C, "<>January Closing CF") ))} -> 0 | O52: =SUM(G52:N52) -> 0 | P52: =(SUMIF(Table14[Party],B52,Table14[Credit])) -> 0 | Q52: =O52-P52 -> 0 | R52: 10.5 | S52: 13
B53: Sufi Nawaz Sahab | C53: 0 | D53: 0 | E53: 0 | F53: 0 | G53: {=(_xlfn.BYROW(B53,_xlfn.LAMBDA(_xlpm.party, (SUMIFS(ledger!J:J,ledger!B:B,_xlpm.party,ledger!E:E,"<>*RD*",ledger!D:D,"Chamki",ledger!C:C,"<>January Closing CF")+ SUMIFS(ledger!J:J,ledger!B:B,_xlpm.party,ledger!E:E,"<>*RD*",ledger!D:D,"Crinkle",ledger!C:C,"<>January Closing CF") ))))} -> 0 | H53: {=_xlfn.BYROW(B53, _xlfn.LAMBDA(_xlpm.party, SUMIFS(ledger!J:J, ledger!B:B, _xlpm.party, ledger!E:E, "<>*RD*", ledger!D:D, "Silky", ledger!C:C, "<>January Closing CF") ))} -> 0 | I53: {=_xlfn.BYROW(B53, _xlfn.LAMBDA(_xlpm.party, SUMIFS(ledger!J:J, ledger!B:B, _xlpm.party, ledger!E:E, "<>*RD*", ledger!D:D, "Slub", ledger!C:C, "<>January Closing CF") ))} -> 0 | J53: {=_xlfn.BYROW(B53, _xlfn.LAMBDA(_xlpm.party, SUMIFS(ledger!J:J, ledger!B:B, _xlpm.party, ledger!E:E, "<>*RD*", ledger!D:D, "Satin", ledger!C:C, "<>January Closing CF") ))} -> 0 | K53: {=_xlfn.BYROW(B53, _xlfn.LAMBDA(_xlpm.party, SUMIFS(ledger!J:J, ledger!B:B, _xlpm.party, ledger!E:E, "<>*RD*", ledger!D:D, "Black-chamki", ledger!C:C, "<>January Closing CF") ))} -> 0 | L53: {=_xlfn.BYROW(B53, _xlfn.LAMBDA(_xlpm.party, SUMIFS(ledger!J:J, ledger!B:B, _xlpm.party, ledger!E:E, "<>*RD*", ledger!D:D, "Kataan", ledger!C:C, "<>January Closing CF") ))} -> 0 | M53: {=_xlfn.BYROW(B53, _xlfn.LAMBDA(_xlpm.party, SUMIFS(ledger!J:J, ledger!B:B, _xlpm.party, ledger!E:E, "<>*RD*", ledger!D:D, "Munaar", ledger!C:C, "<>January Closing CF") ))} -> 0 | N53: {=_xlfn.BYROW(B53, _xlfn.LAMBDA(_xlpm.party, SUMIFS(ledger!J:J, ledger!B:B, _xlpm.party, ledger!E:E, "<>*RD*", ledger!D:D, "Custom", ledger!C:C, "<>January Closing CF") ))} -> 0 | O53: =SUM(G53:N53) -> 0 | P53: =(SUMIF(Table14[Party],B53,Table14[Credit])) -> 0 | Q53: =O53-P53 -> 0 | R53: 10 | S53: 12
B54: Sajad Khan | C54: 69160 | D54: 63240.673 | E54: 63240.673 | F54: 0 | G54: {=(_xlfn.BYROW(B54,_xlfn.LAMBDA(_xlpm.party, (SUMIFS(ledger!J:J,ledger!B:B,_xlpm.party,ledger!E:E,"<>*RD*",ledger!D:D,"Chamki",ledger!C:C,"<>January Closing CF")+ SUMIFS(ledger!J:J,ledger!B:B,_xlpm.party,ledger!E:E,"<>*RD*",ledger!D:D,"Crinkle",ledger!C:C,"<>January Closing CF") ))))} -> 632406.73 | H54: {=_xlfn.BYROW(B54, _xlfn.LAMBDA(_xlpm.party, SUMIFS(ledger!J:J, ledger!B:B, _xlpm.party, ledger!E:E, "<>*RD*", ledger!D:D, "Silky", ledger!C:C, "<>January Closing CF") ))} -> 0 | I54: {=_xlfn.BYROW(B54, _xlfn.LAMBDA(_xlpm.party, SUMIFS(ledger!J:J, ledger!B:B, _xlpm.party, ledger!E:E, "<>*RD*", ledger!D:D, "Slub", ledger!C:C, "<>January Closing CF") ))} -> 0 | J54: {=_xlfn.BYROW(B54, _xlfn.LAMBDA(_xlpm.party, SUMIFS(ledger!J:J, ledger!B:B, _xlpm.party, ledger!E:E, "<>*RD*", ledger!D:D, "Satin", ledger!C:C, "<>January Closing CF") ))} -> 0 | K54: {=_xlfn.BYROW(B54, _xlfn.LAMBDA(_xlpm.party, SUMIFS(ledger!J:J, ledger!B:B, _xlpm.party, ledger!E:E, "<>*RD*", ledger!D:D, "Black-chamki", ledger!C:C, "<>January Closing CF") ))} -> 0 | L54: {=_xlfn.BYROW(B54, _xlfn.LAMBDA(_xlpm.party, SUMIFS(ledger!J:J, ledger!B:B, _xlpm.party, ledger!E:E, "<>*RD*", ledger!D:D, "Kataan", ledger!C:C, "<>January Closing CF") ))} -> 0 | M54: {=_xlfn.BYROW(B54, _xlfn.LAMBDA(_xlpm.party, SUMIFS(ledger!J:J, ledger!B:B, _xlpm.party, ledger!E:E, "<>*RD*", ledger!D:D, "Munaar", ledger!C:C, "<>January Closing CF") ))} -> 0 | N54: {=_xlfn.BYROW(B54, _xlfn.LAMBDA(_xlpm.party, SUMIFS(ledger!J:J, ledger!B:B, _xlpm.party, ledger!E:E, "<>*RD*", ledger!D:D, "Custom", ledger!C:C, "<>January Closing CF") ))} -> 0 | O54: =SUM(G54:N54) -> 632406.73 | P54: =(SUMIF(Table14[Party],B54,Table14[Credit])) -> 839000 | Q54: =O54-P54 -> -206593.27 | R54: 10 | S54: 12
B55: Raaz Fabrics | C55: 25442 | D55: 23264.448 | E55: 23264.448 | F55: 0 | G55: {=(_xlfn.BYROW(B55,_xlfn.LAMBDA(_xlpm.party, (SUMIFS(ledger!J:J,ledger!B:B,_xlpm.party,ledger!E:E,"<>*RD*",ledger!D:D,"Chamki",ledger!C:C,"<>January Closing CF")+ SUMIFS(ledger!J:J,ledger!B:B,_xlpm.party,ledger!E:E,"<>*RD*",ledger!D:D,"Crinkle",ledger!C:C,"<>January Closing CF") ))))} -> 232644.48 | H55: {=_xlfn.BYROW(B55, _xlfn.LAMBDA(_xlpm.party, SUMIFS(ledger!J:J, ledger!B:B, _xlpm.party, ledger!E:E, "<>*RD*", ledger!D:D, "Silky", ledger!C:C, "<>January Closing CF") ))} -> 0 | I55: {=_xlfn.BYROW(B55, _xlfn.LAMBDA(_xlpm.party, SUMIFS(ledger!J:J, ledger!B:B, _xlpm.party, ledger!E:E, "<>*RD*", ledger!D:D, "Slub", ledger!C:C, "<>January Closing CF") ))} -> 0 | J55: {=_xlfn.BYROW(B55, _xlfn.LAMBDA(_xlpm.party, SUMIFS(ledger!J:J, ledger!B:B, _xlpm.party, ledger!E:E, "<>*RD*", ledger!D:D, "Satin", ledger!C:C, "<>January Closing CF") ))} -> 0 | K55: {=_xlfn.BYROW(B55, _xlfn.LAMBDA(_xlpm.party, SUMIFS(ledger!J:J, ledger!B:B, _xlpm.party, ledger!E:E, "<>*RD*", ledger!D:D, "Black-chamki", ledger!C:C, "<>January Closing CF") ))} -> 0 | L55: {=_xlfn.BYROW(B55, _xlfn.LAMBDA(_xlpm.party, SUMIFS(ledger!J:J, ledger!B:B, _xlpm.party, ledger!E:E, "<>*RD*", ledger!D:D, "Kataan", ledger!C:C, "<>January Closing CF") ))} -> 0 | M55: {=_xlfn.BYROW(B55, _xlfn.LAMBDA(_xlpm.party, SUMIFS(ledger!J:J, ledger!B:B, _xlpm.party, ledger!E:E, "<>*RD*", ledger!D:D, "Munaar", ledger!C:C, "<>January Closing CF") ))} -> 0 | N55: {=_xlfn.BYROW(B55, _xlfn.LAMBDA(_xlpm.party, SUMIFS(ledger!J:J, ledger!B:B, _xlpm.party, ledger!E:E, "<>*RD*", ledger!D:D, "Custom", ledger!C:C, "<>January Closing CF") ))} -> 0 | O55: =SUM(G55:N55) -> 232644.48 | P55: =(SUMIF(Table14[Party],B55,Table14[Credit])) -> 200000 | Q55: =O55-P55 -> 32644.477 | R55: 10 | S55: 12
B56: Azam | C56: 0 | D56: 0 | E56: 0 | F56: 0 | G56: {=(_xlfn.BYROW(B56,_xlfn.LAMBDA(_xlpm.party, (SUMIFS(ledger!J:J,ledger!B:B,_xlpm.party,ledger!E:E,"<>*RD*",ledger!D:D,"Chamki",ledger!C:C,"<>January Closing CF")+ SUMIFS(ledger!J:J,ledger!B:B,_xlpm.party,ledger!E:E,"<>*RD*",ledger!D:D,"Crinkle",ledger!C:C,"<>January Closing CF") ))))} -> 0 | H56: {=_xlfn.BYROW(B56, _xlfn.LAMBDA(_xlpm.party, SUMIFS(ledger!J:J, ledger!B:B, _xlpm.party, ledger!E:E, "<>*RD*", ledger!D:D, "Silky", ledger!C:C, "<>January Closing CF") ))} -> 0 | I56: {=_xlfn.BYROW(B56, _xlfn.LAMBDA(_xlpm.party, SUMIFS(ledger!J:J, ledger!B:B, _xlpm.party, ledger!E:E, "<>*RD*", ledger!D:D, "Slub", ledger!C:C, "<>January Closing CF") ))} -> 0 | J56: {=_xlfn.BYROW(B56, _xlfn.LAMBDA(_xlpm.party, SUMIFS(ledger!J:J, ledger!B:B, _xlpm.party, ledger!E:E, "<>*RD*", ledger!D:D, "Satin", ledger!C:C, "<>January Closing CF") ))} -> 0 | K56: {=_xlfn.BYROW(B56, _xlfn.LAMBDA(_xlpm.party, SUMIFS(ledger!J:J, ledger!B:B, _xlpm.party, ledger!E:E, "<>*RD*", ledger!D:D, "Black-chamki", ledger!C:C, "<>January Closing CF") ))} -> 0 | L56: {=_xlfn.BYROW(B56, _xlfn.LAMBDA(_xlpm.party, SUMIFS(ledger!J:J, ledger!B:B, _xlpm.party, ledger!E:E, "<>*RD*", ledger!D:D, "Kataan", ledger!C:C, "<>January Closing CF") ))} -> 0 | M56: {=_xlfn.BYROW(B56, _xlfn.LAMBDA(_xlpm.party, SUMIFS(ledger!J:J, ledger!B:B, _xlpm.party, ledger!E:E, "<>*RD*", ledger!D:D, "Munaar", ledger!C:C, "<>January Closing CF") ))} -> 0 | N56: {=_xlfn.BYROW(B56, _xlfn.LAMBDA(_xlpm.party, SUMIFS(ledger!J:J, ledger!B:B, _xlpm.party, ledger!E:E, "<>*RD*", ledger!D:D, "Custom", ledger!C:C, "<>January Closing CF") ))} -> 0 | O56: =SUM(G56:N56) -> 0 | P56: =(SUMIF(Table14[Party],B56,Table14[Credit])) -> 0 | Q56: =O56-P56 -> 0 | R56: 10 | S56: 12
B57: Ubaidullah | C57: 109555 | D57: 100178.31 | E57: 0 | F57: 100178.31 | G57: {=(_xlfn.BYROW(B57,_xlfn.LAMBDA(_xlpm.party, (SUMIFS(ledger!J:J,ledger!B:B,_xlpm.party,ledger!E:E,"<>*RD*",ledger!D:D,"Chamki",ledger!C:C,"<>January Closing CF")+ SUMIFS(ledger!J:J,ledger!B:B,_xlpm.party,ledger!E:E,"<>*RD*",ledger!D:D,"Crinkle",ledger!C:C,"<>January Closing CF") ))))} -> 0 | H57: {=_xlfn.BYROW(B57, _xlfn.LAMBDA(_xlpm.party, SUMIFS(ledger!J:J, ledger!B:B, _xlpm.party, ledger!E:E, "<>*RD*", ledger!D:D, "Silky", ledger!C:C, "<>January Closing CF") ))} -> 1202139.7 | I57: {=_xlfn.BYROW(B57, _xlfn.LAMBDA(_xlpm.party, SUMIFS(ledger!J:J, ledger!B:B, _xlpm.party, ledger!E:E, "<>*RD*", ledger!D:D, "Slub", ledger!C:C, "<>January Closing CF") ))} -> 0 | J57: {=_xlfn.BYROW(B57, _xlfn.LAMBDA(_xlpm.party, SUMIFS(ledger!J:J, ledger!B:B, _xlpm.party, ledger!E:E, "<>*RD*", ledger!D:D, "Satin", ledger!C:C, "<>January Closing CF") ))} -> 0 | K57: {=_xlfn.BYROW(B57, _xlfn.LAMBDA(_xlpm.party, SUMIFS(ledger!J:J, ledger!B:B, _xlpm.party, ledger!E:E, "<>*RD*", ledger!D:D, "Black-chamki", ledger!C:C, "<>January Closing CF") ))} -> 0 | L57: {=_xlfn.BYROW(B57, _xlfn.LAMBDA(_xlpm.party, SUMIFS(ledger!J:J, ledger!B:B, _xlpm.party, ledger!E:E, "<>*RD*", ledger!D:D, "Kataan", ledger!C:C, "<>January Closing CF") ))} -> 0 | M57: {=_xlfn.BYROW(B57, _xlfn.LAMBDA(_xlpm.party, SUMIFS(ledger!J:J, ledger!B:B, _xlpm.party, ledger!E:E, "<>*RD*", ledger!D:D, "Munaar", ledger!C:C, "<>January Closing CF") ))} -> 0 | N57: {=_xlfn.BYROW(B57, _xlfn.LAMBDA(_xlpm.party, SUMIFS(ledger!J:J, ledger!B:B, _xlpm.party, ledger!E:E, "<>*RD*", ledger!D:D, "Custom", ledger!C:C, "<>January Closing CF") ))} -> 0 | O57: =SUM(G57:N57) -> 1202139.7 | P57: =(SUMIF(Table14[Party],B57,Table14[Credit])) -> 1101800 | Q57: =O57-P57 -> 100339.72 | R57: 10 | S57: 12 | V57: Row Labels | W57: Sum of Tiyaar | X57: Sum of Total
B58: Ashraf Zia | C58: 0 | D58: 0 | E58: 0 | F58: 0 | G58: {=(_xlfn.BYROW(B58,_xlfn.LAMBDA(_xlpm.party, (SUMIFS(ledger!J:J,ledger!B:B,_xlpm.party,ledger!E:E,"<>*RD*",ledger!D:D,"Chamki",ledger!C:C,"<>January Closing CF")+ SUMIFS(ledger!J:J,ledger!B:B,_xlpm.party,ledger!E:E,"<>*RD*",ledger!D:D,"Crinkle",ledger!C:C,"<>January Closing CF") ))))} -> 0 | H58: {=_xlfn.BYROW(B58, _xlfn.LAMBDA(_xlpm.party, SUMIFS(ledger!J:J, ledger!B:B, _xlpm.party, ledger!E:E, "<>*RD*", ledger!D:D, "Silky", ledger!C:C, "<>January Closing CF") ))} -> 0 | I58: {=_xlfn.BYROW(B58, _xlfn.LAMBDA(_xlpm.party, SUMIFS(ledger!J:J, ledger!B:B, _xlpm.party, ledger!E:E, "<>*RD*", ledger!D:D, "Slub", ledger!C:C, "<>January Closing CF") ))} -> 0 | J58: {=_xlfn.BYROW(B58, _xlfn.LAMBDA(_xlpm.party, SUMIFS(ledger!J:J, ledger!B:B, _xlpm.party, ledger!E:E, "<>*RD*", ledger!D:D, "Satin", ledger!C:C, "<>January Closing CF") ))} -> 0 | K58: {=_xlfn.BYROW(B58, _xlfn.LAMBDA(_xlpm.party, SUMIFS(ledger!J:J, ledger!B:B, _xlpm.party, ledger!E:E, "<>*RD*", ledger!D:D, "Black-chamki", ledger!C:C, "<>January Closing CF") ))} -> 0 | L58: {=_xlfn.BYROW(B58, _xlfn.LAMBDA(_xlpm.party, SUMIFS(ledger!J:J, ledger!B:B, _xlpm.party, ledger!E:E, "<>*RD*", ledger!D:D, "Kataan", ledger!C:C, "<>January Closing CF") ))} -> 0 | M58: {=_xlfn.BYROW(B58, _xlfn.LAMBDA(_xlpm.party, SUMIFS(ledger!J:J, ledger!B:B, _xlpm.party, ledger!E:E, "<>*RD*", ledger!D:D, "Munaar", ledger!C:C, "<>January Closing CF") ))} -> 0 | N58: {=_xlfn.BYROW(B58, _xlfn.LAMBDA(_xlpm.party, SUMIFS(ledger!J:J, ledger!B:B, _xlpm.party, ledger!E:E, "<>*RD*", ledger!D:D, "Custom", ledger!C:C, "<>January Closing CF") ))} -> 0 | O58: =SUM(G58:N58) -> 0 | P58: =(SUMIF(Table14[Party],B58,Table14[Credit])) -> 0 | Q58: =O58-P58 -> 0 | R58: 12 | S58: 12 | V58: BSC | W58: 830695.87 | X58: 5987757.9
B59: Hafiz Qureshi | C59: 235735 | D59: 215558.71 | E59: 168209.58 | F59: 0 | G59: {=(_xlfn.BYROW(B59,_xlfn.LAMBDA(_xlpm.party, (SUMIFS(ledger!J:J,ledger!B:B,_xlpm.party,ledger!E:E,"<>*RD*",ledger!D:D,"Chamki",ledger!C:C,"<>January Closing CF")+ SUMIFS(ledger!J:J,ledger!B:B,_xlpm.party,ledger!E:E,"<>*RD*",ledger!D:D,"Crinkle",ledger!C:C,"<>January Closing CF") ))))} -> 1682095.8 | H59: {=_xlfn.BYROW(B59, _xlfn.LAMBDA(_xlpm.party, SUMIFS(ledger!J:J, ledger!B:B, _xlpm.party, ledger!E:E, "<>*RD*", ledger!D:D, "Silky", ledger!C:C, "<>January Closing CF") ))} -> 0 | I59: {=_xlfn.BYROW(B59, _xlfn.LAMBDA(_xlpm.party, SUMIFS(ledger!J:J, ledger!B:B, _xlpm.party, ledger!E:E, "<>*RD*", ledger!D:D, "Slub", ledger!C:C, "<>January Closing CF") ))} -> 0 | J59: {=_xlfn.BYROW(B59, _xlfn.LAMBDA(_xlpm.party, SUMIFS(ledger!J:J, ledger!B:B, _xlpm.party, ledger!E:E, "<>*RD*", ledger!D:D, "Satin", ledger!C:C, "<>January Closing CF") ))} -> 0 | K59: {=_xlfn.BYROW(B59, _xlfn.LAMBDA(_xlpm.party, SUMIFS(ledger!J:J, ledger!B:B, _xlpm.party, ledger!E:E, "<>*RD*", ledger!D:D, "Black-chamki", ledger!C:C, "<>January Closing CF") ))} -> 0 | L59: {=_xlfn.BYROW(B59, _xlfn.LAMBDA(_xlpm.party, SUMIFS(ledger!J:J, ledger!B:B, _xlpm.party, ledger!E:E, "<>*RD*", ledger!D:D, "Kataan", ledger!C:C, "<>January Closing CF") ))} -> 520840.34 | M59: {=_xlfn.BYROW(B59, _xlfn.LAMBDA(_xlpm.party, SUMIFS(ledger!J:J, ledger!B:B, _xlpm.party, ledger!E:E, "<>*RD*", ledger!D:D, "Munaar", ledger!C:C, "<>January Closing CF") ))} -> 0 | N59: {=_xlfn.BYROW(B59, _xlfn.LAMBDA(_xlpm.party, SUMIFS(ledger!J:J, ledger!B:B, _xlpm.party, ledger!E:E, "<>*RD*", ledger!D:D, "Custom", ledger!C:C, "<>January Closing CF") ))} -> 0 | O59: =SUM(G59:N59) -> 2202936.2 | P59: =(SUMIF(Table14[Party],B59,Table14[Credit])) -> 1679674 | Q59: =O59-P59 -> 523262.17 | R59: 10 | S59: 12 | V59: Ejaz Sahab | W59: 83720.739 | X59: 1004648.9
B60: Badshah Fabrics | C60: 0 | D60: 0 | E60: 0 | F60: 0 | G60: {=(_xlfn.BYROW(B60,_xlfn.LAMBDA(_xlpm.party, (SUMIFS(ledger!J:J,ledger!B:B,_xlpm.party,ledger!E:E,"<>*RD*",ledger!D:D,"Chamki",ledger!C:C,"<>January Closing CF")+ SUMIFS(ledger!J:J,ledger!B:B,_xlpm.party,ledger!E:E,"<>*RD*",ledger!D:D,"Crinkle",ledger!C:C,"<>January Closing CF") ))))} -> 0 | H60: {=_xlfn.BYROW(B60, _xlfn.LAMBDA(_xlpm.party, SUMIFS(ledger!J:J, ledger!B:B, _xlpm.party, ledger!E:E, "<>*RD*", ledger!D:D, "Silky", ledger!C:C, "<>January Closing CF") ))} -> 0 | I60: {=_xlfn.BYROW(B60, _xlfn.LAMBDA(_xlpm.party, SUMIFS(ledger!J:J, ledger!B:B, _xlpm.party, ledger!E:E, "<>*RD*", ledger!D:D, "Slub", ledger!C:C, "<>January Closing CF") ))} -> 0 | J60: {=_xlfn.BYROW(B60, _xlfn.LAMBDA(_xlpm.party, SUMIFS(ledger!J:J, ledger!B:B, _xlpm.party, ledger!E:E, "<>*RD*", ledger!D:D, "Satin", ledger!C:C, "<>January Closing CF") ))} -> 0 | K60: {=_xlfn.BYROW(B60, _xlfn.LAMBDA(_xlpm.party, SUMIFS(ledger!J:J, ledger!B:B, _xlpm.party, ledger!E:E, "<>*RD*", ledger!D:D, "Black-chamki", ledger!C:C, "<>January Closing CF") ))} -> 0 | L60: {=_xlfn.BYROW(B60, _xlfn.LAMBDA(_xlpm.party, SUMIFS(ledger!J:J, ledger!B:B, _xlpm.party, ledger!E:E, "<>*RD*", ledger!D:D, "Kataan", ledger!C:C, "<>January Closing CF") ))} -> 0 | M60: {=_xlfn.BYROW(B60, _xlfn.LAMBDA(_xlpm.party, SUMIFS(ledger!J:J, ledger!B:B, _xlpm.party, ledger!E:E, "<>*RD*", ledger!D:D, "Munaar", ledger!C:C, "<>January Closing CF") ))} -> 0 | N60: {=_xlfn.BYROW(B60, _xlfn.LAMBDA(_xlpm.party, SUMIFS(ledger!J:J, ledger!B:B, _xlpm.party, ledger!E:E, "<>*RD*", ledger!D:D, "Custom", ledger!C:C, "<>January Closing CF") ))} -> 0 | O60: =SUM(G60:N60) -> 0 | P60: =(SUMIF(Table14[Party],B60,Table14[Credit])) -> 0 | Q60: =O60-P60 -> 0 | R60: 10 | S60: 12 | V60: Arshad | W60: 115056.69 | X60: 1189264.8
B61: Gauhar Kashif | C61: 0 | D61: 0 | E61: 0 | F61: 0 | G61: {=(_xlfn.BYROW(B61,_xlfn.LAMBDA(_xlpm.party, (SUMIFS(ledger!J:J,ledger!B:B,_xlpm.party,ledger!E:E,"<>*RD*",ledger!D:D,"Chamki",ledger!C:C,"<>January Closing CF")+ SUMIFS(ledger!J:J,ledger!B:B,_xlpm.party,ledger!E:E,"<>*RD*",ledger!D:D,"Crinkle",ledger!C:C,"<>January Closing CF") ))))} -> 0 | H61: {=_xlfn.BYROW(B61, _xlfn.LAMBDA(_xlpm.party, SUMIFS(ledger!J:J, ledger!B:B, _xlpm.party, ledger!E:E, "<>*RD*", ledger!D:D, "Silky", ledger!C:C, "<>January Closing CF") ))} -> 0 | I61: {=_xlfn.BYROW(B61, _xlfn.LAMBDA(_xlpm.party, SUMIFS(ledger!J:J, ledger!B:B, _xlpm.party, ledger!E:E, "<>*RD*", ledger!D:D, "Slub", ledger!C:C, "<>January Closing CF") ))} -> 0 | J61: {=_xlfn.BYROW(B61, _xlfn.LAMBDA(_xlpm.party, SUMIFS(ledger!J:J, ledger!B:B, _xlpm.party, ledger!E:E, "<>*RD*", ledger!D:D, "Satin", ledger!C:C, "<>January Closing CF") ))} -> 0 | K61: {=_xlfn.BYROW(B61, _xlfn.LAMBDA(_xlpm.party, SUMIFS(ledger!J:J, ledger!B:B, _xlpm.party, ledger!E:E, "<>*RD*", ledger!D:D, "Black-chamki", ledger!C:C, "<>January Closing CF") ))} -> 0 | L61: {=_xlfn.BYROW(B61, _xlfn.LAMBDA(_xlpm.party, SUMIFS(ledger!J:J, ledger!B:B, _xlpm.party, ledger!E:E, "<>*RD*", ledger!D:D, "Kataan", ledger!C:C, "<>January Closing CF") ))} -> 0 | M61: {=_xlfn.BYROW(B61, _xlfn.LAMBDA(_xlpm.party, SUMIFS(ledger!J:J, ledger!B:B, _xlpm.party, ledger!E:E, "<>*RD*", ledger!D:D, "Munaar", ledger!C:C, "<>January Closing CF") ))} -> 0 | N61: {=_xlfn.BYROW(B61, _xlfn.LAMBDA(_xlpm.party, SUMIFS(ledger!J:J, ledger!B:B, _xlpm.party, ledger!E:E, "<>*RD*", ledger!D:D, "Custom", ledger!C:C, "<>January Closing CF") ))} -> 0 | O61: =SUM(G61:N61) -> 0 | P61: =(SUMIF(Table14[Party],B61,Table14[Credit])) -> 0 | Q61: =O61-P61 -> 0 | R61: 10 | S61: 12 | V61: Shehzad Kamoki | W61: 0 | X61: 0
B62: Amjad 7up | C62: 0 | D62: 0 | E62: 0 | F62: 0 | G62: {=(_xlfn.BYROW(B62,_xlfn.LAMBDA(_xlpm.party, (SUMIFS(ledger!J:J,ledger!B:B,_xlpm.party,ledger!E:E,"<>*RD*",ledger!D:D,"Chamki",ledger!C:C,"<>January Closing CF")+ SUMIFS(ledger!J:J,ledger!B:B,_xlpm.party,ledger!E:E,"<>*RD*",ledger!D:D,"Crinkle",ledger!C:C,"<>January Closing CF") ))))} -> 0 | H62: {=_xlfn.BYROW(B62, _xlfn.LAMBDA(_xlpm.party, SUMIFS(ledger!J:J, ledger!B:B, _xlpm.party, ledger!E:E, "<>*RD*", ledger!D:D, "Silky", ledger!C:C, "<>January Closing CF") ))} -> 0 | I62: {=_xlfn.BYROW(B62, _xlfn.LAMBDA(_xlpm.party, SUMIFS(ledger!J:J, ledger!B:B, _xlpm.party, ledger!E:E, "<>*RD*", ledger!D:D, "Slub", ledger!C:C, "<>January Closing CF") ))} -> 0 | J62: {=_xlfn.BYROW(B62, _xlfn.LAMBDA(_xlpm.party, SUMIFS(ledger!J:J, ledger!B:B, _xlpm.party, ledger!E:E, "<>*RD*", ledger!D:D, "Satin", ledger!C:C, "<>January Closing CF") ))} -> 0 | K62: {=_xlfn.BYROW(B62, _xlfn.LAMBDA(_xlpm.party, SUMIFS(ledger!J:J, ledger!B:B, _xlpm.party, ledger!E:E, "<>*RD*", ledger!D:D, "Black-chamki", ledger!C:C, "<>January Closing CF") ))} -> 0 | L62: {=_xlfn.BYROW(B62, _xlfn.LAMBDA(_xlpm.party, SUMIFS(ledger!J:J, ledger!B:B, _xlpm.party, ledger!E:E, "<>*RD*", ledger!D:D, "Kataan", ledger!C:C, "<>January Closing CF") ))} -> 0 | M62: {=_xlfn.BYROW(B62, _xlfn.LAMBDA(_xlpm.party, SUMIFS(ledger!J:J, ledger!B:B, _xlpm.party, ledger!E:E, "<>*RD*", ledger!D:D, "Munaar", ledger!C:C, "<>January Closing CF") ))} -> 0 | N62: {=_xlfn.BYROW(B62, _xlfn.LAMBDA(_xlpm.party, SUMIFS(ledger!J:J, ledger!B:B, _xlpm.party, ledger!E:E, "<>*RD*", ledger!D:D, "Custom", ledger!C:C, "<>January Closing CF") ))} -> 0 | O62: =SUM(G62:N62) -> 0 | P62: =(SUMIF(Table14[Party],B62,Table14[Credit])) -> 0 | Q62: =O62-P62 -> 0 | R62: 10 | S62: 12 | V62: Sufi Nawaz Sahab | W62: 0 | X62: 0
B63: Hazrat Khan | C63: 0 | D63: 0 | E63: 0 | F63: 0 | G63: {=(_xlfn.BYROW(B63,_xlfn.LAMBDA(_xlpm.party, (SUMIFS(ledger!J:J,ledger!B:B,_xlpm.party,ledger!E:E,"<>*RD*",ledger!D:D,"Chamki",ledger!C:C,"<>January Closing CF")+ SUMIFS(ledger!J:J,ledger!B:B,_xlpm.party,ledger!E:E,"<>*RD*",ledger!D:D,"Crinkle",ledger!C:C,"<>January Closing CF") ))))} -> 0 | H63: {=_xlfn.BYROW(B63, _xlfn.LAMBDA(_xlpm.party, SUMIFS(ledger!J:J, ledger!B:B, _xlpm.party, ledger!E:E, "<>*RD*", ledger!D:D, "Silky", ledger!C:C, "<>January Closing CF") ))} -> 0 | I63: {=_xlfn.BYROW(B63, _xlfn.LAMBDA(_xlpm.party, SUMIFS(ledger!J:J, ledger!B:B, _xlpm.party, ledger!E:E, "<>*RD*", ledger!D:D, "Slub", ledger!C:C, "<>January Closing CF") ))} -> 0 | J63: {=_xlfn.BYROW(B63, _xlfn.LAMBDA(_xlpm.party, SUMIFS(ledger!J:J, ledger!B:B, _xlpm.party, ledger!E:E, "<>*RD*", ledger!D:D, "Satin", ledger!C:C, "<>January Closing CF") ))} -> 0 | K63: {=_xlfn.BYROW(B63, _xlfn.LAMBDA(_xlpm.party, SUMIFS(ledger!J:J, ledger!B:B, _xlpm.party, ledger!E:E, "<>*RD*", ledger!D:D, "Black-chamki", ledger!C:C, "<>January Closing CF") ))} -> 0 | L63: {=_xlfn.BYROW(B63, _xlfn.LAMBDA(_xlpm.party, SUMIFS(ledger!J:J, ledger!B:B, _xlpm.party, ledger!E:E, "<>*RD*", ledger!D:D, "Kataan", ledger!C:C, "<>January Closing CF") ))} -> 0 | M63: {=_xlfn.BYROW(B63, _xlfn.LAMBDA(_xlpm.party, SUMIFS(ledger!J:J, ledger!B:B, _xlpm.party, ledger!E:E, "<>*RD*", ledger!D:D, "Munaar", ledger!C:C, "<>January Closing CF") ))} -> 0 | N63: {=_xlfn.BYROW(B63, _xlfn.LAMBDA(_xlpm.party, SUMIFS(ledger!J:J, ledger!B:B, _xlpm.party, ledger!E:E, "<>*RD*", ledger!D:D, "Custom", ledger!C:C, "<>January Closing CF") ))} -> 0 | O63: =SUM(G63:N63) -> 0 | P63: =(SUMIF(Table14[Party],B63,Table14[Credit])) -> 0 | Q63: =O63-P63 -> 0 | R63: 10 | S63: 12 | V63: Sajad Khan | W63: 63240.673 | X63: 632406.73
B64: Haseeb Shamsi | C64: 0 | D64: 0 | E64: 0 | F64: 0 | G64: {=(_xlfn.BYROW(B64,_xlfn.LAMBDA(_xlpm.party, (SUMIFS(ledger!J:J,ledger!B:B,_xlpm.party,ledger!E:E,"<>*RD*",ledger!D:D,"Chamki",ledger!C:C,"<>January Closing CF")+ SUMIFS(ledger!J:J,ledger!B:B,_xlpm.party,ledger!E:E,"<>*RD*",ledger!D:D,"Crinkle",ledger!C:C,"<>January Closing CF") ))))} -> 0 | H64: {=_xlfn.BYROW(B64, _xlfn.LAMBDA(_xlpm.party, SUMIFS(ledger!J:J, ledger!B:B, _xlpm.party, ledger!E:E, "<>*RD*", ledger!D:D, "Silky", ledger!C:C, "<>January Closing CF") ))} -> 0 | I64: {=_xlfn.BYROW(B64, _xlfn.LAMBDA(_xlpm.party, SUMIFS(ledger!J:J, ledger!B:B, _xlpm.party, ledger!E:E, "<>*RD*", ledger!D:D, "Slub", ledger!C:C, "<>January Closing CF") ))} -> 0 | J64: {=_xlfn.BYROW(B64, _xlfn.LAMBDA(_xlpm.party, SUMIFS(ledger!J:J, ledger!B:B, _xlpm.party, ledger!E:E, "<>*RD*", ledger!D:D, "Satin", ledger!C:C, "<>January Closing CF") ))} -> 0 | K64: {=_xlfn.BYROW(B64, _xlfn.LAMBDA(_xlpm.party, SUMIFS(ledger!J:J, ledger!B:B, _xlpm.party, ledger!E:E, "<>*RD*", ledger!D:D, "Black-chamki", ledger!C:C, "<>January Closing CF") ))} -> 0 | L64: {=_xlfn.BYROW(B64, _xlfn.LAMBDA(_xlpm.party, SUMIFS(ledger!J:J, ledger!B:B, _xlpm.party, ledger!E:E, "<>*RD*", ledger!D:D, "Kataan", ledger!C:C, "<>January Closing CF") ))} -> 0 | M64: {=_xlfn.BYROW(B64, _xlfn.LAMBDA(_xlpm.party, SUMIFS(ledger!J:J, ledger!B:B, _xlpm.party, ledger!E:E, "<>*RD*", ledger!D:D, "Munaar", ledger!C:C, "<>January Closing CF") ))} -> 0 | N64: {=_xlfn.BYROW(B64, _xlfn.LAMBDA(_xlpm.party, SUMIFS(ledger!J:J, ledger!B:B, _xlpm.party, ledger!E:E, "<>*RD*", ledger!D:D, "Custom", ledger!C:C, "<>January Closing CF") ))} -> 0 | O64: =SUM(G64:N64) -> 0 | P64: =(SUMIF(Table14[Party],B64,Table14[Credit])) -> 0 | Q64: =O64-P64 -> 0 | R64: 10 | S64: 12 | V64: Raaz Fabrics | W64: 23264.448 | X64: 232644.48
B65: Faizan | C65: 55739 | D65: 50968.361 | E65: 0 | F65: 50968.361 | G65: {=(_xlfn.BYROW(B65,_xlfn.LAMBDA(_xlpm.party, (SUMIFS(ledger!J:J,ledger!B:B,_xlpm.party,ledger!E:E,"<>*RD*",ledger!D:D,"Chamki",ledger!C:C,"<>January Closing CF")+ SUMIFS(ledger!J:J,ledger!B:B,_xlpm.party,ledger!E:E,"<>*RD*",ledger!D:D,"Crinkle",ledger!C:C,"<>January Closing CF") ))))} -> 0 | H65: {=_xlfn.BYROW(B65, _xlfn.LAMBDA(_xlpm.party, SUMIFS(ledger!J:J, ledger!B:B, _xlpm.party, ledger!E:E, "<>*RD*", ledger!D:D, "Silky", ledger!C:C, "<>January Closing CF") ))} -> 662588.7 | I65: {=_xlfn.BYROW(B65, _xlfn.LAMBDA(_xlpm.party, SUMIFS(ledger!J:J, ledger!B:B, _xlpm.party, ledger!E:E, "<>*RD*", ledger!D:D, "Slub", ledger!C:C, "<>January Closing CF") ))} -> 0 | J65: {=_xlfn.BYROW(B65, _xlfn.LAMBDA(_xlpm.party, SUMIFS(ledger!J:J, ledger!B:B, _xlpm.party, ledger!E:E, "<>*RD*", ledger!D:D, "Satin", ledger!C:C, "<>January Closing CF") ))} -> 0 | K65: {=_xlfn.BYROW(B65, _xlfn.LAMBDA(_xlpm.party, SUMIFS(ledger!J:J, ledger!B:B, _xlpm.party, ledger!E:E, "<>*RD*", ledger!D:D, "Black-chamki", ledger!C:C, "<>January Closing CF") ))} -> 0 | L65: {=_xlfn.BYROW(B65, _xlfn.LAMBDA(_xlpm.party, SUMIFS(ledger!J:J, ledger!B:B, _xlpm.party, ledger!E:E, "<>*RD*", ledger!D:D, "Kataan", ledger!C:C, "<>January Closing CF") ))} -> 0 | M65: {=_xlfn.BYROW(B65, _xlfn.LAMBDA(_xlpm.party, SUMIFS(ledger!J:J, ledger!B:B, _xlpm.party, ledger!E:E, "<>*RD*", ledger!D:D, "Munaar", ledger!C:C, "<>January Closing CF") ))} -> 0 | N65: {=_xlfn.BYROW(B65, _xlfn.LAMBDA(_xlpm.party, SUMIFS(ledger!J:J, ledger!B:B, _xlpm.party, ledger!E:E, "<>*RD*", ledger!D:D, "Custom", ledger!C:C, "<>January Closing CF") ))} -> 0 | O65: =SUM(G65:N65) -> 662588.7 | P65: =(SUMIF(Table14[Party],B65,Table14[Credit])) -> 704000 | Q65: =O65-P65 -> -41411.302 | R65: 10 | S65: 13 | V65: Azam | W65: 0 | X65: 0
B66: Shafique Ansari | C66: 0 | D66: 0 | E66: 0 | F66: 0 | G66: {=(_xlfn.BYROW(B66,_xlfn.LAMBDA(_xlpm.party, (SUMIFS(ledger!J:J,ledger!B:B,_xlpm.party,ledger!E:E,"<>*RD*",ledger!D:D,"Chamki",ledger!C:C,"<>January Closing CF")+ SUMIFS(ledger!J:J,ledger!B:B,_xlpm.party,ledger!E:E,"<>*RD*",ledger!D:D,"Crinkle",ledger!C:C,"<>January Closing CF") ))))} -> 0 | H66: {=_xlfn.BYROW(B66, _xlfn.LAMBDA(_xlpm.party, SUMIFS(ledger!J:J, ledger!B:B, _xlpm.party, ledger!E:E, "<>*RD*", ledger!D:D, "Silky", ledger!C:C, "<>January Closing CF") ))} -> 0 | I66: {=_xlfn.BYROW(B66, _xlfn.LAMBDA(_xlpm.party, SUMIFS(ledger!J:J, ledger!B:B, _xlpm.party, ledger!E:E, "<>*RD*", ledger!D:D, "Slub", ledger!C:C, "<>January Closing CF") ))} -> 0 | J66: {=_xlfn.BYROW(B66, _xlfn.LAMBDA(_xlpm.party, SUMIFS(ledger!J:J, ledger!B:B, _xlpm.party, ledger!E:E, "<>*RD*", ledger!D:D, "Satin", ledger!C:C, "<>January Closing CF") ))} -> 0 | K66: {=_xlfn.BYROW(B66, _xlfn.LAMBDA(_xlpm.party, SUMIFS(ledger!J:J, ledger!B:B, _xlpm.party, ledger!E:E, "<>*RD*", ledger!D:D, "Black-chamki", ledger!C:C, "<>January Closing CF") ))} -> 0 | L66: {=_xlfn.BYROW(B66, _xlfn.LAMBDA(_xlpm.party, SUMIFS(ledger!J:J, ledger!B:B, _xlpm.party, ledger!E:E, "<>*RD*", ledger!D:D, "Kataan", ledger!C:C, "<>January Closing CF") ))} -> 0 | M66: {=_xlfn.BYROW(B66, _xlfn.LAMBDA(_xlpm.party, SUMIFS(ledger!J:J, ledger!B:B, _xlpm.party, ledger!E:E, "<>*RD*", ledger!D:D, "Munaar", ledger!C:C, "<>January Closing CF") ))} -> 0 | N66: {=_xlfn.BYROW(B66, _xlfn.LAMBDA(_xlpm.party, SUMIFS(ledger!J:J, ledger!B:B, _xlpm.party, ledger!E:E, "<>*RD*", ledger!D:D, "Custom", ledger!C:C, "<>January Closing CF") ))} -> 0 | O66: =SUM(G66:N66) -> 0 | P66: =(SUMIF(Table14[Party],B66,Table14[Credit])) -> 0 | Q66: =O66-P66 -> 0 | R66: 10 | S66: 12 | V66: Ubaidullah | W66: 100178.31 | X66: 1202139.7
B67: Amjad sohail | C67: 55625 | D67: 50864.119 | E67: 2022.6774 | F67: 48841.441 | G67: {=(_xlfn.BYROW(B67,_xlfn.LAMBDA(_xlpm.party, (SUMIFS(ledger!J:J,ledger!B:B,_xlpm.party,ledger!E:E,"<>*RD*",ledger!D:D,"Chamki",ledger!C:C,"<>January Closing CF")+ SUMIFS(ledger!J:J,ledger!B:B,_xlpm.party,ledger!E:E,"<>*RD*",ledger!D:D,"Crinkle",ledger!C:C,"<>January Closing CF") ))))} -> 20226.774 | H67: {=_xlfn.BYROW(B67, _xlfn.LAMBDA(_xlpm.party, SUMIFS(ledger!J:J, ledger!B:B, _xlpm.party, ledger!E:E, "<>*RD*", ledger!D:D, "Silky", ledger!C:C, "<>January Closing CF") ))} -> 634938.73 | I67: {=_xlfn.BYROW(B67, _xlfn.LAMBDA(_xlpm.party, SUMIFS(ledger!J:J, ledger!B:B, _xlpm.party, ledger!E:E, "<>*RD*", ledger!D:D, "Slub", ledger!C:C, "<>January Closing CF") ))} -> 0 | J67: {=_xlfn.BYROW(B67, _xlfn.LAMBDA(_xlpm.party, SUMIFS(ledger!J:J, ledger!B:B, _xlpm.party, ledger!E:E, "<>*RD*", ledger!D:D, "Satin", ledger!C:C, "<>January Closing CF") ))} -> 0 | K67: {=_xlfn.BYROW(B67, _xlfn.LAMBDA(_xlpm.party, SUMIFS(ledger!J:J, ledger!B:B, _xlpm.party, ledger!E:E, "<>*RD*", ledger!D:D, "Black-chamki", ledger!C:C, "<>January Closing CF") ))} -> 0 | L67: {=_xlfn.BYROW(B67, _xlfn.LAMBDA(_xlpm.party, SUMIFS(ledger!J:J, ledger!B:B, _xlpm.party, ledger!E:E, "<>*RD*", ledger!D:D, "Kataan", ledger!C:C, "<>January Closing CF") ))} -> 0 | M67: {=_xlfn.BYROW(B67, _xlfn.LAMBDA(_xlpm.party, SUMIFS(ledger!J:J, ledger!B:B, _xlpm.party, ledger!E:E, "<>*RD*", ledger!D:D, "Munaar", ledger!C:C, "<>January Closing CF") ))} -> 0 | N67: {=_xlfn.BYROW(B67, _xlfn.LAMBDA(_xlpm.party, SUMIFS(ledger!J:J, ledger!B:B, _xlpm.party, ledger!E:E, "<>*RD*", ledger!D:D, "Custom", ledger!C:C, "<>January Closing CF") ))} -> 0 | O67: =SUM(G67:N67) -> 655165.51 | P67: =(SUMIF(Table14[Party],B67,Table14[Credit])) -> 0 | Q67: =O67-P67 -> 655165.51 | R67: 10 | S67: 12 | V67: Ashraf Zia | W67: 0 | X67: 0
B68: Salman Zaffar | C68: 0 | D68: 0 | E68: 0 | F68: 0 | G68: {=(_xlfn.BYROW(B68,_xlfn.LAMBDA(_xlpm.party, (SUMIFS(ledger!J:J,ledger!B:B,_xlpm.party,ledger!E:E,"<>*RD*",ledger!D:D,"Chamki",ledger!C:C,"<>January Closing CF")+ SUMIFS(ledger!J:J,ledger!B:B,_xlpm.party,ledger!E:E,"<>*RD*",ledger!D:D,"Crinkle",ledger!C:C,"<>January Closing CF") ))))} -> 0 | H68: {=_xlfn.BYROW(B68, _xlfn.LAMBDA(_xlpm.party, SUMIFS(ledger!J:J, ledger!B:B, _xlpm.party, ledger!E:E, "<>*RD*", ledger!D:D, "Silky", ledger!C:C, "<>January Closing CF") ))} -> 0 | I68: {=_xlfn.BYROW(B68, _xlfn.LAMBDA(_xlpm.party, SUMIFS(ledger!J:J, ledger!B:B, _xlpm.party, ledger!E:E, "<>*RD*", ledger!D:D, "Slub", ledger!C:C, "<>January Closing CF") ))} -> 0 | J68: {=_xlfn.BYROW(B68, _xlfn.LAMBDA(_xlpm.party, SUMIFS(ledger!J:J, ledger!B:B, _xlpm.party, ledger!E:E, "<>*RD*", ledger!D:D, "Satin", ledger!C:C, "<>January Closing CF") ))} -> 0 | K68: {=_xlfn.BYROW(B68, _xlfn.LAMBDA(_xlpm.party, SUMIFS(ledger!J:J, ledger!B:B, _xlpm.party, ledger!E:E, "<>*RD*", ledger!D:D, "Black-chamki", ledger!C:C, "<>January Closing CF") ))} -> 0 | L68: {=_xlfn.BYROW(B68, _xlfn.LAMBDA(_xlpm.party, SUMIFS(ledger!J:J, ledger!B:B, _xlpm.party, ledger!E:E, "<>*RD*", ledger!D:D, "Kataan", ledger!C:C, "<>January Closing CF") ))} -> 0 | M68: {=_xlfn.BYROW(B68, _xlfn.LAMBDA(_xlpm.party, SUMIFS(ledger!J:J, ledger!B:B, _xlpm.party, ledger!E:E, "<>*RD*", ledger!D:D, "Munaar", ledger!C:C, "<>January Closing CF") ))} -> 0 | N68: {=_xlfn.BYROW(B68, _xlfn.LAMBDA(_xlpm.party, SUMIFS(ledger!J:J, ledger!B:B, _xlpm.party, ledger!E:E, "<>*RD*", ledger!D:D, "Custom", ledger!C:C, "<>January Closing CF") ))} -> 0 | O68: =SUM(G68:N68) -> 0 | P68: =(SUMIF(Table14[Party],B68,Table14[Credit])) -> 0 | Q68: =O68-P68 -> 0 | R68: 10 | S68: 12 | V68: Hafiz Qureshi | W68: 215558.71 | X68: 1682095.8
B69: Shahid Qasayi | C69: 83675 | D69: 76513.35 | E69: 76513.35 | F69: 0 | G69: {=(_xlfn.BYROW(B69,_xlfn.LAMBDA(_xlpm.party, (SUMIFS(ledger!J:J,ledger!B:B,_xlpm.party,ledger!E:E,"<>*RD*",ledger!D:D,"Chamki",ledger!C:C,"<>January Closing CF")+ SUMIFS(ledger!J:J,ledger!B:B,_xlpm.party,ledger!E:E,"<>*RD*",ledger!D:D,"Crinkle",ledger!C:C,"<>January Closing CF") ))))} -> 765133.5 | H69: {=_xlfn.BYROW(B69, _xlfn.LAMBDA(_xlpm.party, SUMIFS(ledger!J:J, ledger!B:B, _xlpm.party, ledger!E:E, "<>*RD*", ledger!D:D, "Silky", ledger!C:C, "<>January Closing CF") ))} -> 0 | I69: {=_xlfn.BYROW(B69, _xlfn.LAMBDA(_xlpm.party, SUMIFS(ledger!J:J, ledger!B:B, _xlpm.party, ledger!E:E, "<>*RD*", ledger!D:D, "Slub", ledger!C:C, "<>January Closing CF") ))} -> 0 | J69: {=_xlfn.BYROW(B69, _xlfn.LAMBDA(_xlpm.party, SUMIFS(ledger!J:J, ledger!B:B, _xlpm.party, ledger!E:E, "<>*RD*", ledger!D:D, "Satin", ledger!C:C, "<>January Closing CF") ))} -> 0 | K69: {=_xlfn.BYROW(B69, _xlfn.LAMBDA(_xlpm.party, SUMIFS(ledger!J:J, ledger!B:B, _xlpm.party, ledger!E:E, "<>*RD*", ledger!D:D, "Black-chamki", ledger!C:C, "<>January Closing CF") ))} -> 0 | L69: {=_xlfn.BYROW(B69, _xlfn.LAMBDA(_xlpm.party, SUMIFS(ledger!J:J, ledger!B:B, _xlpm.party, ledger!E:E, "<>*RD*", ledger!D:D, "Kataan", ledger!C:C, "<>January Closing CF") ))} -> 0 | M69: {=_xlfn.BYROW(B69, _xlfn.LAMBDA(_xlpm.party, SUMIFS(ledger!J:J, ledger!B:B, _xlpm.party, ledger!E:E, "<>*RD*", ledger!D:D, "Munaar", ledger!C:C, "<>January Closing CF") ))} -> 0 | N69: {=_xlfn.BYROW(B69, _xlfn.LAMBDA(_xlpm.party, SUMIFS(ledger!J:J, ledger!B:B, _xlpm.party, ledger!E:E, "<>*RD*", ledger!D:D, "Custom", ledger!C:C, "<>January Closing CF") ))} -> 0 | O69: =SUM(G69:N69) -> 765133.5 | P69: =(SUMIF(Table14[Party],B69,Table14[Credit])) -> 220340 | Q69: =O69-P69 -> 544793.5 | R69: 10 | S69: 12 | V69: Badshah Fabrics | W69: 0 | X69: 0
B70: Hameed corporation | C70: 0 | D70: 0 | E70: 0 | F70: 0 | G70: {=(_xlfn.BYROW(B70,_xlfn.LAMBDA(_xlpm.party, (SUMIFS(ledger!J:J,ledger!B:B,_xlpm.party,ledger!E:E,"<>*RD*",ledger!D:D,"Chamki",ledger!C:C,"<>January Closing CF")+ SUMIFS(ledger!J:J,ledger!B:B,_xlpm.party,ledger!E:E,"<>*RD*",ledger!D:D,"Crinkle",ledger!C:C,"<>January Closing CF") ))))} -> 0 | H70: {=_xlfn.BYROW(B70, _xlfn.LAMBDA(_xlpm.party, SUMIFS(ledger!J:J, ledger!B:B, _xlpm.party, ledger!E:E, "<>*RD*", ledger!D:D, "Silky", ledger!C:C, "<>January Closing CF") ))} -> 0 | I70: {=_xlfn.BYROW(B70, _xlfn.LAMBDA(_xlpm.party, SUMIFS(ledger!J:J, ledger!B:B, _xlpm.party, ledger!E:E, "<>*RD*", ledger!D:D, "Slub", ledger!C:C, "<>January Closing CF") ))} -> 0 | J70: {=_xlfn.BYROW(B70, _xlfn.LAMBDA(_xlpm.party, SUMIFS(ledger!J:J, ledger!B:B, _xlpm.party, ledger!E:E, "<>*RD*", ledger!D:D, "Satin", ledger!C:C, "<>January Closing CF") ))} -> 0 | K70: {=_xlfn.BYROW(B70, _xlfn.LAMBDA(_xlpm.party, SUMIFS(ledger!J:J, ledger!B:B, _xlpm.party, ledger!E:E, "<>*RD*", ledger!D:D, "Black-chamki", ledger!C:C, "<>January Closing CF") ))} -> 0 | L70: {=_xlfn.BYROW(B70, _xlfn.LAMBDA(_xlpm.party, SUMIFS(ledger!J:J, ledger!B:B, _xlpm.party, ledger!E:E, "<>*RD*", ledger!D:D, "Kataan", ledger!C:C, "<>January Closing CF") ))} -> 0 | M70: {=_xlfn.BYROW(B70, _xlfn.LAMBDA(_xlpm.party, SUMIFS(ledger!J:J, ledger!B:B, _xlpm.party, ledger!E:E, "<>*RD*", ledger!D:D, "Munaar", ledger!C:C, "<>January Closing CF") ))} -> 0 | N70: {=_xlfn.BYROW(B70, _xlfn.LAMBDA(_xlpm.party, SUMIFS(ledger!J:J, ledger!B:B, _xlpm.party, ledger!E:E, "<>*RD*", ledger!D:D, "Custom", ledger!C:C, "<>January Closing CF") ))} -> 0 | O70: =SUM(G70:N70) -> 0 | P70: =(SUMIF(Table14[Party],B70,Table14[Credit])) -> 0 | Q70: =O70-P70 -> 0 | V70: Gauhar Kashif | W70: 0 | X70: 0
B71: ibraheem behraam | C71: 37934 | D71: 34687.271 | E71: 0 | F71: 34687.271 | G71: {=(_xlfn.BYROW(B71,_xlfn.LAMBDA(_xlpm.party, (SUMIFS(ledger!J:J,ledger!B:B,_xlpm.party,ledger!E:E,"<>*RD*",ledger!D:D,"Chamki",ledger!C:C,"<>January Closing CF")+ SUMIFS(ledger!J:J,ledger!B:B,_xlpm.party,ledger!E:E,"<>*RD*",ledger!D:D,"Crinkle",ledger!C:C,"<>January Closing CF") ))))} -> 0 | H71: {=_xlfn.BYROW(B71, _xlfn.LAMBDA(_xlpm.party, SUMIFS(ledger!J:J, ledger!B:B, _xlpm.party, ledger!E:E, "<>*RD*", ledger!D:D, "Silky", ledger!C:C, "<>January Closing CF") ))} -> 450934.53 | I71: {=_xlfn.BYROW(B71, _xlfn.LAMBDA(_xlpm.party, SUMIFS(ledger!J:J, ledger!B:B, _xlpm.party, ledger!E:E, "<>*RD*", ledger!D:D, "Slub", ledger!C:C, "<>January Closing CF") ))} -> 0 | J71: {=_xlfn.BYROW(B71, _xlfn.LAMBDA(_xlpm.party, SUMIFS(ledger!J:J, ledger!B:B, _xlpm.party, ledger!E:E, "<>*RD*", ledger!D:D, "Satin", ledger!C:C, "<>January Closing CF") ))} -> 0 | K71: {=_xlfn.BYROW(B71, _xlfn.LAMBDA(_xlpm.party, SUMIFS(ledger!J:J, ledger!B:B, _xlpm.party, ledger!E:E, "<>*RD*", ledger!D:D, "Black-chamki", ledger!C:C, "<>January Closing CF") ))} -> 0 | L71: {=_xlfn.BYROW(B71, _xlfn.LAMBDA(_xlpm.party, SUMIFS(ledger!J:J, ledger!B:B, _xlpm.party, ledger!E:E, "<>*RD*", ledger!D:D, "Kataan", ledger!C:C, "<>January Closing CF") ))} -> 0 | M71: {=_xlfn.BYROW(B71, _xlfn.LAMBDA(_xlpm.party, SUMIFS(ledger!J:J, ledger!B:B, _xlpm.party, ledger!E:E, "<>*RD*", ledger!D:D, "Munaar", ledger!C:C, "<>January Closing CF") ))} -> 0 | N71: {=_xlfn.BYROW(B71, _xlfn.LAMBDA(_xlpm.party, SUMIFS(ledger!J:J, ledger!B:B, _xlpm.party, ledger!E:E, "<>*RD*", ledger!D:D, "Custom", ledger!C:C, "<>January Closing CF") ))} -> 0 | O71: =SUM(G71:N71) -> 450934.53 | P71: =(SUMIF(Table14[Party],B71,Table14[Credit])) -> 308000 | Q71: =O71-P71 -> 142934.53 | V71: Amjad 7up | W71: 0 | X71: 0
B72: Zia-ullah karachi | C72: 0 | D72: 0 | E72: 0 | F72: 0 | G72: {=(_xlfn.BYROW(B72,_xlfn.LAMBDA(_xlpm.party, (SUMIFS(ledger!J:J,ledger!B:B,_xlpm.party,ledger!E:E,"<>*RD*",ledger!D:D,"Chamki",ledger!C:C,"<>January Closing CF")+ SUMIFS(ledger!J:J,ledger!B:B,_xlpm.party,ledger!E:E,"<>*RD*",ledger!D:D,"Crinkle",ledger!C:C,"<>January Closing CF") ))))} -> 0 | H72: {=_xlfn.BYROW(B72, _xlfn.LAMBDA(_xlpm.party, SUMIFS(ledger!J:J, ledger!B:B, _xlpm.party, ledger!E:E, "<>*RD*", ledger!D:D, "Silky", ledger!C:C, "<>January Closing CF") ))} -> 0 | I72: {=_xlfn.BYROW(B72, _xlfn.LAMBDA(_xlpm.party, SUMIFS(ledger!J:J, ledger!B:B, _xlpm.party, ledger!E:E, "<>*RD*", ledger!D:D, "Slub", ledger!C:C, "<>January Closing CF") ))} -> 0 | J72: {=_xlfn.BYROW(B72, _xlfn.LAMBDA(_xlpm.party, SUMIFS(ledger!J:J, ledger!B:B, _xlpm.party, ledger!E:E, "<>*RD*", ledger!D:D, "Satin", ledger!C:C, "<>January Closing CF") ))} -> 0 | K72: {=_xlfn.BYROW(B72, _xlfn.LAMBDA(_xlpm.party, SUMIFS(ledger!J:J, ledger!B:B, _xlpm.party, ledger!E:E, "<>*RD*", ledger!D:D, "Black-chamki", ledger!C:C, "<>January Closing CF") ))} -> 0 | L72: {=_xlfn.BYROW(B72, _xlfn.LAMBDA(_xlpm.party, SUMIFS(ledger!J:J, ledger!B:B, _xlpm.party, ledger!E:E, "<>*RD*", ledger!D:D, "Kataan", ledger!C:C, "<>January Closing CF") ))} -> 0 | M72: {=_xlfn.BYROW(B72, _xlfn.LAMBDA(_xlpm.party, SUMIFS(ledger!J:J, ledger!B:B, _xlpm.party, ledger!E:E, "<>*RD*", ledger!D:D, "Munaar", ledger!C:C, "<>January Closing CF") ))} -> 0 | N72: {=_xlfn.BYROW(B72, _xlfn.LAMBDA(_xlpm.party, SUMIFS(ledger!J:J, ledger!B:B, _xlpm.party, ledger!E:E, "<>*RD*", ledger!D:D, "Custom", ledger!C:C, "<>January Closing CF") ))} -> 0 | O72: =SUM(G72:N72) -> 0 | P72: =(SUMIF(Table14[Party],B72,Table14[Credit])) -> 0 | Q72: =O72-P72 -> 0 | V72: Hazrat Khan | W72: 0 | X72: 0
B73: ZA | C73: 0 | D73: 0 | E73: 0 | F73: 0 | G73: {=(_xlfn.BYROW(B73,_xlfn.LAMBDA(_xlpm.party, (SUMIFS(ledger!J:J,ledger!B:B,_xlpm.party,ledger!E:E,"<>*RD*",ledger!D:D,"Chamki",ledger!C:C,"<>January Closing CF")+ SUMIFS(ledger!J:J,ledger!B:B,_xlpm.party,ledger!E:E,"<>*RD*",ledger!D:D,"Crinkle",ledger!C:C,"<>January Closing CF") ))))} -> 0 | H73: {=_xlfn.BYROW(B73, _xlfn.LAMBDA(_xlpm.party, SUMIFS(ledger!J:J, ledger!B:B, _xlpm.party, ledger!E:E, "<>*RD*", ledger!D:D, "Silky", ledger!C:C, "<>January Closing CF") ))} -> 0 | I73: {=_xlfn.BYROW(B73, _xlfn.LAMBDA(_xlpm.party, SUMIFS(ledger!J:J, ledger!B:B, _xlpm.party, ledger!E:E, "<>*RD*", ledger!D:D, "Slub", ledger!C:C, "<>January Closing CF") ))} -> 0 | J73: {=_xlfn.BYROW(B73, _xlfn.LAMBDA(_xlpm.party, SUMIFS(ledger!J:J, ledger!B:B, _xlpm.party, ledger!E:E, "<>*RD*", ledger!D:D, "Satin", ledger!C:C, "<>January Closing CF") ))} -> 0 | K73: {=_xlfn.BYROW(B73, _xlfn.LAMBDA(_xlpm.party, SUMIFS(ledger!J:J, ledger!B:B, _xlpm.party, ledger!E:E, "<>*RD*", ledger!D:D, "Black-chamki", ledger!C:C, "<>January Closing CF") ))} -> 0 | L73: {=_xlfn.BYROW(B73, _xlfn.LAMBDA(_xlpm.party, SUMIFS(ledger!J:J, ledger!B:B, _xlpm.party, ledger!E:E, "<>*RD*", ledger!D:D, "Kataan", ledger!C:C, "<>January Closing CF") ))} -> 0 | M73: {=_xlfn.BYROW(B73, _xlfn.LAMBDA(_xlpm.party, SUMIFS(ledger!J:J, ledger!B:B, _xlpm.party, ledger!E:E, "<>*RD*", ledger!D:D, "Munaar", ledger!C:C, "<>January Closing CF") ))} -> 0 | N73: {=_xlfn.BYROW(B73, _xlfn.LAMBDA(_xlpm.party, SUMIFS(ledger!J:J, ledger!B:B, _xlpm.party, ledger!E:E, "<>*RD*", ledger!D:D, "Custom", ledger!C:C, "<>January Closing CF") ))} -> 0 | O73: =SUM(G73:N73) -> 0 | P73: =(SUMIF(Table14[Party],B73,Table14[Credit])) -> 135000 | Q73: =O73-P73 -> -135000 | V73: Haseeb Shamsi | W73: 0 | X73: 0
B74: Ahmad Javaid | C74: 0 | D74: 0 | E74: 0 | F74: 0 | G74: {=(_xlfn.BYROW(B74,_xlfn.LAMBDA(_xlpm.party, (SUMIFS(ledger!J:J,ledger!B:B,_xlpm.party,ledger!E:E,"<>*RD*",ledger!D:D,"Chamki",ledger!C:C,"<>January Closing CF")+ SUMIFS(ledger!J:J,ledger!B:B,_xlpm.party,ledger!E:E,"<>*RD*",ledger!D:D,"Crinkle",ledger!C:C,"<>January Closing CF") ))))} -> 0 | H74: {=_xlfn.BYROW(B74, _xlfn.LAMBDA(_xlpm.party, SUMIFS(ledger!J:J, ledger!B:B, _xlpm.party, ledger!E:E, "<>*RD*", ledger!D:D, "Silky", ledger!C:C, "<>January Closing CF") ))} -> 0 | I74: {=_xlfn.BYROW(B74, _xlfn.LAMBDA(_xlpm.party, SUMIFS(ledger!J:J, ledger!B:B, _xlpm.party, ledger!E:E, "<>*RD*", ledger!D:D, "Slub", ledger!C:C, "<>January Closing CF") ))} -> 0 | J74: {=_xlfn.BYROW(B74, _xlfn.LAMBDA(_xlpm.party, SUMIFS(ledger!J:J, ledger!B:B, _xlpm.party, ledger!E:E, "<>*RD*", ledger!D:D, "Satin", ledger!C:C, "<>January Closing CF") ))} -> 0 | K74: {=_xlfn.BYROW(B74, _xlfn.LAMBDA(_xlpm.party, SUMIFS(ledger!J:J, ledger!B:B, _xlpm.party, ledger!E:E, "<>*RD*", ledger!D:D, "Black-chamki", ledger!C:C, "<>January Closing CF") ))} -> 0 | L74: {=_xlfn.BYROW(B74, _xlfn.LAMBDA(_xlpm.party, SUMIFS(ledger!J:J, ledger!B:B, _xlpm.party, ledger!E:E, "<>*RD*", ledger!D:D, "Kataan", ledger!C:C, "<>January Closing CF") ))} -> 0 | M74: {=_xlfn.BYROW(B74, _xlfn.LAMBDA(_xlpm.party, SUMIFS(ledger!J:J, ledger!B:B, _xlpm.party, ledger!E:E, "<>*RD*", ledger!D:D, "Munaar", ledger!C:C, "<>January Closing CF") ))} -> 0 | N74: {=_xlfn.BYROW(B74, _xlfn.LAMBDA(_xlpm.party, SUMIFS(ledger!J:J, ledger!B:B, _xlpm.party, ledger!E:E, "<>*RD*", ledger!D:D, "Custom", ledger!C:C, "<>January Closing CF") ))} -> 0 | O74: =SUM(G74:N74) -> 0 | P74: =(SUMIF(Table14[Party],B74,Table14[Credit])) -> 130000 | Q74: =O74-P74 -> -130000 | V74: Faizan | W74: 50968.361 | X74: 611620.34
B75: Shani Badshah | C75: 112287 | D75: 102676.48 | E75: 102676.48 | F75: 0 | G75: {=(_xlfn.BYROW(B75,_xlfn.LAMBDA(_xlpm.party, (SUMIFS(ledger!J:J,ledger!B:B,_xlpm.party,ledger!E:E,"<>*RD*",ledger!D:D,"Chamki",ledger!C:C,"<>January Closing CF")+ SUMIFS(ledger!J:J,ledger!B:B,_xlpm.party,ledger!E:E,"<>*RD*",ledger!D:D,"Crinkle",ledger!C:C,"<>January Closing CF") ))))} -> 1026764.8 | H75: {=_xlfn.BYROW(B75, _xlfn.LAMBDA(_xlpm.party, SUMIFS(ledger!J:J, ledger!B:B, _xlpm.party, ledger!E:E, "<>*RD*", ledger!D:D, "Silky", ledger!C:C, "<>January Closing CF") ))} -> 0 | I75: {=_xlfn.BYROW(B75, _xlfn.LAMBDA(_xlpm.party, SUMIFS(ledger!J:J, ledger!B:B, _xlpm.party, ledger!E:E, "<>*RD*", ledger!D:D, "Slub", ledger!C:C, "<>January Closing CF") ))} -> 0 | J75: {=_xlfn.BYROW(B75, _xlfn.LAMBDA(_xlpm.party, SUMIFS(ledger!J:J, ledger!B:B, _xlpm.party, ledger!E:E, "<>*RD*", ledger!D:D, "Satin", ledger!C:C, "<>January Closing CF") ))} -> 0 | K75: {=_xlfn.BYROW(B75, _xlfn.LAMBDA(_xlpm.party, SUMIFS(ledger!J:J, ledger!B:B, _xlpm.party, ledger!E:E, "<>*RD*", ledger!D:D, "Black-chamki", ledger!C:C, "<>January Closing CF") ))} -> 0 | L75: {=_xlfn.BYROW(B75, _xlfn.LAMBDA(_xlpm.party, SUMIFS(ledger!J:J, ledger!B:B, _xlpm.party, ledger!E:E, "<>*RD*", ledger!D:D, "Kataan", ledger!C:C, "<>January Closing CF") ))} -> 0 | M75: {=_xlfn.BYROW(B75, _xlfn.LAMBDA(_xlpm.party, SUMIFS(ledger!J:J, ledger!B:B, _xlpm.party, ledger!E:E, "<>*RD*", ledger!D:D, "Munaar", ledger!C:C, "<>January Closing CF") ))} -> 0 | N75: {=_xlfn.BYROW(B75, _xlfn.LAMBDA(_xlpm.party, SUMIFS(ledger!J:J, ledger!B:B, _xlpm.party, ledger!E:E, "<>*RD*", ledger!D:D, "Custom", ledger!C:C, "<>January Closing CF") ))} -> 0 | O75: =SUM(G75:N75) -> 1026764.8 | P75: =(SUMIF(Table14[Party],B75,Table14[Credit])) -> 1816071 | Q75: =O75-P75 -> -789306.19 | V75: Grand Total | W75: 1482683.8 | X75: 12542579
B76: Rehman Ali | C76: 0 | D76: 0 | E76: 0 | F76: 0 | G76: {=(_xlfn.BYROW(B76,_xlfn.LAMBDA(_xlpm.party, (SUMIFS(ledger!J:J,ledger!B:B,_xlpm.party,ledger!E:E,"<>*RD*",ledger!D:D,"Chamki",ledger!C:C,"<>January Closing CF")+ SUMIFS(ledger!J:J,ledger!B:B,_xlpm.party,ledger!E:E,"<>*RD*",ledger!D:D,"Crinkle",ledger!C:C,"<>January Closing CF") ))))} -> 0 | H76: {=_xlfn.BYROW(B76, _xlfn.LAMBDA(_xlpm.party, SUMIFS(ledger!J:J, ledger!B:B, _xlpm.party, ledger!E:E, "<>*RD*", ledger!D:D, "Silky", ledger!C:C, "<>January Closing CF") ))} -> 0 | I76: {=_xlfn.BYROW(B76, _xlfn.LAMBDA(_xlpm.party, SUMIFS(ledger!J:J, ledger!B:B, _xlpm.party, ledger!E:E, "<>*RD*", ledger!D:D, "Slub", ledger!C:C, "<>January Closing CF") ))} -> 0 | J76: {=_xlfn.BYROW(B76, _xlfn.LAMBDA(_xlpm.party, SUMIFS(ledger!J:J, ledger!B:B, _xlpm.party, ledger!E:E, "<>*RD*", ledger!D:D, "Satin", ledger!C:C, "<>January Closing CF") ))} -> 0 | K76: {=_xlfn.BYROW(B76, _xlfn.LAMBDA(_xlpm.party, SUMIFS(ledger!J:J, ledger!B:B, _xlpm.party, ledger!E:E, "<>*RD*", ledger!D:D, "Black-chamki", ledger!C:C, "<>January Closing CF") ))} -> 0 | L76: {=_xlfn.BYROW(B76, _xlfn.LAMBDA(_xlpm.party, SUMIFS(ledger!J:J, ledger!B:B, _xlpm.party, ledger!E:E, "<>*RD*", ledger!D:D, "Kataan", ledger!C:C, "<>January Closing CF") ))} -> 0 | M76: {=_xlfn.BYROW(B76, _xlfn.LAMBDA(_xlpm.party, SUMIFS(ledger!J:J, ledger!B:B, _xlpm.party, ledger!E:E, "<>*RD*", ledger!D:D, "Munaar", ledger!C:C, "<>January Closing CF") ))} -> 0 | N76: {=_xlfn.BYROW(B76, _xlfn.LAMBDA(_xlpm.party, SUMIFS(ledger!J:J, ledger!B:B, _xlpm.party, ledger!E:E, "<>*RD*", ledger!D:D, "Custom", ledger!C:C, "<>January Closing CF") ))} -> 0 | O76: =SUM(G76:N76) -> 0 | P76: =SUMIF(Table14[Party], B76, Table14[Credit]) -> 0 | Q76: =O76-P76 -> 0
B77: Ahmad Shafique | C77: 0 | D77: 0 | E77: 0 | F77: 0 | G77: {=(_xlfn.BYROW(B77,_xlfn.LAMBDA(_xlpm.party, (SUMIFS(ledger!J:J,ledger!B:B,_xlpm.party,ledger!E:E,"<>*RD*",ledger!D:D,"Chamki",ledger!C:C,"<>January Closing CF")+ SUMIFS(ledger!J:J,ledger!B:B,_xlpm.party,ledger!E:E,"<>*RD*",ledger!D:D,"Crinkle",ledger!C:C,"<>January Closing CF") ))))} -> 0 | H77: {=_xlfn.BYROW(B77, _xlfn.LAMBDA(_xlpm.party, SUMIFS(ledger!J:J, ledger!B:B, _xlpm.party, ledger!E:E, "<>*RD*", ledger!D:D, "Silky", ledger!C:C, "<>January Closing CF") ))} -> 0 | I77: {=_xlfn.BYROW(B77, _xlfn.LAMBDA(_xlpm.party, SUMIFS(ledger!J:J, ledger!B:B, _xlpm.party, ledger!E:E, "<>*RD*", ledger!D:D, "Slub", ledger!C:C, "<>January Closing CF") ))} -> 0 | J77: {=_xlfn.BYROW(B77, _xlfn.LAMBDA(_xlpm.party, SUMIFS(ledger!J:J, ledger!B:B, _xlpm.party, ledger!E:E, "<>*RD*", ledger!D:D, "Satin", ledger!C:C, "<>January Closing CF") ))} -> 0 | K77: {=_xlfn.BYROW(B77, _xlfn.LAMBDA(_xlpm.party, SUMIFS(ledger!J:J, ledger!B:B, _xlpm.party, ledger!E:E, "<>*RD*", ledger!D:D, "Black-chamki", ledger!C:C, "<>January Closing CF") ))} -> 0 | L77: {=_xlfn.BYROW(B77, _xlfn.LAMBDA(_xlpm.party, SUMIFS(ledger!J:J, ledger!B:B, _xlpm.party, ledger!E:E, "<>*RD*", ledger!D:D, "Kataan", ledger!C:C, "<>January Closing CF") ))} -> 0 | M77: {=_xlfn.BYROW(B77, _xlfn.LAMBDA(_xlpm.party, SUMIFS(ledger!J:J, ledger!B:B, _xlpm.party, ledger!E:E, "<>*RD*", ledger!D:D, "Munaar", ledger!C:C, "<>January Closing CF") ))} -> 0 | N77: {=_xlfn.BYROW(B77, _xlfn.LAMBDA(_xlpm.party, SUMIFS(ledger!J:J, ledger!B:B, _xlpm.party, ledger!E:E, "<>*RD*", ledger!D:D, "Custom", ledger!C:C, "<>January Closing CF") ))} -> 0 | O77: =SUM(G77:N77) -> 0 | P77: =SUMIF(Table14[Party], B77, Table14[Credit]) -> 0 | Q77: =O77-P77 -> 0
B78: Hafiz Shawl | C78: 31950 | D78: 29215.435 | E78: 0 | F78: 0 | G78: {=(_xlfn.BYROW(B78,_xlfn.LAMBDA(_xlpm.party, (SUMIFS(ledger!J:J,ledger!B:B,_xlpm.party,ledger!E:E,"<>*RD*",ledger!D:D,"Chamki",ledger!C:C,"<>January Closing CF")+ SUMIFS(ledger!J:J,ledger!B:B,_xlpm.party,ledger!E:E,"<>*RD*",ledger!D:D,"Crinkle",ledger!C:C,"<>January Closing CF") ))))} -> 0 | H78: {=_xlfn.BYROW(B78, _xlfn.LAMBDA(_xlpm.party, SUMIFS(ledger!J:J, ledger!B:B, _xlpm.party, ledger!E:E, "<>*RD*", ledger!D:D, "Silky", ledger!C:C, "<>January Closing CF") ))} -> 0 | I78: {=_xlfn.BYROW(B78, _xlfn.LAMBDA(_xlpm.party, SUMIFS(ledger!J:J, ledger!B:B, _xlpm.party, ledger!E:E, "<>*RD*", ledger!D:D, "Slub", ledger!C:C, "<>January Closing CF") ))} -> 0 | J78: {=_xlfn.BYROW(B78, _xlfn.LAMBDA(_xlpm.party, SUMIFS(ledger!J:J, ledger!B:B, _xlpm.party, ledger!E:E, "<>*RD*", ledger!D:D, "Satin", ledger!C:C, "<>January Closing CF") ))} -> 0 | K78: {=_xlfn.BYROW(B78, _xlfn.LAMBDA(_xlpm.party, SUMIFS(ledger!J:J, ledger!B:B, _xlpm.party, ledger!E:E, "<>*RD*", ledger!D:D, "Black-chamki", ledger!C:C, "<>January Closing CF") ))} -> 0 | L78: {=_xlfn.BYROW(B78, _xlfn.LAMBDA(_xlpm.party, SUMIFS(ledger!J:J, ledger!B:B, _xlpm.party, ledger!E:E, "<>*RD*", ledger!D:D, "Kataan", ledger!C:C, "<>January Closing CF") ))} -> 0 | M78: {=_xlfn.BYROW(B78, _xlfn.LAMBDA(_xlpm.party, SUMIFS(ledger!J:J, ledger!B:B, _xlpm.party, ledger!E:E, "<>*RD*", ledger!D:D, "Munaar", ledger!C:C, "<>January Closing CF") ))} -> 0 | N78: {=_xlfn.BYROW(B78, _xlfn.LAMBDA(_xlpm.party, SUMIFS(ledger!J:J, ledger!B:B, _xlpm.party, ledger!E:E, "<>*RD*", ledger!D:D, "Custom", ledger!C:C, "<>January Closing CF") ))} -> 584043.53 | O78: =SUM(G78:N78) -> 584043.53 | P78: =SUMIF(Table14[Party], B78, Table14[Credit]) -> 40000 | Q78: =O78-P78 -> 544043.53
B79: Zahid Ejaz | C79: 16060 | D79: 14685.443 | E79: 14685.443 | F79: 0 | G79: {=(_xlfn.BYROW(B79,_xlfn.LAMBDA(_xlpm.party, (SUMIFS(ledger!J:J,ledger!B:B,_xlpm.party,ledger!E:E,"<>*RD*",ledger!D:D,"Chamki",ledger!C:C,"<>January Closing CF")+ SUMIFS(ledger!J:J,ledger!B:B,_xlpm.party,ledger!E:E,"<>*RD*",ledger!D:D,"Crinkle",ledger!C:C,"<>January Closing CF") ))))} -> 161539.87 | H79: {=_xlfn.BYROW(B79, _xlfn.LAMBDA(_xlpm.party, SUMIFS(ledger!J:J, ledger!B:B, _xlpm.party, ledger!E:E, "<>*RD*", ledger!D:D, "Silky", ledger!C:C, "<>January Closing CF") ))} -> 0 | I79: {=_xlfn.BYROW(B79, _xlfn.LAMBDA(_xlpm.party, SUMIFS(ledger!J:J, ledger!B:B, _xlpm.party, ledger!E:E, "<>*RD*", ledger!D:D, "Slub", ledger!C:C, "<>January Closing CF") ))} -> 0 | J79: {=_xlfn.BYROW(B79, _xlfn.LAMBDA(_xlpm.party, SUMIFS(ledger!J:J, ledger!B:B, _xlpm.party, ledger!E:E, "<>*RD*", ledger!D:D, "Satin", ledger!C:C, "<>January Closing CF") ))} -> 0 | K79: {=_xlfn.BYROW(B79, _xlfn.LAMBDA(_xlpm.party, SUMIFS(ledger!J:J, ledger!B:B, _xlpm.party, ledger!E:E, "<>*RD*", ledger!D:D, "Black-chamki", ledger!C:C, "<>January Closing CF") ))} -> 0 | L79: {=_xlfn.BYROW(B79, _xlfn.LAMBDA(_xlpm.party, SUMIFS(ledger!J:J, ledger!B:B, _xlpm.party, ledger!E:E, "<>*RD*", ledger!D:D, "Kataan", ledger!C:C, "<>January Closing CF") ))} -> 0 | M79: {=_xlfn.BYROW(B79, _xlfn.LAMBDA(_xlpm.party, SUMIFS(ledger!J:J, ledger!B:B, _xlpm.party, ledger!E:E, "<>*RD*", ledger!D:D, "Munaar", ledger!C:C, "<>January Closing CF") ))} -> 0 | N79: {=_xlfn.BYROW(B79, _xlfn.LAMBDA(_xlpm.party, SUMIFS(ledger!J:J, ledger!B:B, _xlpm.party, ledger!E:E, "<>*RD*", ledger!D:D, "Custom", ledger!C:C, "<>January Closing CF") ))} -> 0 | O79: =SUM(G79:N79) -> 161539.87 | P79: =SUMIF(Table14[Party], B79, Table14[Credit]) -> 169278 | Q79: =O79-P79 -> -7738.1317
B80: Faizan Kamoki | C80: 490216 | D80: 448258.96 | E80: 0 | F80: 306760.24 | G80: {=(_xlfn.BYROW(B80,_xlfn.LAMBDA(_xlpm.party, (SUMIFS(ledger!J:J,ledger!B:B,_xlpm.party,ledger!E:E,"<>*RD*",ledger!D:D,"Chamki",ledger!C:C,"<>January Closing CF")+ SUMIFS(ledger!J:J,ledger!B:B,_xlpm.party,ledger!E:E,"<>*RD*",ledger!D:D,"Crinkle",ledger!C:C,"<>January Closing CF") ))))} -> 0 | H80: {=_xlfn.BYROW(B80, _xlfn.LAMBDA(_xlpm.party, SUMIFS(ledger!J:J, ledger!B:B, _xlpm.party, ledger!E:E, "<>*RD*", ledger!D:D, "Silky", ledger!C:C, "<>January Closing CF") ))} -> 3987883.1 | I80: {=_xlfn.BYROW(B80, _xlfn.LAMBDA(_xlpm.party, SUMIFS(ledger!J:J, ledger!B:B, _xlpm.party, ledger!E:E, "<>*RD*", ledger!D:D, "Slub", ledger!C:C, "<>January Closing CF") ))} -> 0 | J80: {=_xlfn.BYROW(B80, _xlfn.LAMBDA(_xlpm.party, SUMIFS(ledger!J:J, ledger!B:B, _xlpm.party, ledger!E:E, "<>*RD*", ledger!D:D, "Satin", ledger!C:C, "<>January Closing CF") ))} -> 0 | K80: {=_xlfn.BYROW(B80, _xlfn.LAMBDA(_xlpm.party, SUMIFS(ledger!J:J, ledger!B:B, _xlpm.party, ledger!E:E, "<>*RD*", ledger!D:D, "Black-chamki", ledger!C:C, "<>January Closing CF") ))} -> 0 | L80: {=_xlfn.BYROW(B80, _xlfn.LAMBDA(_xlpm.party, SUMIFS(ledger!J:J, ledger!B:B, _xlpm.party, ledger!E:E, "<>*RD*", ledger!D:D, "Kataan", ledger!C:C, "<>January Closing CF") ))} -> 1638023 | M80: {=_xlfn.BYROW(B80, _xlfn.LAMBDA(_xlpm.party, SUMIFS(ledger!J:J, ledger!B:B, _xlpm.party, ledger!E:E, "<>*RD*", ledger!D:D, "Munaar", ledger!C:C, "<>January Closing CF") ))} -> 0 | N80: {=_xlfn.BYROW(B80, _xlfn.LAMBDA(_xlpm.party, SUMIFS(ledger!J:J, ledger!B:B, _xlpm.party, ledger!E:E, "<>*RD*", ledger!D:D, "Custom", ledger!C:C, "<>January Closing CF") ))} -> 0 | O80: =SUM(G80:N80) -> 5625906.2 | P80: =SUMIF(Table14[Party], B80, Table14[Credit]) -> 5245323.5 | Q80: =O80-P80 -> 380582.69
B81: KK fabrics | C81: 59639 | D81: 54534.565 | E81: 54534.565 | F81: 0 | G81: {=(_xlfn.BYROW(B81,_xlfn.LAMBDA(_xlpm.party, (SUMIFS(ledger!J:J,ledger!B:B,_xlpm.party,ledger!E:E,"<>*RD*",ledger!D:D,"Chamki",ledger!C:C,"<>January Closing CF")+ SUMIFS(ledger!J:J,ledger!B:B,_xlpm.party,ledger!E:E,"<>*RD*",ledger!D:D,"Crinkle",ledger!C:C,"<>January Closing CF") ))))} -> 545345.65 | H81: {=_xlfn.BYROW(B81, _xlfn.LAMBDA(_xlpm.party, SUMIFS(ledger!J:J, ledger!B:B, _xlpm.party, ledger!E:E, "<>*RD*", ledger!D:D, "Silky", ledger!C:C, "<>January Closing CF") ))} -> 0 | I81: {=_xlfn.BYROW(B81, _xlfn.LAMBDA(_xlpm.party, SUMIFS(ledger!J:J, ledger!B:B, _xlpm.party, ledger!E:E, "<>*RD*", ledger!D:D, "Slub", ledger!C:C, "<>January Closing CF") ))} -> 0 | J81: {=_xlfn.BYROW(B81, _xlfn.LAMBDA(_xlpm.party, SUMIFS(ledger!J:J, ledger!B:B, _xlpm.party, ledger!E:E, "<>*RD*", ledger!D:D, "Satin", ledger!C:C, "<>January Closing CF") ))} -> 0 | K81: {=_xlfn.BYROW(B81, _xlfn.LAMBDA(_xlpm.party, SUMIFS(ledger!J:J, ledger!B:B, _xlpm.party, ledger!E:E, "<>*RD*", ledger!D:D, "Black-chamki", ledger!C:C, "<>January Closing CF") ))} -> 0 | L81: {=_xlfn.BYROW(B81, _xlfn.LAMBDA(_xlpm.party, SUMIFS(ledger!J:J, ledger!B:B, _xlpm.party, ledger!E:E, "<>*RD*", ledger!D:D, "Kataan", ledger!C:C, "<>January Closing CF") ))} -> 0 | M81: {=_xlfn.BYROW(B81, _xlfn.LAMBDA(_xlpm.party, SUMIFS(ledger!J:J, ledger!B:B, _xlpm.party, ledger!E:E, "<>*RD*", ledger!D:D, "Munaar", ledger!C:C, "<>January Closing CF") ))} -> 0 | N81: {=_xlfn.BYROW(B81, _xlfn.LAMBDA(_xlpm.party, SUMIFS(ledger!J:J, ledger!B:B, _xlpm.party, ledger!E:E, "<>*RD*", ledger!D:D, "Custom", ledger!C:C, "<>January Closing CF") ))} -> 0 | O81: =SUM(G81:N81) -> 545345.65 | P81: =SUMIF(Table14[Party], B81, Table14[Credit]) -> 544000 | Q81: =O81-P81 -> 1345.6474
A82: Billing (Previous) | B82: Rauf Khan | C82: 110981 | D82: 101482.26 | E82: 81045.172 | F82: 0 | G82: {=(_xlfn.BYROW(B82,_xlfn.LAMBDA(_xlpm.party, (SUMIFS(ledger!J:J,ledger!B:B,_xlpm.party,ledger!E:E,"<>*RD*",ledger!D:D,"Chamki",ledger!C:C,"<>January Closing CF")+ SUMIFS(ledger!J:J,ledger!B:B,_xlpm.party,ledger!E:E,"<>*RD*",ledger!D:D,"Crinkle",ledger!C:C,"<>January Closing CF") ))))} -> 810451.72 | H82: {=_xlfn.BYROW(B82, _xlfn.LAMBDA(_xlpm.party, SUMIFS(ledger!J:J, ledger!B:B, _xlpm.party, ledger!E:E, "<>*RD*", ledger!D:D, "Silky", ledger!C:C, "<>January Closing CF") ))} -> 0 | I82: {=_xlfn.BYROW(B82, _xlfn.LAMBDA(_xlpm.party, SUMIFS(ledger!J:J, ledger!B:B, _xlpm.party, ledger!E:E, "<>*RD*", ledger!D:D, "Slub", ledger!C:C, "<>January Closing CF") ))} -> 0 | J82: {=_xlfn.BYROW(B82, _xlfn.LAMBDA(_xlpm.party, SUMIFS(ledger!J:J, ledger!B:B, _xlpm.party, ledger!E:E, "<>*RD*", ledger!D:D, "Satin", ledger!C:C, "<>January Closing CF") ))} -> 306556.33 | K82: {=_xlfn.BYROW(B82, _xlfn.LAMBDA(_xlpm.party, SUMIFS(ledger!J:J, ledger!B:B, _xlpm.party, ledger!E:E, "<>*RD*", ledger!D:D, "Black-chamki", ledger!C:C, "<>January Closing CF") ))} -> 0 | L82: {=_xlfn.BYROW(B82, _xlfn.LAMBDA(_xlpm.party, SUMIFS(ledger!J:J, ledger!B:B, _xlpm.party, ledger!E:E, "<>*RD*", ledger!D:D, "Kataan", ledger!C:C, "<>January Closing CF") ))} -> 0 | M82: {=_xlfn.BYROW(B82, _xlfn.LAMBDA(_xlpm.party, SUMIFS(ledger!J:J, ledger!B:B, _xlpm.party, ledger!E:E, "<>*RD*", ledger!D:D, "Munaar", ledger!C:C, "<>January Closing CF") ))} -> 0 | N82: {=_xlfn.BYROW(B82, _xlfn.LAMBDA(_xlpm.party, SUMIFS(ledger!J:J, ledger!B:B, _xlpm.party, ledger!E:E, "<>*RD*", ledger!D:D, "Custom", ledger!C:C, "<>January Closing CF") ))} -> 0 | O82: =SUM(G82:N82) -> 1117008 | P82: =SUMIF(Table14[Party], B82, Table14[Credit]) -> 0 | Q82: =O82-P82 -> 1117008
B83: Farhaan ali | C83: 163883 | D83: 149856.44 | E83: 0 | F83: 149856.44 | G83: {=(_xlfn.BYROW(B83,_xlfn.LAMBDA(_xlpm.party, (SUMIFS(ledger!J:J,ledger!B:B,_xlpm.party,ledger!E:E,"<>*RD*",ledger!D:D,"Chamki",ledger!C:C,"<>January Closing CF")+ SUMIFS(ledger!J:J,ledger!B:B,_xlpm.party,ledger!E:E,"<>*RD*",ledger!D:D,"Crinkle",ledger!C:C,"<>January Closing CF") ))))} -> 0 | H83: {=_xlfn.BYROW(B83, _xlfn.LAMBDA(_xlpm.party, SUMIFS(ledger!J:J, ledger!B:B, _xlpm.party, ledger!E:E, "<>*RD*", ledger!D:D, "Silky", ledger!C:C, "<>January Closing CF") ))} -> 1798277.2 | I83: {=_xlfn.BYROW(B83, _xlfn.LAMBDA(_xlpm.party, SUMIFS(ledger!J:J, ledger!B:B, _xlpm.party, ledger!E:E, "<>*RD*", ledger!D:D, "Slub", ledger!C:C, "<>January Closing CF") ))} -> 0 | J83: {=_xlfn.BYROW(B83, _xlfn.LAMBDA(_xlpm.party, SUMIFS(ledger!J:J, ledger!B:B, _xlpm.party, ledger!E:E, "<>*RD*", ledger!D:D, "Satin", ledger!C:C, "<>January Closing CF") ))} -> 0 | K83: {=_xlfn.BYROW(B83, _xlfn.LAMBDA(_xlpm.party, SUMIFS(ledger!J:J, ledger!B:B, _xlpm.party, ledger!E:E, "<>*RD*", ledger!D:D, "Black-chamki", ledger!C:C, "<>January Closing CF") ))} -> 0 | L83: {=_xlfn.BYROW(B83, _xlfn.LAMBDA(_xlpm.party, SUMIFS(ledger!J:J, ledger!B:B, _xlpm.party, ledger!E:E, "<>*RD*", ledger!D:D, "Kataan", ledger!C:C, "<>January Closing CF") ))} -> 0 | M83: {=_xlfn.BYROW(B83, _xlfn.LAMBDA(_xlpm.party, SUMIFS(ledger!J:J, ledger!B:B, _xlpm.party, ledger!E:E, "<>*RD*", ledger!D:D, "Munaar", ledger!C:C, "<>January Closing CF") ))} -> 0 | N83: {=_xlfn.BYROW(B83, _xlfn.LAMBDA(_xlpm.party, SUMIFS(ledger!J:J, ledger!B:B, _xlpm.party, ledger!E:E, "<>*RD*", ledger!D:D, "Custom", ledger!C:C, "<>January Closing CF") ))} -> 0 | O83: =SUM(G83:N83) -> 1798277.2 | P83: =SUMIF(Table14[Party], B83, Table14[Credit]) -> 0 | Q83: =O83-P83 -> 1798277.2
B84: 0 | C84: 0 | D84: 0 | E84: 0 | F84: 0
B97: Parties: | C97: Gaz | D97: Total Metres | E97: Total Chamki | F97: Total Super Silky | G97: Billing (Chamki/Crinkle) | H97: Billing (Super Chamki) | I97: billing (Slub) | J97: Billing (Satin) | K97: Billing (Black-Chamki) | L97: Billing (kataan | M97: Billing (Munaar) | N97: Billing Custom | O97: Adjusted Bill | P97: Amount Paid | Q97: Balance | R97: Rate (Chamki) | S97: Rate (Super Silky)
B98: {=_xlfn.UNIQUE(Table1[Party Name])} -> BSC | C98: =_xlfn.XLOOKUP($B49,[1]Billing!$Q$5:$Q$40,[1]Billing!$R$5:$R$40) -> 3652766.9 | D98: =_xlfn.XLOOKUP($B49,[1]Billing!$Q$5:$Q$40,[1]Billing!$S$5:$S$40) -> 3340130.7 | E98: =_xlfn.XLOOKUP($B49,[1]Billing!$Q$5:$Q$40,[1]Billing!$T$5:$T$40) -> 2767584 | F98: =_xlfn.XLOOKUP($B49,[1]Billing!$Q$5:$Q$40,[1]Billing!$U$5:$U$40) -> 561031.46 | G98: =_xlfn.XLOOKUP($B49,[1]Billing!$Q$5:$Q$40,[1]Billing!$V$5:$V$40) -> 27675840 | H98: =_xlfn.XLOOKUP($B49,[1]Billing!$Q$5:$Q$40,[1]Billing!$W$5:$W$40) -> 7205053 | I98: =_xlfn.XLOOKUP($B49,[1]Billing!$Q$5:$Q$40,[1]Billing!$X$5:$X$40) -> 0 | J98: =_xlfn.XLOOKUP($B49,[1]Billing!$Q$5:$Q$40,[1]Billing!$Y$5:$Y$40) -> 0 | K98: =_xlfn.XLOOKUP($B49,[1]Billing!$Q$5:$Q$40,[1]Billing!$Z$5:$Z$40) -> 0 | L98: =_xlfn.XLOOKUP($B49,[1]Billing!$Q$5:$Q$40,[1]Billing!$AA$5:$AA$40) -> 126666.97 | M98: =_xlfn.XLOOKUP($B49,[1]Billing!$Q$5:$Q$40,[1]Billing!$AB$5:$AB$40) -> 0 | O98: =G98+H98+I98+J98+K98+L98+M98 -> 35007560 | P98: =_xlfn.XLOOKUP($B49,[1]Billing!$Q$5:$Q$40,[1]Billing!$AD$5:$AD$40) -> 19750734 | Q98: =O98-P98 -> 15256826 | R98: 10 | S98: 13
B99: Ejaz Sahab | C99: =_xlfn.XLOOKUP($B50,[1]Billing!$Q$5:$Q$40,[1]Billing!$R$5:$R$40) -> 580479 | D99: =_xlfn.XLOOKUP($B50,[1]Billing!$Q$5:$Q$40,[1]Billing!$S$5:$S$40) -> 530796.45 | E99: =_xlfn.XLOOKUP($B50,[1]Billing!$Q$5:$Q$40,[1]Billing!$T$5:$T$40) -> 148145.57 | F99: =_xlfn.XLOOKUP($B50,[1]Billing!$Q$5:$Q$40,[1]Billing!$U$5:$U$40) -> 382650.88 | G99: =_xlfn.XLOOKUP($B50,[1]Billing!$Q$5:$Q$40,[1]Billing!$V$5:$V$40) -> 1481455.7 | H99: =_xlfn.XLOOKUP($B50,[1]Billing!$Q$5:$Q$40,[1]Billing!$W$5:$W$40) -> 4915317.3 | I99: =_xlfn.XLOOKUP($B50,[1]Billing!$Q$5:$Q$40,[1]Billing!$X$5:$X$40) -> 0 | J99: =_xlfn.XLOOKUP($B50,[1]Billing!$Q$5:$Q$40,[1]Billing!$Y$5:$Y$40) -> 0 | K99: =_xlfn.XLOOKUP($B50,[1]Billing!$Q$5:$Q$40,[1]Billing!$Z$5:$Z$40) -> 0 | L99: =_xlfn.XLOOKUP($B50,[1]Billing!$Q$5:$Q$40,[1]Billing!$AA$5:$AA$40) -> 0 | M99: =_xlfn.XLOOKUP($B50,[1]Billing!$Q$5:$Q$40,[1]Billing!$AB$5:$AB$40) -> 0 | O99: =G99+H99+I99+J99+K99+L99+M99 -> 6396773 | P99: =_xlfn.XLOOKUP($B50,[1]Billing!$Q$5:$Q$40,[1]Billing!$AD$5:$AD$40) -> 6067319 | Q99: =O99-P99 -> 329454.04 | R99: 10 | S99: 13
B100: Arshad | C100: =_xlfn.XLOOKUP($B51,[1]Billing!$Q$5:$Q$40,[1]Billing!$R$5:$R$40) -> 894593 | D100: =_xlfn.XLOOKUP($B51,[1]Billing!$Q$5:$Q$40,[1]Billing!$S$5:$S$40) -> 818025.79 | E100: =_xlfn.XLOOKUP($B51,[1]Billing!$Q$5:$Q$40,[1]Billing!$T$5:$T$40) -> 671848.94 | F100: =_xlfn.XLOOKUP($B51,[1]Billing!$Q$5:$Q$40,[1]Billing!$U$5:$U$40) -> 146176.85 | G100: =_xlfn.XLOOKUP($B51,[1]Billing!$Q$5:$Q$40,[1]Billing!$V$5:$V$40) -> 6718489.4 | H100: =_xlfn.XLOOKUP($B51,[1]Billing!$Q$5:$Q$40,[1]Billing!$W$5:$W$40) -> 1885504.8 | I100: =_xlfn.XLOOKUP($B51,[1]Billing!$Q$5:$Q$40,[1]Billing!$X$5:$X$40) -> 0 | J100: =_xlfn.XLOOKUP($B51,[1]Billing!$Q$5:$Q$40,[1]Billing!$Y$5:$Y$40) -> 0 | K100: =_xlfn.XLOOKUP($B51,[1]Billing!$Q$5:$Q$40,[1]Billing!$Z$5:$Z$40) -> 0 | L100: =_xlfn.XLOOKUP($B51,[1]Billing!$Q$5:$Q$40,[1]Billing!$AA$5:$AA$40) -> 0 | M100: =_xlfn.XLOOKUP($B51,[1]Billing!$Q$5:$Q$40,[1]Billing!$AB$5:$AB$40) -> 0 | O100: =G100+H100+I100+J100+K100+L100+M100 -> 8603994.1 | P100: =_xlfn.XLOOKUP($B51,[1]Billing!$Q$5:$Q$40,[1]Billing!$AD$5:$AD$40) -> 8492501 | Q100: =O100-P100 -> 111493.15 | R100: 10 | S100: 13
B101: Shehzad Kamoki | C101: =_xlfn.XLOOKUP($B52,[1]Billing!$Q$5:$Q$40,[1]Billing!$R$5:$R$40) -> 143457 | D101: =_xlfn.XLOOKUP($B52,[1]Billing!$Q$5:$Q$40,[1]Billing!$S$5:$S$40) -> 131178.68 | E101: =_xlfn.XLOOKUP($B52,[1]Billing!$Q$5:$Q$40,[1]Billing!$T$5:$T$40) -> 131178.68 | F101: =_xlfn.XLOOKUP($B52,[1]Billing!$Q$5:$Q$40,[1]Billing!$U$5:$U$40) -> 0 | G101: =_xlfn.XLOOKUP($B52,[1]Billing!$Q$5:$Q$40,[1]Billing!$V$5:$V$40) -> 1354242 | H101: =_xlfn.XLOOKUP($B52,[1]Billing!$Q$5:$Q$40,[1]Billing!$W$5:$W$40) -> 0 | I101: =_xlfn.XLOOKUP($B52,[1]Billing!$Q$5:$Q$40,[1]Billing!$X$5:$X$40) -> 0 | J101: =_xlfn.XLOOKUP($B52,[1]Billing!$Q$5:$Q$40,[1]Billing!$Y$5:$Y$40) -> 0 | K101: =_xlfn.XLOOKUP($B52,[1]Billing!$Q$5:$Q$40,[1]Billing!$Z$5:$Z$40) -> 0 | L101: =_xlfn.XLOOKUP($B52,[1]Billing!$Q$5:$Q$40,[1]Billing!$AA$5:$AA$40) -> 0 | M101: =_xlfn.XLOOKUP($B52,[1]Billing!$Q$5:$Q$40,[1]Billing!$AB$5:$AB$40) -> 0 | O101: =G101+H101+I101+J101+K101+L101+M101 -> 1354242 | P101: =_xlfn.XLOOKUP($B52,[1]Billing!$Q$5:$Q$40,[1]Billing!$AD$5:$AD$40) -> 1353710 | Q101: =O101-P101 -> 531.99729 | R101: 10.5 | S101: 13
B102: Sufi Nawaz Sahab | C102: =_xlfn.XLOOKUP($B53,[1]Billing!$Q$5:$Q$40,[1]Billing!$R$5:$R$40) -> 1212967 | D102: =_xlfn.XLOOKUP($B53,[1]Billing!$Q$5:$Q$40,[1]Billing!$S$5:$S$40) -> 1109150.5 | E102: =_xlfn.XLOOKUP($B53,[1]Billing!$Q$5:$Q$40,[1]Billing!$T$5:$T$40) -> 599330.65 | F102: =_xlfn.XLOOKUP($B53,[1]Billing!$Q$5:$Q$40,[1]Billing!$U$5:$U$40) -> 485823.88 | G102: =_xlfn.XLOOKUP($B53,[1]Billing!$Q$5:$Q$40,[1]Billing!$V$5:$V$40) -> 5408917.9 | H102: =_xlfn.XLOOKUP($B53,[1]Billing!$Q$5:$Q$40,[1]Billing!$W$5:$W$40) -> 5829886.6 | I102: =_xlfn.XLOOKUP($B53,[1]Billing!$Q$5:$Q$40,[1]Billing!$X$5:$X$40) -> 0 | J102: =_xlfn.XLOOKUP($B53,[1]Billing!$Q$5:$Q$40,[1]Billing!$Y$5:$Y$40) -> 239959.77 | K102: =_xlfn.XLOOKUP($B53,[1]Billing!$Q$5:$Q$40,[1]Billing!$Z$5:$Z$40) -> 0 | L102: =_xlfn.XLOOKUP($B53,[1]Billing!$Q$5:$Q$40,[1]Billing!$AA$5:$AA$40) -> 0 | M102: =_xlfn.XLOOKUP($B53,[1]Billing!$Q$5:$Q$40,[1]Billing!$AB$5:$AB$40) -> 0 | O102: =G102+H102+I102+J102+K102+L102+M102 -> 11478764 | P102: =_xlfn.XLOOKUP($B53,[1]Billing!$Q$5:$Q$40,[1]Billing!$AD$5:$AD$40) -> 11478764 | Q102: =O102-P102 -> 0.23847842 | R102: 10 | S102: 13
B103: Sajad Khan | C103: =_xlfn.XLOOKUP($B54,[1]Billing!$Q$5:$Q$40,[1]Billing!$R$5:$R$40) -> 1065869 | D103: =_xlfn.XLOOKUP($B54,[1]Billing!$Q$5:$Q$40,[1]Billing!$S$5:$S$40) -> 974642.47 | E103: =_xlfn.XLOOKUP($B54,[1]Billing!$Q$5:$Q$40,[1]Billing!$T$5:$T$40) -> 942295.17 | F103: =_xlfn.XLOOKUP($B54,[1]Billing!$Q$5:$Q$40,[1]Billing!$U$5:$U$40) -> 0 | G103: =_xlfn.XLOOKUP($B54,[1]Billing!$Q$5:$Q$40,[1]Billing!$V$5:$V$40) -> 9422951.7 | H103: =_xlfn.XLOOKUP($B54,[1]Billing!$Q$5:$Q$40,[1]Billing!$W$5:$W$40) -> 0 | I103: =_xlfn.XLOOKUP($B54,[1]Billing!$Q$5:$Q$40,[1]Billing!$X$5:$X$40) -> 71359.729 | J103: =_xlfn.XLOOKUP($B54,[1]Billing!$Q$5:$Q$40,[1]Billing!$Y$5:$Y$40) -> 0 | K103: =_xlfn.XLOOKUP($B54,[1]Billing!$Q$5:$Q$40,[1]Billing!$Z$5:$Z$40) -> 322297 | L103: =_xlfn.XLOOKUP($B54,[1]Billing!$Q$5:$Q$40,[1]Billing!$AA$5:$AA$40) -> 0 | M103: =_xlfn.XLOOKUP($B54,[1]Billing!$Q$5:$Q$40,[1]Billing!$AB$5:$AB$40) -> 0 | O103: =G103+H103+I103+J103+K103+L103+M103 -> 9816608.4 | P103: =_xlfn.XLOOKUP($B54,[1]Billing!$Q$5:$Q$40,[1]Billing!$AD$5:$AD$40) -> 9609871 | Q103: =O103-P103 -> 206737.45 | R103: 10 | S103: 13
B104: Raaz Fabrics | C104: =_xlfn.XLOOKUP($B55,[1]Billing!$Q$5:$Q$40,[1]Billing!$R$5:$R$40) -> 177861 | D104: =_xlfn.XLOOKUP($B55,[1]Billing!$Q$5:$Q$40,[1]Billing!$S$5:$S$40) -> 162638.08 | E104: =_xlfn.XLOOKUP($B55,[1]Billing!$Q$5:$Q$40,[1]Billing!$T$5:$T$40) -> 162638.08 | F104: =_xlfn.XLOOKUP($B55,[1]Billing!$Q$5:$Q$40,[1]Billing!$U$5:$U$40) -> 0 | G104: =_xlfn.XLOOKUP($B55,[1]Billing!$Q$5:$Q$40,[1]Billing!$V$5:$V$40) -> 1626380.8 | H104: =_xlfn.XLOOKUP($B55,[1]Billing!$Q$5:$Q$40,[1]Billing!$W$5:$W$40) -> 0 | I104: =_xlfn.XLOOKUP($B55,[1]Billing!$Q$5:$Q$40,[1]Billing!$X$5:$X$40) -> 0 | J104: =_xlfn.XLOOKUP($B55,[1]Billing!$Q$5:$Q$40,[1]Billing!$Y$5:$Y$40) -> 0 | K104: =_xlfn.XLOOKUP($B55,[1]Billing!$Q$5:$Q$40,[1]Billing!$Z$5:$Z$40) -> 0 | L104: =_xlfn.XLOOKUP($B55,[1]Billing!$Q$5:$Q$40,[1]Billing!$AA$5:$AA$40) -> 0 | M104: =_xlfn.XLOOKUP($B55,[1]Billing!$Q$5:$Q$40,[1]Billing!$AB$5:$AB$40) -> 0 | O104: =G104+H104+I104+J104+K104+L104+M104 -> 1626380.8 | P104: =_xlfn.XLOOKUP($B55,[1]Billing!$Q$5:$Q$40,[1]Billing!$AD$5:$AD$40) -> 1526321 | Q104: =O104-P104 -> 100059.76 | R104: 10 | S104: 13
B105: Azam | C105: =_xlfn.XLOOKUP($B56,[1]Billing!$Q$5:$Q$40,[1]Billing!$R$5:$R$40) -> 749236 | D105: =_xlfn.XLOOKUP($B56,[1]Billing!$Q$5:$Q$40,[1]Billing!$S$5:$S$40) -> 685109.73 | E105: =_xlfn.XLOOKUP($B56,[1]Billing!$Q$5:$Q$40,[1]Billing!$T$5:$T$40) -> 501118.32 | F105: =_xlfn.XLOOKUP($B56,[1]Billing!$Q$5:$Q$40,[1]Billing!$U$5:$U$40) -> 183991.4 | G105: =_xlfn.XLOOKUP($B56,[1]Billing!$Q$5:$Q$40,[1]Billing!$V$5:$V$40) -> 5011183.2 | H105: =_xlfn.XLOOKUP($B56,[1]Billing!$Q$5:$Q$40,[1]Billing!$W$5:$W$40) -> 2391888.3 | I105: =_xlfn.XLOOKUP($B56,[1]Billing!$Q$5:$Q$40,[1]Billing!$X$5:$X$40) -> 0 | J105: =_xlfn.XLOOKUP($B56,[1]Billing!$Q$5:$Q$40,[1]Billing!$Y$5:$Y$40) -> 0 | K105: =_xlfn.XLOOKUP($B56,[1]Billing!$Q$5:$Q$40,[1]Billing!$Z$5:$Z$40) -> 0 | L105: =_xlfn.XLOOKUP($B56,[1]Billing!$Q$5:$Q$40,[1]Billing!$AA$5:$AA$40) -> 0 | M105: =_xlfn.XLOOKUP($B56,[1]Billing!$Q$5:$Q$40,[1]Billing!$AB$5:$AB$40) -> 0 | O105: =G105+H105+I105+J105+K105+L105+M105 -> 7403071.5 | P105: =_xlfn.XLOOKUP($B56,[1]Billing!$Q$5:$Q$40,[1]Billing!$AD$5:$AD$40) -> 7402540 | Q105: =O105-P105 -> 531.50695 | R105: 10 | S105: 13
B106: Ubaidullah | C106: =_xlfn.XLOOKUP($B57,[1]Billing!$Q$5:$Q$40,[1]Billing!$R$5:$R$40) -> 173534 | D106: =_xlfn.XLOOKUP($B57,[1]Billing!$Q$5:$Q$40,[1]Billing!$S$5:$S$40) -> 158681.42 | E106: =_xlfn.XLOOKUP($B57,[1]Billing!$Q$5:$Q$40,[1]Billing!$T$5:$T$40) -> 46132.955 | F106: =_xlfn.XLOOKUP($B57,[1]Billing!$Q$5:$Q$40,[1]Billing!$U$5:$U$40) -> 112548.46 | G106: =_xlfn.XLOOKUP($B57,[1]Billing!$Q$5:$Q$40,[1]Billing!$V$5:$V$40) -> 461329.55 | H106: =_xlfn.XLOOKUP($B57,[1]Billing!$Q$5:$Q$40,[1]Billing!$W$5:$W$40) -> 1448134.6 | I106: =_xlfn.XLOOKUP($B57,[1]Billing!$Q$5:$Q$40,[1]Billing!$X$5:$X$40) -> 0 | J106: =_xlfn.XLOOKUP($B57,[1]Billing!$Q$5:$Q$40,[1]Billing!$Y$5:$Y$40) -> 0 | K106: =_xlfn.XLOOKUP($B57,[1]Billing!$Q$5:$Q$40,[1]Billing!$Z$5:$Z$40) -> 0 | L106: =_xlfn.XLOOKUP($B57,[1]Billing!$Q$5:$Q$40,[1]Billing!$AA$5:$AA$40) -> 0 | M106: =_xlfn.XLOOKUP($B57,[1]Billing!$Q$5:$Q$40,[1]Billing!$AB$5:$AB$40) -> 0 | O106: =G106+H106+I106+J106+K106+L106+M106 -> 1909464.2 | P106: =_xlfn.XLOOKUP($B57,[1]Billing!$Q$5:$Q$40,[1]Billing!$AD$5:$AD$40) -> 1908190 | Q106: =O106-P106 -> 1274.1551 | R106: 10 | S106: 13
B107: Ashraf Zia | C107: =_xlfn.XLOOKUP($B58,[1]Billing!$Q$5:$Q$40,[1]Billing!$R$5:$R$40) -> 23305 | D107: =_xlfn.XLOOKUP($B58,[1]Billing!$Q$5:$Q$40,[1]Billing!$S$5:$S$40) -> 21310.351 | E107: =_xlfn.XLOOKUP($B58,[1]Billing!$Q$5:$Q$40,[1]Billing!$T$5:$T$40) -> 21310.351 | F107: =_xlfn.XLOOKUP($B58,[1]Billing!$Q$5:$Q$40,[1]Billing!$U$5:$U$40) -> 0 | G107: =_xlfn.XLOOKUP($B58,[1]Billing!$Q$5:$Q$40,[1]Billing!$V$5:$V$40) -> 255724.21 | H107: =_xlfn.XLOOKUP($B58,[1]Billing!$Q$5:$Q$40,[1]Billing!$W$5:$W$40) -> 0 | I107: =_xlfn.XLOOKUP($B58,[1]Billing!$Q$5:$Q$40,[1]Billing!$X$5:$X$40) -> 0 | J107: =_xlfn.XLOOKUP($B58,[1]Billing!$Q$5:$Q$40,[1]Billing!$Y$5:$Y$40) -> 0 | K107: =_xlfn.XLOOKUP($B58,[1]Billing!$Q$5:$Q$40,[1]Billing!$Z$5:$Z$40) -> 0 | L107: =_xlfn.XLOOKUP($B58,[1]Billing!$Q$5:$Q$40,[1]Billing!$AA$5:$AA$40) -> 0 | M107: =_xlfn.XLOOKUP($B58,[1]Billing!$Q$5:$Q$40,[1]Billing!$AB$5:$AB$40) -> 0 | O107: =G107+H107+I107+J107+K107+L107+M107 -> 255724.21 | P107: =_xlfn.XLOOKUP($B58,[1]Billing!$Q$5:$Q$40,[1]Billing!$AD$5:$AD$40) -> 130000 | Q107: =O107-P107 -> 125724.21 | R107: 12 | S107: 13
B108: Hafiz Qureshi | C108: =_xlfn.XLOOKUP($B59,[1]Billing!$Q$5:$Q$40,[1]Billing!$R$5:$R$40) -> 454627 | D108: =_xlfn.XLOOKUP($B59,[1]Billing!$Q$5:$Q$40,[1]Billing!$S$5:$S$40) -> 415715.98 | E108: =_xlfn.XLOOKUP($B59,[1]Billing!$Q$5:$Q$40,[1]Billing!$T$5:$T$40) -> 415715.98 | F108: =_xlfn.XLOOKUP($B59,[1]Billing!$Q$5:$Q$40,[1]Billing!$U$5:$U$40) -> 0 | G108: =_xlfn.XLOOKUP($B59,[1]Billing!$Q$5:$Q$40,[1]Billing!$V$5:$V$40) -> 4157159.8 | H108: =_xlfn.XLOOKUP($B59,[1]Billing!$Q$5:$Q$40,[1]Billing!$W$5:$W$40) -> 0 | I108: =_xlfn.XLOOKUP($B59,[1]Billing!$Q$5:$Q$40,[1]Billing!$X$5:$X$40) -> 0 | J108: =_xlfn.XLOOKUP($B59,[1]Billing!$Q$5:$Q$40,[1]Billing!$Y$5:$Y$40) -> 0 | K108: =_xlfn.XLOOKUP($B59,[1]Billing!$Q$5:$Q$40,[1]Billing!$Z$5:$Z$40) -> 0 | L108: =_xlfn.XLOOKUP($B59,[1]Billing!$Q$5:$Q$40,[1]Billing!$AA$5:$AA$40) -> 0 | M108: =_xlfn.XLOOKUP($B59,[1]Billing!$Q$5:$Q$40,[1]Billing!$AB$5:$AB$40) -> 0 | O108: =G108+H108+I108+J108+K108+L108+M108 -> 4157159.8 | P108: =_xlfn.XLOOKUP($B59,[1]Billing!$Q$5:$Q$40,[1]Billing!$AD$5:$AD$40) -> 4146179 | Q108: =O108-P108 -> 10980.839 | R108: 10 | S108: 13
B109: Badshah Fabrics | C109: =_xlfn.XLOOKUP($B60,[1]Billing!$Q$5:$Q$40,[1]Billing!$R$5:$R$40) -> 681314 | D109: =_xlfn.XLOOKUP($B60,[1]Billing!$Q$5:$Q$40,[1]Billing!$S$5:$S$40) -> 623001.1 | E109: =_xlfn.XLOOKUP($B60,[1]Billing!$Q$5:$Q$40,[1]Billing!$T$5:$T$40) -> 481526.15 | F109: =_xlfn.XLOOKUP($B60,[1]Billing!$Q$5:$Q$40,[1]Billing!$U$5:$U$40) -> 141474.95 | G109: =_xlfn.XLOOKUP($B60,[1]Billing!$Q$5:$Q$40,[1]Billing!$V$5:$V$40) -> 4861679.8 | H109: =_xlfn.XLOOKUP($B60,[1]Billing!$Q$5:$Q$40,[1]Billing!$W$5:$W$40) -> 1776019.6 | I109: =_xlfn.XLOOKUP($B60,[1]Billing!$Q$5:$Q$40,[1]Billing!$X$5:$X$40) -> 0 | J109: =_xlfn.XLOOKUP($B60,[1]Billing!$Q$5:$Q$40,[1]Billing!$Y$5:$Y$40) -> 0 | K109: =_xlfn.XLOOKUP($B60,[1]Billing!$Q$5:$Q$40,[1]Billing!$Z$5:$Z$40) -> 0 | L109: =_xlfn.XLOOKUP($B60,[1]Billing!$Q$5:$Q$40,[1]Billing!$AA$5:$AA$40) -> 0 | M109: =_xlfn.XLOOKUP($B60,[1]Billing!$Q$5:$Q$40,[1]Billing!$AB$5:$AB$40) -> 0 | O109: =G109+H109+I109+J109+K109+L109+M109 -> 6637699.3 | P109: =_xlfn.XLOOKUP($B60,[1]Billing!$Q$5:$Q$40,[1]Billing!$AD$5:$AD$40) -> 6545761 | Q109: =O109-P109 -> 91938.342 | R109: 10 | S109: 13
B110: Gauhar Kashif | C110: =_xlfn.XLOOKUP($B61,[1]Billing!$Q$5:$Q$40,[1]Billing!$R$5:$R$40) -> 132768 | D110: =_xlfn.XLOOKUP($B61,[1]Billing!$Q$5:$Q$40,[1]Billing!$S$5:$S$40) -> 121404.54 | E110: =_xlfn.XLOOKUP($B61,[1]Billing!$Q$5:$Q$40,[1]Billing!$T$5:$T$40) -> 121404.54 | F110: =_xlfn.XLOOKUP($B61,[1]Billing!$Q$5:$Q$40,[1]Billing!$U$5:$U$40) -> 0 | G110: =_xlfn.XLOOKUP($B61,[1]Billing!$Q$5:$Q$40,[1]Billing!$V$5:$V$40) -> 1214045.4 | H110: =_xlfn.XLOOKUP($B61,[1]Billing!$Q$5:$Q$40,[1]Billing!$W$5:$W$40) -> 0 | I110: =_xlfn.XLOOKUP($B61,[1]Billing!$Q$5:$Q$40,[1]Billing!$X$5:$X$40) -> 0 | J110: =_xlfn.XLOOKUP($B61,[1]Billing!$Q$5:$Q$40,[1]Billing!$Y$5:$Y$40) -> 0 | K110: =_xlfn.XLOOKUP($B61,[1]Billing!$Q$5:$Q$40,[1]Billing!$Z$5:$Z$40) -> 0 | L110: =_xlfn.XLOOKUP($B61,[1]Billing!$Q$5:$Q$40,[1]Billing!$AA$5:$AA$40) -> 0 | M110: =_xlfn.XLOOKUP($B61,[1]Billing!$Q$5:$Q$40,[1]Billing!$AB$5:$AB$40) -> 0 | O110: =G110+H110+I110+J110+K110+L110+M110 -> 1214045.4 | P110: =_xlfn.XLOOKUP($B61,[1]Billing!$Q$5:$Q$40,[1]Billing!$AD$5:$AD$40) -> 1214045 | Q110: =O110-P110 -> 0.35479151 | R110: 10 | S110: 13
... B117: Salman Zaffar | C117: =_xlfn.XLOOKUP($B68,[1]Billing!$Q$5:$Q$40,[1]Billing!$R$5:$R$40) -> 344332 | D117: =_xlfn.XLOOKUP($B68,[1]Billing!$Q$5:$Q$40,[1]Billing!$S$5:$S$40) -> 314861.01 | E117: =_xlfn.XLOOKUP($B68,[1]Billing!$Q$5:$Q$40,[1]Billing!$T$5:$T$40) -> 72939.832 | F117: =_xlfn.XLOOKUP($B68,[1]Billing!$Q$5:$Q$40,[1]Billing!$U$5:$U$40) -> 31409.108 | G117: =_xlfn.XLOOKUP($B68,[1]Billing!$Q$5:$Q$40,[1]Billing!$V$5:$V$40) -> 729398.32 | H117: =_xlfn.XLOOKUP($B68,[1]Billing!$Q$5:$Q$40,[1]Billing!$W$5:$W$40) -> 408318.4 | I117: =_xlfn.XLOOKUP($B68,[1]Billing!$Q$5:$Q$40,[1]Billing!$X$5:$X$40) -> 0 | J117: =_xlfn.XLOOKUP($B68,[1]Billing!$Q$5:$Q$40,[1]Billing!$Y$5:$Y$40) -> 0 | K117: =_xlfn.XLOOKUP($B68,[1]Billing!$Q$5:$Q$40,[1]Billing!$Z$5:$Z$40) -> 161653.26 | L117: =_xlfn.XLOOKUP($B68,[1]Billing!$Q$5:$Q$40,[1]Billing!$AA$5:$AA$40) -> 1970409.7 | M117: =_xlfn.XLOOKUP($B68,[1]Billing!$Q$5:$Q$40,[1]Billing!$AB$5:$AB$40) -> 0 | O117: =G117+H117+I117+J117+K117+L117+M117 -> 3269779.6 | P117: =_xlfn.XLOOKUP($B68,[1]Billing!$Q$5:$Q$40,[1]Billing!$AD$5:$AD$40) -> 3296025 | Q117: =O117-P117 -> -26245.373 | R117: 10 | S117: 13
B118: Shahid Qasayi | C118: =_xlfn.XLOOKUP($B69,[1]Billing!$Q$5:$Q$40,[1]Billing!$R$5:$R$40) -> 394284 | D118: =_xlfn.XLOOKUP($B69,[1]Billing!$Q$5:$Q$40,[1]Billing!$S$5:$S$40) -> 360537.67 | E118: =_xlfn.XLOOKUP($B69,[1]Billing!$Q$5:$Q$40,[1]Billing!$T$5:$T$40) -> 310998.54 | F118: =_xlfn.XLOOKUP($B69,[1]Billing!$Q$5:$Q$40,[1]Billing!$U$5:$U$40) -> 0 | G118: =_xlfn.XLOOKUP($B69,[1]Billing!$Q$5:$Q$40,[1]Billing!$V$5:$V$40) -> 3109985.4 | H118: =_xlfn.XLOOKUP($B69,[1]Billing!$Q$5:$Q$40,[1]Billing!$W$5:$W$40) -> 0 | I118: =_xlfn.XLOOKUP($B69,[1]Billing!$Q$5:$Q$40,[1]Billing!$X$5:$X$40) -> 0 | J118: =_xlfn.XLOOKUP($B69,[1]Billing!$Q$5:$Q$40,[1]Billing!$Y$5:$Y$40) -> 0 | K118: =_xlfn.XLOOKUP($B69,[1]Billing!$Q$5:$Q$40,[1]Billing!$Z$5:$Z$40) -> 23767.374 | L118: =_xlfn.XLOOKUP($B69,[1]Billing!$Q$5:$Q$40,[1]Billing!$AA$5:$AA$40) -> 523143.75 | M118: =_xlfn.XLOOKUP($B69,[1]Billing!$Q$5:$Q$40,[1]Billing!$AB$5:$AB$40) -> 0 | O118: =G118+H118+I118+J118+K118+L118+M118 -> 3656896.5 | P118: =_xlfn.XLOOKUP($B69,[1]Billing!$Q$5:$Q$40,[1]Billing!$AD$5:$AD$40) -> 3625137 | Q118: =O118-P118 -> 31759.489
B119: Hameed corporation | C119: =_xlfn.XLOOKUP($B70,[1]Billing!$Q$5:$Q$40,[1]Billing!$R$5:$R$40) -> 46404 | D119: =_xlfn.XLOOKUP($B70,[1]Billing!$Q$5:$Q$40,[1]Billing!$S$5:$S$40) -> 42432.334 | E119: =_xlfn.XLOOKUP($B70,[1]Billing!$Q$5:$Q$40,[1]Billing!$T$5:$T$40) -> 42432.334 | F119: =_xlfn.XLOOKUP($B70,[1]Billing!$Q$5:$Q$40,[1]Billing!$U$5:$U$40) -> 0 | G119: =_xlfn.XLOOKUP($B70,[1]Billing!$Q$5:$Q$40,[1]Billing!$V$5:$V$40) -> 424323.34 | H119: =_xlfn.XLOOKUP($B70,[1]Billing!$Q$5:$Q$40,[1]Billing!$W$5:$W$40) -> 0 | I119: =_xlfn.XLOOKUP($B70,[1]Billing!$Q$5:$Q$40,[1]Billing!$X$5:$X$40) -> 0 | J119: =_xlfn.XLOOKUP($B70,[1]Billing!$Q$5:$Q$40,[1]Billing!$Y$5:$Y$40) -> 0 | K119: =_xlfn.XLOOKUP($B70,[1]Billing!$Q$5:$Q$40,[1]Billing!$Z$5:$Z$40) -> 0 | L119: =_xlfn.XLOOKUP($B70,[1]Billing!$Q$5:$Q$40,[1]Billing!$AA$5:$AA$40) -> 0 | M119: =_xlfn.XLOOKUP($B70,[1]Billing!$Q$5:$Q$40,[1]Billing!$AB$5:$AB$40) -> 0 | O119: =G119+H119+I119+J119+K119+L119+M119 -> 424323.34 | P119: =_xlfn.XLOOKUP($B70,[1]Billing!$Q$5:$Q$40,[1]Billing!$AD$5:$AD$40) -> 424323 | Q119: =O119-P119 -> 0.33577176
B120: ibraheem behraam | C120: =_xlfn.XLOOKUP($B71,[1]Billing!$Q$5:$Q$40,[1]Billing!$R$5:$R$40) -> 122386 | D120: =_xlfn.XLOOKUP($B71,[1]Billing!$Q$5:$Q$40,[1]Billing!$S$5:$S$40) -> 111911.12 | E120: =_xlfn.XLOOKUP($B71,[1]Billing!$Q$5:$Q$40,[1]Billing!$T$5:$T$40) -> 0 | F120: =_xlfn.XLOOKUP($B71,[1]Billing!$Q$5:$Q$40,[1]Billing!$U$5:$U$40) -> 111911.12 | G120: =_xlfn.XLOOKUP($B71,[1]Billing!$Q$5:$Q$40,[1]Billing!$V$5:$V$40) -> 0 | H120: =_xlfn.XLOOKUP($B71,[1]Billing!$Q$5:$Q$40,[1]Billing!$W$5:$W$40) -> 1454844.6 | I120: =_xlfn.XLOOKUP($B71,[1]Billing!$Q$5:$Q$40,[1]Billing!$X$5:$X$40) -> 0 | J120: =_xlfn.XLOOKUP($B71,[1]Billing!$Q$5:$Q$40,[1]Billing!$Y$5:$Y$40) -> 0 | K120: =_xlfn.XLOOKUP($B71,[1]Billing!$Q$5:$Q$40,[1]Billing!$Z$5:$Z$40) -> 0 | L120: =_xlfn.XLOOKUP($B71,[1]Billing!$Q$5:$Q$40,[1]Billing!$AA$5:$AA$40) -> 0 | M120: =_xlfn.XLOOKUP($B71,[1]Billing!$Q$5:$Q$40,[1]Billing!$AB$5:$AB$40) -> 0 | O120: =G120+H120+I120+J120+K120+L120+M120 -> 1454844.6 | P120: =_xlfn.XLOOKUP($B71,[1]Billing!$Q$5:$Q$40,[1]Billing!$AD$5:$AD$40) -> 1415500 | Q120: =O120-P120 -> 39344.55
B121: Zia-ullah karachi | C121: =_xlfn.XLOOKUP($B72,[1]Billing!$Q$5:$Q$40,[1]Billing!$R$5:$R$40) -> 13622 | D121: =_xlfn.XLOOKUP($B72,[1]Billing!$Q$5:$Q$40,[1]Billing!$S$5:$S$40) -> 12456.108 | E121: =_xlfn.XLOOKUP($B72,[1]Billing!$Q$5:$Q$40,[1]Billing!$T$5:$T$40) -> 12456.108 | F121: =_xlfn.XLOOKUP($B72,[1]Billing!$Q$5:$Q$40,[1]Billing!$U$5:$U$40) -> 0 | G121: =_xlfn.XLOOKUP($B72,[1]Billing!$Q$5:$Q$40,[1]Billing!$V$5:$V$40) -> 124561.08 | H121: =_xlfn.XLOOKUP($B72,[1]Billing!$Q$5:$Q$40,[1]Billing!$W$5:$W$40) -> 0 | I121: =_xlfn.XLOOKUP($B72,[1]Billing!$Q$5:$Q$40,[1]Billing!$X$5:$X$40) -> 0 | J121: =_xlfn.XLOOKUP($B72,[1]Billing!$Q$5:$Q$40,[1]Billing!$Y$5:$Y$40) -> 0 | K121: =_xlfn.XLOOKUP($B72,[1]Billing!$Q$5:$Q$40,[1]Billing!$Z$5:$Z$40) -> 0 | L121: =_xlfn.XLOOKUP($B72,[1]Billing!$Q$5:$Q$40,[1]Billing!$AA$5:$AA$40) -> 0 | M121: =_xlfn.XLOOKUP($B72,[1]Billing!$Q$5:$Q$40,[1]Billing!$AB$5:$AB$40) -> 0 | O121: =G121+H121+I121+J121+K121+L121+M121 -> 124561.08 | P121: =_xlfn.XLOOKUP($B72,[1]Billing!$Q$5:$Q$40,[1]Billing!$AD$5:$AD$40) -> 124560 | Q121: =O121-P121 -> 1.0826628
B122: ZA | C122: =_xlfn.XLOOKUP($B73,[1]Billing!$Q$5:$Q$40,[1]Billing!$R$5:$R$40) -> 32399 | D122: =_xlfn.XLOOKUP($B73,[1]Billing!$Q$5:$Q$40,[1]Billing!$S$5:$S$40) -> 29626.006 | E122: =_xlfn.XLOOKUP($B73,[1]Billing!$Q$5:$Q$40,[1]Billing!$T$5:$T$40) -> 0 | F122: =_xlfn.XLOOKUP($B73,[1]Billing!$Q$5:$Q$40,[1]Billing!$U$5:$U$40) -> 29626.006 | G122: =_xlfn.XLOOKUP($B73,[1]Billing!$Q$5:$Q$40,[1]Billing!$V$5:$V$40) -> 0 | H122: =_xlfn.XLOOKUP($B73,[1]Billing!$Q$5:$Q$40,[1]Billing!$W$5:$W$40) -> 385138.08 | I122: =_xlfn.XLOOKUP($B73,[1]Billing!$Q$5:$Q$40,[1]Billing!$X$5:$X$40) -> 0 | J122: =_xlfn.XLOOKUP($B73,[1]Billing!$Q$5:$Q$40,[1]Billing!$Y$5:$Y$40) -> 0 | K122: =_xlfn.XLOOKUP($B73,[1]Billing!$Q$5:$Q$40,[1]Billing!$Z$5:$Z$40) -> 0 | L122: =_xlfn.XLOOKUP($B73,[1]Billing!$Q$5:$Q$40,[1]Billing!$AA$5:$AA$40) -> 0 | M122: =_xlfn.XLOOKUP($B73,[1]Billing!$Q$5:$Q$40,[1]Billing!$AB$5:$AB$40) -> 0 | O122: =G122+H122+I122+J122+K122+L122+M122 -> 385138.08 | P122: =_xlfn.XLOOKUP($B73,[1]Billing!$Q$5:$Q$40,[1]Billing!$AD$5:$AD$40) -> 250000 | Q122: =O122-P122 -> 135138.08
...

Sheet Bill Print
I4: Party Names: | J4: {=_xlfn.UNIQUE(Table1[Party Name])} -> BSC
J5: Ejaz Sahab
B6: farhaan ali | J6: Arshad
B7: Description | C7: Rate | D7: gazana | E7: sum | J7: Shehzad Kamoki
B8: Total Gazana/gaz | D8: {=_xlfn.XLOOKUP($B$6,_xlfn.ANCHORARRAY( Billing!R5), INDEX(Billing!S5:S25, _xlfn.SEQUENCE(ROWS(_xlfn.ANCHORARRAY(Billing!$R$5)))), "Not Found")} -> #REF! | J8: Sufi Nawaz Sahab
J9: Sajad Khan
B10: Gazana/meters | D10: {=_xlfn.XLOOKUP($B$6,_xlfn.ANCHORARRAY( Billing!$R$5), INDEX(Billing!T5:T25, _xlfn.SEQUENCE(ROWS(_xlfn.ANCHORARRAY(Billing!$R$5)))), "Not Found")} -> #REF! | J10: Raaz Fabrics
J11: Azam
B12: Total Chamki-crinkle/meters | C12: {=_xlfn.XLOOKUP($B$6,_xlfn.ANCHORARRAY( Billing!$B$49), OFFSET(Billing!R49, 0, 0, ROWS(_xlfn.ANCHORARRAY(Billing!$B$49))), "Not Found")} -> 0 | D12: {=_xlfn.XLOOKUP($B$6,_xlfn.ANCHORARRAY( Billing!$R$5), INDEX(Billing!U5:U25, _xlfn.SEQUENCE(ROWS(_xlfn.ANCHORARRAY(Billing!$R$5)))), "Not Found")} -> #REF! | E12: =Table21[[#This Row],[gazana]]*Table21[[#This Row],[Rate]] -> #REF! | J12: Ubaidullah
J13: Ashraf Zia
B14: Total Super Silky/meters | C14: 13 | D14: {=_xlfn.XLOOKUP($B$6,_xlfn.ANCHORARRAY( Billing!$R$5), INDEX(Billing!V5:V25, _xlfn.SEQUENCE(ROWS(_xlfn.ANCHORARRAY(Billing!$R$5)))), "Not Found")} -> #REF! | E14: =Table21[[#This Row],[gazana]]*Table21[[#This Row],[Rate]] -> #REF! | J14: Hafiz Qureshi
J15: Badshah Fabrics
B16: Total Billing | E16: =E12+E14 -> #REF! | J16: Gauhar Kashif
J17: Amjad 7up
B18: Total Paid | E18: {=_xlfn.XLOOKUP($B$6,_xlfn.ANCHORARRAY( Billing!R5), OFFSET(Billing!AF5, 0, 0, ROWS(_xlfn.ANCHORARRAY(Billing!R5))), "Not Found")} -> 0 | J18: Hazrat Khan
J19: Haseeb Shamsi
B20: Total Balance | E20: {=_xlfn.XLOOKUP($B$6,_xlfn.ANCHORARRAY( Billing!R5), OFFSET(Billing!AG5, 0, 0, ROWS(_xlfn.ANCHORARRAY(Billing!R5))), "Not Found")} -> 1798277.2 | J20: Faizan
J21: Shafique Ansari
J22: Amjad sohail
J23: Salman Zaffar
J24: Shahid Qasayi
J25: Hameed corporation
J26: ibraheem behraam
J27: Zia-ullah karachi
J28: ZA
J29: Ahmad Javaid
J30: Shani Badshah
J31: Rehman Ali
J32: Ahmad Shafique
... J38: Farhaan ali
J39: 0

Sheet Expenses
B1: Expenses
B3: Type | C3: Amount | D3: Description | E3: cost per meter
B4: Wood | C4: =Wood!K6+(1000*810) -> 12772585 | D4: 700*810 | E4: =Table12[[#This Row],[Amount]]/Table1[[#Totals],[tiyar/meters]] -> 5.0177942
B5: Dyes/Chemical | C5: =SUM(Table8[Price])+(301660) -> 2638415 | E5: =Table12[[#This Row],[Amount]]/Table1[[#Totals],[tiyar/meters]] -> 1.0365187
B6: Finish | C6: =SUM(Table2[Price]) -> 1120250 | D6: 60 bags starch 3 bp26 | E6: =Table12[[#This Row],[Amount]]/Table1[[#Totals],[tiyar/meters]] -> 0.4400976
B7: Misc | C7: =SUMIFS(Table14[Debit], Table14[Party],Table12[[#This Row],[Type]]) -> 102080 | E7: =Table12[[#This Row],[Amount]]/Table1[[#Totals],[tiyar/meters]] -> 0.040102801
B8: Electricity | C8: =Electricity!E5 -> 3500011 | E8: =Table12[[#This Row],[Amount]]/Table1[[#Totals],[tiyar/meters]] -> 1.3750024
B9: Salary | C9: =SUMIFS(Table14[Debit], Table14[Party],Table12[[#This Row],[Type]])+SUMIFS(Table14[Debit], Table14[Party],"Advance Salary") -> 5027653 | E9: =Table12[[#This Row],[Amount]]/Table1[[#Totals],[tiyar/meters]] -> 1.9751466
B10: Running Acc | C10: =Table5[[#Totals],[Amount]] -> 245140 | E10: =Table12[[#This Row],[Amount]]/Table1[[#Totals],[tiyar/meters]] -> 0.096304865
B11: Transport | C11: =Table13[[#Totals],[Debit]] -> 126926 | E11: =Table12[[#This Row],[Amount]]/Table1[[#Totals],[tiyar/meters]] -> 0.049863716
